Workbook

Sheet TKP 终端汇总
A1: TKP 2024年NPI报表（1-6月）-按客户终端汇总
A2: 币别:HKD
A3: 终端客户 | B3: 量产前收入 | C3: 量产前成本 | D3: 量产前收益 | E3: 量产后成本 | F3: 项目收益 | G3: 原因分析
A4: BAT | B4: =SUMIF('TKP 项目汇总'!D:D,'TKP 终端汇总'!A:A,'TKP 项目汇总'!M:M) -> 1915072 | C4: =SUMIF('TKP 项目汇总'!$D:$D,'TKP 终端汇总'!$A:$A,'TKP 项目汇总'!$S:$S) -> 28056360 | D4: =SUMIF('TKP 项目汇总'!$D:$D,'TKP 终端汇总'!$A:$A,'TKP 项目汇总'!$T:$T) -> -26141288 | E4: =SUMIF('TKP 项目汇总'!$D:$D,'TKP 终端汇总'!$A:$A,'TKP 项目汇总'!$W:$W) -> 244088.39 | F4: =SUMIF('TKP 项目汇总'!$D:$D,'TKP 终端汇总'!$A:$A,'TKP 项目汇总'!$X:$X) -> -26385376
A5: 合元 | B5: =SUMIF('TKP 项目汇总'!D:D,'TKP 终端汇总'!A:A,'TKP 项目汇总'!M:M) -> 7116459.5 | C5: =SUMIF('TKP 项目汇总'!$D:$D,'TKP 终端汇总'!$A:$A,'TKP 项目汇总'!$S:$S) -> 11709292 | D5: =SUMIF('TKP 项目汇总'!$D:$D,'TKP 终端汇总'!$A:$A,'TKP 项目汇总'!$T:$T) -> -4592833 | E5: =SUMIF('TKP 项目汇总'!$D:$D,'TKP 终端汇总'!$A:$A,'TKP 项目汇总'!$W:$W) -> 123669.23 | F5: =SUMIF('TKP 项目汇总'!$D:$D,'TKP 终端汇总'!$A:$A,'TKP 项目汇总'!$X:$X) -> -4716502.3
A6: Sonos | B6: =SUMIF('TKP 项目汇总'!D:D,'TKP 终端汇总'!A:A,'TKP 项目汇总'!M:M) -> 11023040 | C6: =SUMIF('TKP 项目汇总'!$D:$D,'TKP 终端汇总'!$A:$A,'TKP 项目汇总'!$S:$S) -> 12366751 | D6: =SUMIF('TKP 项目汇总'!$D:$D,'TKP 终端汇总'!$A:$A,'TKP 项目汇总'!$T:$T) -> -1343710.5 | E6: =SUMIF('TKP 项目汇总'!$D:$D,'TKP 终端汇总'!$A:$A,'TKP 项目汇总'!$W:$W) -> 1123794.8 | F6: =SUMIF('TKP 项目汇总'!$D:$D,'TKP 终端汇总'!$A:$A,'TKP 项目汇总'!$X:$X) -> -2467505.3
A7: 通力 | B7: =SUMIF('TKP 项目汇总'!D:D,'TKP 终端汇总'!A:A,'TKP 项目汇总'!M:M) -> 2701479.6 | C7: =SUMIF('TKP 项目汇总'!$D:$D,'TKP 终端汇总'!$A:$A,'TKP 项目汇总'!$S:$S) -> 4972751.8 | D7: =SUMIF('TKP 项目汇总'!$D:$D,'TKP 终端汇总'!$A:$A,'TKP 项目汇总'!$T:$T) -> -2271272.3 | E7: =SUMIF('TKP 项目汇总'!$D:$D,'TKP 终端汇总'!$A:$A,'TKP 项目汇总'!$W:$W) -> 116964.66 | F7: =SUMIF('TKP 项目汇总'!$D:$D,'TKP 终端汇总'!$A:$A,'TKP 项目汇总'!$X:$X) -> -2388236.9
A8: 韶音 | B8: =SUMIF('TKP 项目汇总'!D:D,'TKP 终端汇总'!A:A,'TKP 项目汇总'!M:M) -> 846468.08 | C8: =SUMIF('TKP 项目汇总'!$D:$D,'TKP 终端汇总'!$A:$A,'TKP 项目汇总'!$S:$S) -> 2065434.7 | D8: =SUMIF('TKP 项目汇总'!$D:$D,'TKP 终端汇总'!$A:$A,'TKP 项目汇总'!$T:$T) -> -1218966.6 | E8: =SUMIF('TKP 项目汇总'!$D:$D,'TKP 终端汇总'!$A:$A,'TKP 项目汇总'!$W:$W) -> 324641.65 | F8: =SUMIF('TKP 项目汇总'!$D:$D,'TKP 终端汇总'!$A:$A,'TKP 项目汇总'!$X:$X) -> -1543608.2
A9: Google | B9: =SUMIF('TKP 项目汇总'!D:D,'TKP 终端汇总'!A:A,'TKP 项目汇总'!M:M) -> 4113660.1 | C9: =SUMIF('TKP 项目汇总'!$D:$D,'TKP 终端汇总'!$A:$A,'TKP 项目汇总'!$S:$S) -> 4095308.3 | D9: =SUMIF('TKP 项目汇总'!$D:$D,'TKP 终端汇总'!$A:$A,'TKP 项目汇总'!$T:$T) -> 18351.82 | E9: =SUMIF('TKP 项目汇总'!$D:$D,'TKP 终端汇总'!$A:$A,'TKP 项目汇总'!$W:$W) -> 365605.18 | F9: =SUMIF('TKP 项目汇总'!$D:$D,'TKP 终端汇总'!$A:$A,'TKP 项目汇总'!$X:$X) -> -347253.36
A10: August | B10: =SUMIF('TKP 项目汇总'!D:D,'TKP 终端汇总'!A:A,'TKP 项目汇总'!M:M) -> 768103.15 | C10: =SUMIF('TKP 项目汇总'!$D:$D,'TKP 终端汇总'!$A:$A,'TKP 项目汇总'!$S:$S) -> 1002916.6 | D10: =SUMIF('TKP 项目汇总'!$D:$D,'TKP 终端汇总'!$A:$A,'TKP 项目汇总'!$T:$T) -> -234813.49 | E10: =SUMIF('TKP 项目汇总'!$D:$D,'TKP 终端汇总'!$A:$A,'TKP 项目汇总'!$W:$W) -> 107742.62 | F10: =SUMIF('TKP 项目汇总'!$D:$D,'TKP 终端汇总'!$A:$A,'TKP 项目汇总'!$X:$X) -> -342556.11
A11: AMAZON | B11: =SUMIF('TKP 项目汇总'!D:D,'TKP 终端汇总'!A:A,'TKP 项目汇总'!M:M) -> 0 | C11: =SUMIF('TKP 项目汇总'!$D:$D,'TKP 终端汇总'!$A:$A,'TKP 项目汇总'!$S:$S) -> 232604.77 | D11: =SUMIF('TKP 项目汇总'!$D:$D,'TKP 终端汇总'!$A:$A,'TKP 项目汇总'!$T:$T) -> -232604.77 | E11: =SUMIF('TKP 项目汇总'!$D:$D,'TKP 终端汇总'!$A:$A,'TKP 项目汇总'!$W:$W) -> 80767.77 | F11: =SUMIF('TKP 项目汇总'!$D:$D,'TKP 终端汇总'!$A:$A,'TKP 项目汇总'!$X:$X) -> -313372.54
A12: 索尼电子 | B12: =SUMIF('TKP 项目汇总'!D:D,'TKP 终端汇总'!A:A,'TKP 项目汇总'!M:M) -> 1032298.2 | C12: =SUMIF('TKP 项目汇总'!$D:$D,'TKP 终端汇总'!$A:$A,'TKP 项目汇总'!$S:$S) -> 1329526.2 | D12: =SUMIF('TKP 项目汇总'!$D:$D,'TKP 终端汇总'!$A:$A,'TKP 项目汇总'!$T:$T) -> -297228.05 | E12: =SUMIF('TKP 项目汇总'!$D:$D,'TKP 终端汇总'!$A:$A,'TKP 项目汇总'!$W:$W) -> 0 | F12: =SUMIF('TKP 项目汇总'!$D:$D,'TKP 终端汇总'!$A:$A,'TKP 项目汇总'!$X:$X) -> -297228.05
A13: 歌尔 | B13: =SUMIF('TKP 项目汇总'!D:D,'TKP 终端汇总'!A:A,'TKP 项目汇总'!M:M) -> 48163.01 | C13: =SUMIF('TKP 项目汇总'!$D:$D,'TKP 终端汇总'!$A:$A,'TKP 项目汇总'!$S:$S) -> 327228.73 | D13: =SUMIF('TKP 项目汇总'!$D:$D,'TKP 终端汇总'!$A:$A,'TKP 项目汇总'!$T:$T) -> -279065.72 | E13: =SUMIF('TKP 项目汇总'!$D:$D,'TKP 终端汇总'!$A:$A,'TKP 项目汇总'!$W:$W) -> 1098.26 | F13: =SUMIF('TKP 项目汇总'!$D:$D,'TKP 终端汇总'!$A:$A,'TKP 项目汇总'!$X:$X) -> -280163.98
A14: 影石 | B14: =SUMIF('TKP 项目汇总'!D:D,'TKP 终端汇总'!A:A,'TKP 项目汇总'!M:M) -> 1291063.3 | C14: =SUMIF('TKP 项目汇总'!$D:$D,'TKP 终端汇总'!$A:$A,'TKP 项目汇总'!$S:$S) -> 1379274.3 | D14: =SUMIF('TKP 项目汇总'!$D:$D,'TKP 终端汇总'!$A:$A,'TKP 项目汇总'!$T:$T) -> -88211 | E14: =SUMIF('TKP 项目汇总'!$D:$D,'TKP 终端汇总'!$A:$A,'TKP 项目汇总'!$W:$W) -> 158719.22 | F14: =SUMIF('TKP 项目汇总'!$D:$D,'TKP 终端汇总'!$A:$A,'TKP 项目汇总'!$X:$X) -> -246930.22
A15: 爱立康 | B15: =SUMIF('TKP 项目汇总'!D:D,'TKP 终端汇总'!A:A,'TKP 项目汇总'!M:M) -> 501666.11 | C15: =SUMIF('TKP 项目汇总'!$D:$D,'TKP 终端汇总'!$A:$A,'TKP 项目汇总'!$S:$S) -> 742401.23 | D15: =SUMIF('TKP 项目汇总'!$D:$D,'TKP 终端汇总'!$A:$A,'TKP 项目汇总'!$T:$T) -> -240735.12 | E15: =SUMIF('TKP 项目汇总'!$D:$D,'TKP 终端汇总'!$A:$A,'TKP 项目汇总'!$W:$W) -> 0 | F15: =SUMIF('TKP 项目汇总'!$D:$D,'TKP 终端汇总'!$A:$A,'TKP 项目汇总'!$X:$X) -> -240735.12
... A92: BigScreen | B92: =SUMIF('TKP 项目汇总'!D:D,'TKP 终端汇总'!A:A,'TKP 项目汇总'!M:M) -> 823788.54 | C92: =SUMIF('TKP 项目汇总'!$D:$D,'TKP 终端汇总'!$A:$A,'TKP 项目汇总'!$S:$S) -> 7488.99 | D92: =SUMIF('TKP 项目汇总'!$D:$D,'TKP 终端汇总'!$A:$A,'TKP 项目汇总'!$T:$T) -> 816299.55 | E92: =SUMIF('TKP 项目汇总'!$D:$D,'TKP 终端汇总'!$A:$A,'TKP 项目汇总'!$W:$W) -> 10271.46 | F92: =SUMIF('TKP 项目汇总'!$D:$D,'TKP 终端汇总'!$A:$A,'TKP 项目汇总'!$X:$X) -> 806028.09
A93: 总计： | B93: =SUM(B4:B92) -> 50828982 | C93: =SUM(C4:C92) -> 83937409 | D93: =SUM(D4:D92) -> -33108427 | E93: =SUM(E4:E92) -> 4088386.5 | F93: =SUM(F4:F92) -> -37196814
B94: =B93-'TKP 项目汇总'!M393 -> 0 | C94: =C93-'TKP 项目汇总'!S393 -> 0 | D94: =D93-'TKP 项目汇总'!T393 -> 0 | E94: =E93-'TKP 项目汇总'!W393 -> 0 | F94: =F93-'TKP 项目汇总'!X393 -> 0
A96: TKP 2024年NPI报表（1-6月）-按BU汇总
A97: 币别:HKD
A98: 事业部 | B98: 量产前收入 | C98: 量产前成本 | D98: 量产前收益 | E98: 量产后成本 | F98: 项目收益 | G98: 原因分析
A99: HP1 | B99: ='HP1'!$O$58 -> 8818552.2 | C99: ='HP1'!$U$58 -> 10737954 | D99: =B99-C99 -> -1919401.9 | E99: ='HP1'!$Y$58 -> 161623.03 | F99: =D99-E99 -> -2081025
A100: HP3 | B100: ='HP3'!O55 -> 5800873 | C100: ='HP3'!U55 -> 5328200.8 | D100: =B100-C100 -> 472672.13 | E100: ='HP3'!Y55 -> 106770.27 | F100: =D100-E100 -> 365901.86
A101: HP4 | B101: ='HP4'!O55 -> 8819603.8 | C101: ='HP4'!U55 -> 37052015 | D101: =B101-C101 -> -28232412 | E101: ='HP4'!Y55 -> 354814.42 | F101: =D101-E101 -> -28587226
A102: SD1 | B102: ='SD1'!O91 -> 3805816.1 | C102: ='SD1'!U91 -> 3248089.4 | D102: =B102-C102 -> 557726.74 | E102: ='SD1'!Y91 -> 772244.11 | F102: =D102-E102 -> -214517.37
A103: MDT | B103: =MDT!O10 -> 698609.53 | C103: =MDT!U10 -> 83686.12 | D103: =B103-C103 -> 614923.41 | E103: =MDT!Y10 -> 8087.78 | F103: =D103-E103 -> 606835.63
A104: HCT | B104: =HCT!O34 -> 609552.03 | C104: =HCT!U34 -> 358293.82 | D104: =B104-C104 -> 251258.21 | E104: =HCT!Y34 -> 32984.27 | F104: =D104-E104 -> 218273.94
A105: HZ1 | B105: ='HZ1 '!O91 -> 12687346 | C105: ='HZ1 '!U91 -> 18205147 | D105: =B105-C105 -> -5517801.1 | E105: ='HZ1 '!Y91 -> 2036960.9 | F105: =D105-E105 -> -7554762
A106: HD1 | B106: ='HD1'!O39 -> 2110942 | C106: ='HD1'!U39 -> 1844751.6 | D106: =B106-C106 -> 266190.43 | E106: ='HD1'!Y39 -> 160958.39 | F106: =D106-E106 -> 105232.04
A107: HD2 | B107: ='HD2'!O50 -> 6850217 | C107: ='HD2'!U50 -> 5509725.9 | D107: =B107-C107 -> 1340491.1 | E107: ='HD2'!Y50 -> 242763.85 | F107: =D107-E107 -> 1097727.2
A108: TKTC | B108: =TKTC!O50 -> 627470.58 | C108: =TKTC!U50 -> 899108.08 | D108: =B108-C108 -> -271637.5 | E108: =TKTC!Y50 -> 182444.67 | F108: =D108-E108 -> -454082.17
A109: TKYN | B109: =TKYN!O19 -> 0 | C109: =TKYN!U19 -> 562417.84 | D109: =B109-C109 -> -562417.84 | E109: =TKYN!Y19 -> 28734.78 | F109: =D109-E109 -> -591152.62
A110: PDS | B110: =PDS!O6 -> 0 | C110: =PDS!U6 -> 108019.21 | D110: =B110-C110 -> -108019.21 | E110: =PDS!Y6 -> 0 | F110: =D110-E110 -> -108019.21
A111: 合计 | B111: =SUM(B99:B110) -> 50828982 | C111: =SUM(C99:C110) -> 83937409 | D111: =SUM(D99:D110) -> -33108427 | E111: =SUM(E99:E110) -> 4088386.5 | F111: =SUM(F99:F110) -> -37196814
D112: =D111-'TKP 项目汇总'!T393 -> 0.03999998 | F112: =F111-'TKP 项目汇总'!X393 -> 0.030999996

Sheet TKP 项目汇总
A1: TKP 2024年1-6月NPI报表明细
A2: 币别:HKD
A3: TK项目号 | B3: 项目名称 | C3: 终端客户 | D3: 终端客户名称 | E3: 创建日期 | F3: 量产日期 | G3: NPI预算收入 | H3: 注塑模具收入 | I3: 其他模具收入 | J3: 样板费收入 | K3: 夹治具收入 | L3: 其它杂项收入 | M3: 量产前收入 | N3: 注塑模具成本 | O3: 其他模具成本 | P3: 自费模具摊销 | Q3: 夹治具成本 | R3: 试模成本 | S3: 量产前成本 | T3: 量产前收益 | U3: 量产后夹治具成本 | V3: 量产后打样成本 | W3: 量产后成本 | X3: 项目收益
A4: P440075 | B4: JAMS-0097 | C4: 440 | D4: OTTERBOX | E4: 44698 | F4: 44838 | G4: 15668730 | H4: 0 | I4: 0 | J4: 83983.05 | K4: 0 | L4: 0 | M4: 83983.05 | N4: 0 | O4: 0 | P4: 0 | Q4: 0 | R4: 57554.78 | S4: 57554.78 | T4: 26428.27 | U4: 2003.31 | V4: 0 | W4: 2003.31 | X4: 24424.96 | Y4: =VLOOKUP(D4,'TKP 终端汇总'!A:A,1,0) -> OTTERBOX
A5: P831004 | B5: IO LOCK | C5: C831 | D5: August | E5: 44503 | G5: 1686960 | H5: 730384.2 | I5: 0 | J5: 2962.88 | K5: 0 | L5: 0 | M5: 733347.08 | N5: 747658.93 | O5: 0 | P5: 0 | Q5: 0 | R5: 4282.35 | S5: 751941.28 | T5: -18594.2 | U5: 0 | V5: 47.65 | W5: 47.65 | X5: -18641.85 | Y5: =VLOOKUP(D5,'TKP 终端汇总'!A:A,1,0) -> August
A6: P201010 | B6: 反应杯-16腔六联杯 | C6: C201 | D6: 新产业 | E6: 44616 | F6: 44848 | G6: 5247000 | H6: 576713.82 | I6: 0 | J6: 0 | K6: 0 | L6: 0 | M6: 576713.82 | N6: 0 | O6: 0 | P6: 0 | Q6: 0 | R6: 0 | S6: 0 | T6: 576713.82 | U6: 0 | V6: 2530.34 | W6: 2530.34 | X6: 574183.48 | Y6: =VLOOKUP(D6,'TKP 终端汇总'!A:A,1,0) -> 新产业
A7: P440074 | B7: JAMS-0277 | C7: 440 | D7: OTTERBOX | E7: 44698 | F7: 44826 | G7: 0 | H7: 0 | I7: 0 | J7: 0 | K7: 0 | L7: 0 | M7: 0 | N7: 0 | O7: 0 | P7: 0 | Q7: 0 | R7: 0 | S7: 0 | T7: 0 | U7: 0 | V7: 0 | W7: 0 | X7: 0 | Y7: =VLOOKUP(D7,'TKP 终端汇总'!A:A,1,0) -> OTTERBOX
A8: P440076 | B8: JAMS-0085 | C8: 440 | D8: OTTERBOX | E8: 44698 | F8: 44830 | G8: 7643856 | H8: 0 | I8: 0 | J8: 0 | K8: 0 | L8: 0 | M8: 0 | N8: 0 | O8: 0 | P8: 0 | Q8: 1900.51 | R8: 0 | S8: 1900.51 | T8: -1900.51 | U8: 34953.85 | V8: 0 | W8: 34953.85 | X8: -36854.36 | Y8: =VLOOKUP(D8,'TKP 终端汇总'!A:A,1,0) -> OTTERBOX
A9: P440072 | B9: JAMS-0193 | C9: 440 | D9: OTTERBOX | E9: 44698 | G9: 0 | H9: 0 | I9: 0 | J9: 0 | K9: 0 | L9: 0 | M9: 0 | N9: 0 | O9: 0 | P9: 0 | Q9: 0 | R9: 0 | S9: 0 | T9: 0 | U9: 0 | V9: 0 | W9: 0 | X9: 0 | Y9: =VLOOKUP(D9,'TKP 终端汇总'!A:A,1,0) -> OTTERBOX
A10: P440080 | B10: JAMS-0041 | C10: 440 | D10: OTTERBOX | E10: 44699 | F10: 44830 | G10: 0 | H10: 0 | I10: 0 | J10: 0 | K10: 0 | L10: 0 | M10: 0 | N10: 0 | O10: 0 | P10: 0 | Q10: 0 | R10: 0 | S10: 0 | T10: 0 | U10: 0 | V10: 0 | W10: 0 | X10: 0 | Y10: =VLOOKUP(D10,'TKP 终端汇总'!A:A,1,0) -> OTTERBOX
A11: P440073 | B11: JAMS-0227 | C11: 440 | D11: OTTERBOX | E11: 44698 | F11: 44826 | G11: 0 | H11: 0 | I11: 0 | J11: 0 | K11: 0 | L11: 0 | M11: 0 | N11: 0 | O11: 0 | P11: 0 | Q11: 0 | R11: -9156.37 | S11: -9156.37 | T11: 9156.37 | U11: 0 | V11: 0 | W11: 0 | X11: 9156.37 | Y11: =VLOOKUP(D11,'TKP 终端汇总'!A:A,1,0) -> OTTERBOX
A12: P833002 | B12: 眼部植入T型管 | C12: C833 | D12: 润视 | E12: 44427 | G12: 93305.3 | H12: 0 | I12: 0 | J12: 0 | K12: 0 | L12: 0 | M12: 0 | N12: 2923.87 | O12: 0 | P12: 0 | Q12: 0 | R12: 0 | S12: 2923.87 | T12: -2923.87 | U12: 0 | V12: 0 | W12: 0 | X12: -2923.87 | Y12: =VLOOKUP(D12,'TKP 终端汇总'!A:A,1,0) -> 润视
A13: P330040 | B13: SAMWISE | C13: 330 | D13: GN | E13: 44482 | G13: 19323850 | H13: 178849 | I13: 0 | J13: 13557.21 | K13: 0 | L13: 0 | M13: 192406.21 | N13: 106233.68 | O13: 0 | P13: 9788.82 | Q13: 0 | R13: 10150.58 | S13: 126173.08 | T13: 66233.13 | U13: 2079.44 | V13: 425.67 | W13: 2505.11 | X13: 63728.02 | Y13: =VLOOKUP(D13,'TKP 终端汇总'!A:A,1,0) -> GN
A14: P805023 | B14: KFC | C14: C805 | D14: 合元 | E14: 44461 | G14: 136000 | H14: 0 | I14: 0 | J14: 0 | K14: 0 | L14: 0 | M14: 0 | N14: 0 | O14: 0 | P14: 308.58 | Q14: 0 | R14: 0 | S14: 308.58 | T14: -308.58 | U14: 0 | V14: 0 | W14: 0 | X14: -308.58 | Y14: =VLOOKUP(D14,'TKP 终端汇总'!A:A,1,0) -> 合元
A15: P863001 | B15: WTH13 | C15: C863 | D15: Stripe | E15: 44628 | G15: 15365460 | H15: 0 | I15: 0 | J15: 4657.88 | K15: 4686 | L15: 0 | M15: 9343.88 | N15: 0 | O15: 0 | P15: 185333.27 | Q15: 0 | R15: 2749.9 | S15: 188083.17 | T15: -178739.29 | U15: 369.77 | V15: 10195.97 | W15: 10565.74 | X15: -189305.03 | Y15: =VLOOKUP(D15,'TKP 终端汇总'!A:A,1,0) -> Stripe
A16: P805024 | B16: PD2 | C16: C805 | D16: 合元 | E16: 44558 | G16: 0 | H16: 0 | I16: 0 | J16: 0 | K16: 0 | L16: 0 | M16: 0 | N16: 0 | O16: 0 | P16: 0 | Q16: 0 | R16: 0 | S16: 0 | T16: 0 | U16: 0 | V16: 0 | W16: 0 | X16: 0 | Y16: =VLOOKUP(D16,'TKP 终端汇总'!A:A,1,0) -> 合元
A17: P857001 | B17: AUDIGO INTRO | C17: C857 | D17: Audigo | E17: 44461 | G17: 1900000 | H17: 0 | I17: 0 | J17: 0 | K17: 0 | L17: 0 | M17: 0 | N17: 0 | O17: 0 | P17: 0 | Q17: 0 | R17: 0 | S17: 0 | T17: 0 | U17: 0 | V17: 12178.5 | W17: 12178.5 | X17: -12178.5 | Y17: =VLOOKUP(D17,'TKP 终端汇总'!A:A,1,0) -> Audigo
A18: P330041 | B18: WILLOW | C18: 330 | D18: GN | E18: 44487 | G18: 50367000 | H18: 43635.9 | I18: 0 | J18: 0 | K18: 0 | L18: 0 | M18: 43635.9 | N18: 42091.21 | O18: 0 | P18: 21652.58 | Q18: 20047.54 | R18: 0 | S18: 83791.33 | T18: -40155.43 | U18: 0 | V18: 2116.79 | W18: 2116.79 | X18: -42272.22 | Y18: =VLOOKUP(D18,'TKP 终端汇总'!A:A,1,0) -> GN
A19: P360022 | B19: C9 | C19: 360 | D19: Google | E19: 44638 | G19: 2420000 | H19: 0 | I19: 0 | J19: 0 | K19: 0 | L19: 0 | M19: 0 | N19: 0 | O19: 0 | P19: 868.98 | Q19: 0 | R19: 0 | S19: 868.98 | T19: -868.98 | U19: 0 | V19: 0 | W19: 0 | X19: -868.98 | Y19: =VLOOKUP(D19,'TKP 终端汇总'!A:A,1,0) -> Google
A20: P360023 | B20: ZERO DRAFT ADAPTOR | C20: 360 | D20: Google | E20: 44657 | G20: 836000 | H20: 0 | I20: 0 | J20: 0 | K20: 0 | L20: 0 | M20: 0 | N20: 0 | O20: 0 | P20: 2484.52 | Q20: 0 | R20: 0 | S20: 2484.52 | T20: -2484.52 | U20: 0 | V20: 0 | W20: 0 | X20: -2484.52 | Y20: =VLOOKUP(D20,'TKP 终端汇总'!A:A,1,0) -> Google
A21: P831005 | B21: 400 SERIES | C21: C831 | D21: August | E21: 44607 | G21: 4711014 | H21: 0 | I21: 0 | J21: 0 | K21: 0 | L21: 0 | M21: 0 | N21: 190.93 | O21: 0 | P21: 6982.16 | Q21: 2836.66 | R21: 5618.34 | S21: 15628.09 | T21: -15628.09 | U21: 12036.72 | V21: 62837.67 | W21: 74874.39 | X21: -90502.48 | Y21: =VLOOKUP(D21,'TKP 终端汇总'!A:A,1,0) -> August
A22: P805027 | B22: COROLLA | C22: C805 | D22: 合元 | E22: 44677 | G22: 20095000 | H22: 205248.64 | I22: 0 | J22: 0 | K22: 0 | L22: 0 | M22: 205248.64 | N22: 25122.16 | O22: 0 | P22: 37023.95 | Q22: 0 | R22: 0 | S22: 62146.11 | T22: 143102.53 | U22: 0 | V22: 40.42 | W22: 40.42 | X22: 143062.11 | Y22: =VLOOKUP(D22,'TKP 终端汇总'!A:A,1,0) -> 合元
A23: P862001 | B23: PSC56一体机 | C23: C862 | D23: 影石 | E23: 44606 | G23: 10261764 | H23: 81135.91 | I23: 0 | J23: 15261 | K23: 0 | L23: 0 | M23: 96396.91 | N23: 19288.38 | O23: 0 | P23: 10491.48 | Q23: 25292.97 | R23: 0 | S23: 55072.83 | T23: 41324.08 | U23: 0 | V23: 107227.17 | W23: 107227.17 | X23: -65903.09 | Y23: =VLOOKUP(D23,'TKP 终端汇总'!A:A,1,0) -> 影石
A24: P860002 | B24: SKELLIG | C24: C860 | D24: 通力 | E24: 44634 | G24: 0 | H24: 0 | I24: 0 | J24: 0 | K24: 0 | L24: 0 | M24: 0 | N24: 0 | O24: 0 | P24: 0 | Q24: 0 | R24: 0 | S24: 0 | T24: 0 | U24: 0 | V24: 0 | W24: 0 | X24: 0 | Y24: =VLOOKUP(D24,'TKP 终端汇总'!A:A,1,0) -> 通力
A25: P330042 | B25: PILLOW | C25: 330 | D25: GN | E25: 44496 | G25: 7104600 | H25: 0 | I25: 0 | J25: 0 | K25: 0 | L25: 0 | M25: 0 | N25: 0 | O25: 0 | P25: 1845.53 | Q25: 0 | R25: 0 | S25: 1845.53 | T25: -1845.53 | U25: 0 | V25: 289.66 | W25: 289.66 | X25: -2135.19 | Y25: =VLOOKUP(D25,'TKP 终端汇总'!A:A,1,0) -> GN
A26: P866002 | B26: F02 | C26: C866 | D26: Meta | E26: 44691 | G26: 18102000 | H26: 0 | I26: 0 | J26: 0 | K26: 0 | L26: 0 | M26: 0 | N26: 0 | O26: 0 | P26: 0 | Q26: 0 | R26: 0 | S26: 0 | T26: 0 | U26: 0 | V26: 9714.13 | W26: 9714.13 | X26: -9714.13 | Y26: =VLOOKUP(D26,'TKP 终端汇总'!A:A,1,0) -> Meta
A27: P805022 | B27: HW42410 | C27: C805 | D27: 合元 | E27: 44456 | G27: 874800 | H27: 10119.23 | I27: 0 | J27: 0 | K27: 0 | L27: 0 | M27: 10119.23 | N27: 0 | O27: 0 | P27: 0 | Q27: 0 | R27: 0 | S27: 0 | T27: 10119.23 | U27: 0 | V27: 0 | W27: 0 | X27: 10119.23 | Y27: =VLOOKUP(D27,'TKP 终端汇总'!A:A,1,0) -> 合元
A28: P438045 | B28: OSAKA | C28: 438 | D28: PHILIPS | E28: 44516 | G28: 7342600 | H28: 0 | I28: 0 | J28: 120388.34 | K28: 0 | L28: 0 | M28: 120388.34 | N28: 0 | O28: 0 | P28: 0 | Q28: 0 | R28: 0 | S28: 0 | T28: 120388.34 | U28: 0 | V28: 3166.03 | W28: 3166.03 | X28: 117222.31 | Y28: =VLOOKUP(D28,'TKP 终端汇总'!A:A,1,0) -> PHILIPS
A29: P866003 | B29: F03 | C29: C866 | D29: Meta | E29: 44700 | G29: 0 | H29: 0 | I29: 0 | J29: 0 | K29: 0 | L29: 0 | M29: 0 | N29: 0 | O29: 0 | P29: 0 | Q29: 0 | R29: 0 | S29: 0 | T29: 0 | U29: 0 | V29: 0 | W29: 0 | X29: 0 | Y29: =VLOOKUP(D29,'TKP 终端汇总'!A:A,1,0) -> Meta
A30: P438044 | B30: ZETA | C30: 438 | D30: PHILIPS | E30: 44442 | G30: 660000 | H30: 0 | I30: 0 | J30: 41007.48 | K30: 172.38 | L30: 0 | M30: 41179.86 | N30: 5698.39 | O30: 0 | P30: 6663.15 | Q30: 0 | R30: 34528.65 | S30: 46890.19 | T30: -5710.33 | U30: 0 | V30: 53736.09 | W30: 53736.09 | X30: -59446.42 | Y30: =VLOOKUP(D30,'TKP 终端汇总'!A:A,1,0) -> PHILIPS
A31: P440071 | B31: TECHDEV 2022 | C31: 440 | D31: OTTERBOX | E31: 44623 | G31: 0 | H31: 0 | I31: 0 | J31: 0 | K31: 0 | L31: 0 | M31: 0 | N31: 0 | O31: 0 | P31: 0 | Q31: 0 | R31: 0 | S31: 0 | T31: 0 | U31: 0 | V31: 0 | W31: 0 | X31: 0 | Y31: =VLOOKUP(D31,'TKP 终端汇总'!A:A,1,0) -> OTTERBOX
A32: P821003 | B32: S3 MOUNT | C32: C821 | D32: Square | E32: 44480 | G32: 13080000 | H32: 0 | I32: 0 | J32: 0 | K32: 0 | L32: 0 | M32: 0 | N32: 0 | O32: 0 | P32: 9094.98 | Q32: 0 | R32: 0 | S32: 9094.98 | T32: -9094.98 | U32: 0 | V32: 0 | W32: 0 | X32: -9094.98 | Y32: =VLOOKUP(D32,'TKP 终端汇总'!A:A,1,0) -> Square
A33: P438048 | B33: GAEA 1 | C33: 438 | D33: PHILIPS | E33: 44677 | G33: 0 | H33: 0 | I33: 0 | J33: 0 | K33: 0 | L33: 0 | M33: 0 | N33: 0 | O33: 0 | P33: 0 | Q33: 0 | R33: 0 | S33: 0 | T33: 0 | U33: 0 | V33: 0 | W33: 0 | X33: 0 | Y33: =VLOOKUP(D33,'TKP 终端汇总'!A:A,1,0) -> PHILIPS
A34: P438049 | B34: CAIRO | C34: 438 | D34: PHILIPS | E34: 44706 | G34: 25730568 | H34: 0 | I34: 0 | J34: 315522.76 | K34: 0 | L34: 0 | M34: 315522.76 | N34: 0 | O34: 0 | P34: 2576.15 | Q34: 0 | R34: 48234.58 | S34: 50810.73 | T34: 264712.03 | U34: 0 | V34: 0 | W34: 0 | X34: 264712.03 | Y34: =VLOOKUP(D34,'TKP 终端汇总'!A:A,1,0) -> PHILIPS
A35: P805026 | B35: PLUZE 1.5 | C35: C805 | D35: 合元 | E35: 44670 | G35: 26807280 | H35: 0 | I35: 0 | J35: 76914.16 | K35: 0 | L35: 0 | M35: 76914.16 | N35: 45349.59 | O35: 0 | P35: 4167.69 | Q35: 3053.06 | R35: 614.57 | S35: 53184.91 | T35: 23729.25 | U35: 0 | V35: 7287.47 | W35: 7287.47 | X35: 16441.78 | Y35: =VLOOKUP(D35,'TKP 终端汇总'!A:A,1,0) -> 合元
A36: P866001 | B36: F01 | C36: C866 | D36: Meta | E36: 44674 | G36: 2220000 | H36: 0 | I36: 0 | J36: 0 | K36: 0 | L36: 0 | M36: 0 | N36: 0 | O36: 0 | P36: 0 | Q36: 3851.82 | R36: 0 | S36: 3851.82 | T36: -3851.82 | U36: 0 | V36: 0 | W36: 0 | X36: -3851.82 | Y36: =VLOOKUP(D36,'TKP 终端汇总'!A:A,1,0) -> Meta
A37: P861002 | B37: SQUARE | C37: C861 | D37: 合元 | E37: 44623 | G37: 13134000 | H37: 295939.9 | I37: 0 | J37: 0 | K37: 0 | L37: 0 | M37: 295939.9 | N37: 149728.26 | O37: 0 | P37: 3148.49 | Q37: 0 | R37: 0 | S37: 152876.75 | T37: 143063.15 | U37: 2711.19 | V37: 4644.01 | W37: 7355.2 | X37: 135707.95 | Y37: =VLOOKUP(D37,'TKP 终端汇总'!A:A,1,0) -> 合元
A38: P824006 | B38: MD2.0 | C38: C824 | D38: BAT | E38: 44729 | G38: 4796000 | H38: 0 | I38: 0 | J38: 0 | K38: 0 | L38: 0 | M38: 0 | N38: 0 | O38: 0 | P38: 21775.83 | Q38: 0 | R38: 0 | S38: 21775.83 | T38: -21775.83 | U38: 0 | V38: 0 | W38: 0 | X38: -21775.83 | Y38: =VLOOKUP(D38,'TKP 终端汇总'!A:A,1,0) -> BAT
A39: P805025 | B39: MOTO | C39: C805 | D39: 合元 | E39: 44652 | G39: 55264500 | H39: 1262215.6 | I39: 0 | J39: 0 | K39: 0 | L39: 0 | M39: 1262215.6 | N39: 3053703 | O39: 0 | P39: 514608.27 | Q39: 0 | R39: 3052.5 | S39: 3571363.8 | T39: -2309148.2 | U39: 0 | V39: 442.38 | W39: 442.38 | X39: -2309590.6 | Y39: =VLOOKUP(D39,'TKP 终端汇总'!A:A,1,0) -> 合元
A40: P815005 | B40: URANUS | C40: C815 | D40: 问问 | E40: 44629 | G40: 5427000 | H40: 0 | I40: 0 | J40: 0 | K40: 0 | L40: 0 | M40: 0 | N40: 2815.22 | O40: 0 | P40: 8093.37 | Q40: 0 | R40: 0 | S40: 10908.59 | T40: -10908.59 | U40: 2291.14 | V40: 141.25 | W40: 2432.39 | X40: -13340.98 | Y40: =VLOOKUP(D40,'TKP 终端汇总'!A:A,1,0) -> 问问
A41: P824004 | B41: EPODS3 | C41: C824 | D41: BAT | E41: 44543 | G41: 52956600 | H41: 130045.96 | I41: 0 | J41: 224867.61 | K41: 0 | L41: 0 | M41: 354913.57 | N41: 5469595.1 | O41: 0 | P41: 184235.24 | Q41: 0 | R41: -2361.51 | S41: 5651468.8 | T41: -5296555.3 | U41: 35385.36 | V41: 33086.97 | W41: 68472.33 | X41: -5365027.6 | Y41: =VLOOKUP(D41,'TKP 终端汇总'!A:A,1,0) -> BAT
A42: P831003 | B42: NEST 1.5 | C42: C831 | D42: August | E42: 44411 | G42: 8056400 | H42: 0 | I42: 0 | J42: 0 | K42: 0 | L42: 0 | M42: 0 | N42: 0 | O42: 0 | P42: 19335.68 | Q42: 0 | R42: 0 | S42: 19335.68 | T42: -19335.68 | U42: 0 | V42: 0 | W42: 0 | X42: -19335.68 | Y42: =VLOOKUP(D42,'TKP 终端汇总'!A:A,1,0) -> August
A43: P208007 | B43: WHARF左右耳挂 | C43: C208 | D43: 韶音 | E43: 44613 | G43: 968000 | H43: 0 | I43: 0 | J43: 0 | K43: 0 | L43: 0 | M43: 0 | N43: 0 | O43: 0 | P43: 19124.08 | Q43: 0 | R43: 2464.48 | S43: 21588.56 | T43: -21588.56 | U43: 0 | V43: 0 | W43: 0 | X43: -21588.56 | Y43: =VLOOKUP(D43,'TKP 终端汇总'!A:A,1,0) -> 韶音
A44: P208008 | B44: PARIS | C44: C208 | D44: 韶音 | E44: 44628 | G44: 3825000 | H44: 7055.03 | I44: 0 | J44: 0 | K44: 0 | L44: 0 | M44: 7055.03 | N44: 0 | O44: 0 | P44: 5660.3 | Q44: 0 | R44: 0 | S44: 5660.3 | T44: 1394.73 | U44: 0 | V44: 275.41 | W44: 275.41 | X44: 1119.32 | Y44: =VLOOKUP(D44,'TKP 终端汇总'!A:A,1,0) -> 韶音
A45: P818002 | B45: HDT666 | C45: C818 | D45: 美律 | E45: 44757 | G45: 21578100 | H45: 23064.6 | I45: 0 | J45: 1762.11 | K45: 0 | L45: 0 | M45: 24826.71 | N45: 18546.06 | O45: 0 | P45: 36388.43 | Q45: 41718.65 | R45: 15796.86 | S45: 112450 | T45: -87623.29 | U45: 3174.29 | V45: 26735.29 | W45: 29909.58 | X45: -117532.87 | Y45: =VLOOKUP(D45,'TKP 终端汇总'!A:A,1,0) -> 美律
A46: P360024 | B46: NTI PHONE CASE | C46: 360 | D46: Google | E46: 44722 | G46: 0 | H46: 0 | I46: 0 | J46: 0 | K46: 0 | L46: 0 | M46: 0 | N46: 0 | O46: 0 | P46: 0 | Q46: 0 | R46: 0 | S46: 0 | T46: 0 | U46: 0 | V46: 0 | W46: 0 | X46: 0 | Y46: =VLOOKUP(D46,'TKP 终端汇总'!A:A,1,0) -> Google
A47: P440078 | B47: JAMS-0262 | C47: 440 | D47: OTTERBOX | E47: 44698 | G47: 0 | H47: 0 | I47: 0 | J47: 0 | K47: 0 | L47: 0 | M47: 0 | N47: 0 | O47: 0 | P47: 0 | Q47: 0 | R47: 0 | S47: 0 | T47: 0 | U47: 0 | V47: 0 | W47: 0 | X47: 0 | Y47: =VLOOKUP(D47,'TKP 终端汇总'!A:A,1,0) -> OTTERBOX
A48: P833001 | B48: 泪点塞 | C48: C833 | D48: 润视 | E48: 44279 | G48: 0 | H48: 0 | I48: 0 | J48: 0 | K48: 0 | L48: 0 | M48: 0 | N48: 0 | O48: 0 | P48: 0 | Q48: 0 | R48: 0 | S48: 0 | T48: 0 | U48: 0 | V48: 0 | W48: 0 | X48: 0 | Y48: =VLOOKUP(D48,'TKP 终端汇总'!A:A,1,0) -> 润视
A49: P832001 | B49: 照明透镜 | C49: C832 | D49: 元晖 | E49: 44279 | G49: 176000 | H49: 0 | I49: 0 | J49: 0 | K49: 0 | L49: 0 | M49: 0 | N49: 1525.79 | O49: 0 | P49: 0 | Q49: 0 | R49: 0 | S49: 1525.79 | T49: -1525.79 | U49: 0 | V49: 163.1 | W49: 163.1 | X49: -1688.89 | Y49: =VLOOKUP(D49,'TKP 终端汇总'!A:A,1,0) -> 元晖
A50: P017005 | B50: SILBERSPITZ | C50: C017 | D50: Sensirion | E50: 44326 | F50: 44337 | G50: 3506250 | H50: 23732.47 | I50: 0 | J50: 0 | K50: 0 | L50: 0 | M50: 23732.47 | N50: 7530.59 | O50: 0 | P50: 0 | Q50: 0 | R50: 2884.97 | S50: 10415.56 | T50: 13316.91 | U50: 0 | V50: 2148.54 | W50: 2148.54 | X50: 11168.37 | Y50: =VLOOKUP(D50,'TKP 终端汇总'!A:A,1,0) -> Sensirion
A51: P024106 | B51: REVLON | C51: C024 | D51: POLYCOM | E51: 44245 | F51: 44271 | G51: 78450090 | H51: 0 | I51: 0 | J51: 68784 | K51: 0 | L51: 0 | M51: 68784 | N51: 479.07 | O51: 0 | P51: 0 | Q51: 0 | R51: 726.96 | S51: 1206.03 | T51: 67577.97 | U51: 9576.88 | V51: 10136.72 | W51: 19713.6 | X51: 47864.37 | Y51: =VLOOKUP(D51,'TKP 终端汇总'!A:A,1,0) -> POLYCOM
A52: P024108 | B52: REVLON3 | C52: C024 | D52: POLYCOM | E52: 44314 | F52: 44364 | G52: 36811500 | H52: 0 | I52: 0 | J52: 0 | K52: 0 | L52: 0 | M52: 0 | N52: 343.3 | O52: 0 | P52: 0 | Q52: 0 | R52: 0 | S52: 343.3 | T52: -343.3 | U52: 11053.36 | V52: 10550.16 | W52: 21603.52 | X52: -21946.82 | Y52: =VLOOKUP(D52,'TKP 终端汇总'!A:A,1,0) -> POLYCOM
A53: P024109 | B53: LARK | C53: C024 | D53: POLYCOM | E53: 44411 | F53: 41820 | G53: 2250775 | H53: 0 | I53: 0 | J53: 0 | K53: 0 | L53: 0 | M53: 0 | N53: 0 | O53: 0 | P53: 0 | Q53: 0 | R53: 1617.5 | S53: 1617.5 | T53: -1617.5 | U53: 0 | V53: 0 | W53: 0 | X53: -1617.5 | Y53: =VLOOKUP(D53,'TKP 终端汇总'!A:A,1,0) -> POLYCOM
A54: P024110 | B54: ASGARD30 | C54: C024 | D54: POLYCOM | E54: 44420 | F54: 44433 | G54: 4502100 | H54: 0 | I54: 0 | J54: 0 | K54: 0 | L54: 0 | M54: 0 | N54: 0 | O54: 0 | P54: 0 | Q54: 0 | R54: 0 | S54: 0 | T54: 0 | U54: 0 | V54: 2821.83 | W54: 2821.83 | X54: -2821.83 | Y54: =VLOOKUP(D54,'TKP 终端汇总'!A:A,1,0) -> POLYCOM
A55: P201009 | B55: 新产业单孔反应杯 | C55: C201 | D55: 新产业 | E55: 44226 | F55: 44195 | G55: 52313745 | H55: 0 | I55: 0 | J55: 0 | K55: 117776.09 | L55: 0 | M55: 117776.09 | N55: 26308.36 | O55: 0 | P55: 6051.19 | Q55: 0 | R55: 19372.84 | S55: 51732.39 | T55: 66043.7 | U55: 0 | V55: 5347.42 | W55: 5347.42 | X55: 60696.28 | Y55: =VLOOKUP(D55,'TKP 终端汇总'!A:A,1,0) -> 新产业
A56: P207004 | B56: JF-139 | C56: 207 | D56: 骏丰 | E56: 44226 | F56: 42198 | G56: 0 | H56: 0 | I56: 0 | J56: 283.56 | K56: 0 | L56: 0 | M56: 283.56 | N56: 2144.17 | O56: 0 | P56: 0 | Q56: 0 | R56: 0 | S56: 2144.17 | T56: -1860.61 | U56: 0 | V56: 8688.55 | W56: 8688.55 | X56: -10549.16 | Y56: =VLOOKUP(D56,'TKP 终端汇总'!A:A,1,0) -> 骏丰
A57: P208003 | B57: VIE | C57: C208 | D57: 韶音 | E57: 44226 | F57: 44223 | G57: 9839800 | H57: 40021.57 | I57: 0 | J57: 0 | K57: 0 | L57: 0 | M57: 40021.57 | N57: 40373.18 | O57: 0 | P57: 21366.23 | Q57: 0 | R57: 0 | S57: 61739.41 | T57: -21717.84 | U57: 1525.79 | V57: 95376.65 | W57: 96902.44 | X57: -118620.28 | Y57: =VLOOKUP(D57,'TKP 终端汇总'!A:A,1,0) -> 韶音
A58: P208004 | B58: TT0 | C58: C208 | D58: 韶音 | E58: 44306 | F58: 44403 | G58: 1058000 | H58: 0 | I58: 0 | J58: -3.24 | K58: 0 | L58: 0 | M58: -3.24 | N58: 0 | O58: 0 | P58: 0 | Q58: 0 | R58: 0 | S58: 0 | T58: -3.24 | U58: 0 | V58: 0 | W58: 0 | X58: -3.24 | Y58: =VLOOKUP(D58,'TKP 终端汇总'!A:A,1,0) -> 韶音
A59: P404001 | B59: TBD | C59: 404 | D59: Google | E59: 44226 | F59: 42198 | G59: 462000 | H59: 0 | I59: 0 | J59: 0 | K59: 0 | L59: 0 | M59: 0 | N59: 60554.25 | O59: 0 | P59: 0 | Q59: 0 | R59: 0 | S59: 60554.25 | T59: -60554.25 | U59: 0 | V59: 1428.43 | W59: 1428.43 | X59: -61982.68 | Y59: =VLOOKUP(D59,'TKP 终端汇总'!A:A,1,0) -> Google
A60: P404006 | B60: D3 | C60: 404 | D60: Google | E60: 44226 | F60: 42657 | G60: 0 | H60: 0 | I60: 0 | J60: 0 | K60: 0 | L60: 0 | M60: 0 | N60: 0 | O60: 0 | P60: 124124.61 | Q60: 0 | R60: 0 | S60: 124124.61 | T60: -124124.61 | U60: 112505.6 | V60: 0 | W60: 112505.6 | X60: -236630.21 | Y60: =VLOOKUP(D60,'TKP 终端汇总'!A:A,1,0) -> Google
A61: P435002 | B61: Dublin mid | C61: 330 | D61: GN | E61: 44226 | F61: 42181 | G61: 0 | H61: 0 | I61: 0 | J61: 0 | K61: 0 | L61: 0 | M61: 0 | N61: 0 | O61: 0 | P61: 0 | Q61: 0 | R61: 0 | S61: 0 | T61: 0 | U61: 0 | V61: 0 | W61: 0 | X61: 0 | Y61: =VLOOKUP(D61,'TKP 终端汇总'!A:A,1,0) -> GN
A62: P435004 | B62: Dublin MONO | C62: 330 | D62: GN | E62: 44226 | F62: 42181 | G62: 0 | H62: 1926748.6 | I62: 0 | J62: 0 | K62: 0 | L62: 0 | M62: 1926748.6 | N62: 1138252 | O62: 0 | P62: 25728.59 | Q62: 41557.25 | R62: 4489.44 | S62: 1210027.3 | T62: 716721.32 | U62: 0 | V62: 2254.94 | W62: 2254.94 | X62: 714466.38 | Y62: =VLOOKUP(D62,'TKP 终端汇总'!A:A,1,0) -> GN
A63: P437030 | B63: RHEA | C63: 437 | D63: FITBIT | E63: 44226 | F63: 44175 | G63: 6970000 | H63: 0 | I63: 0 | J63: 0 | K63: 0 | L63: 0 | M63: 0 | N63: 0 | O63: 0 | P63: 25128.83 | Q63: 0 | R63: 4304.53 | S63: 29433.36 | T63: -29433.36 | U63: 1803.05 | V63: 0 | W63: 1803.05 | X63: -31236.41 | Y63: =VLOOKUP(D63,'TKP 终端汇总'!A:A,1,0) -> FITBIT
A64: P437031 | B64: HERA | C64: 437 | D64: FITBIT | E64: 44384 | F64: 44426 | G64: 805290 | H64: 0 | I64: 0 | J64: 0 | K64: 0 | L64: 0 | M64: 0 | N64: 0 | O64: 0 | P64: 0 | Q64: 0 | R64: 0 | S64: 0 | T64: 0 | U64: 763.71 | V64: 0 | W64: 763.71 | X64: -763.71 | Y64: =VLOOKUP(D64,'TKP 终端汇总'!A:A,1,0) -> FITBIT
A65: P438012 | B65: Tokyo | C65: 438 | D65: PHILIPS | E65: 44226 | F65: 42391 | G65: 0 | H65: 0 | I65: 0 | J65: 0 | K65: 0 | L65: 0 | M65: 0 | N65: 0 | O65: 0 | P65: 0 | Q65: 0 | R65: 0 | S65: 0 | T65: 0 | U65: 0 | V65: 0 | W65: 0 | X65: 0 | Y65: =VLOOKUP(D65,'TKP 终端汇总'!A:A,1,0) -> PHILIPS
A66: P440054 | B66: TechDev 2021 | C66: 440 | D66: OTTERBOX | E66: 44228 | F66: 44313 | G66: 0 | H66: 0 | I66: 0 | J66: 0 | K66: 0 | L66: 0 | M66: 0 | N66: 0 | O66: 0 | P66: 0 | Q66: 0 | R66: 0 | S66: 0 | T66: 0 | U66: 0 | V66: 0 | W66: 0 | X66: 0 | Y66: =VLOOKUP(D66,'TKP 终端汇总'!A:A,1,0) -> OTTERBOX
A67: P781012 | B67: ARTEMIS | C67: 781 | D67: ECOBEE | E67: 44347 | F67: 44357 | G67: 0 | H67: 0 | I67: 0 | J67: 0 | K67: 0 | L67: 0 | M67: 0 | N67: 0 | O67: 0 | P67: 0 | Q67: 0 | R67: 0 | S67: 0 | T67: 0 | U67: 0 | V67: 0 | W67: 0 | X67: 0 | Y67: =VLOOKUP(D67,'TKP 终端汇总'!A:A,1,0) -> ECOBEE
A68: P802009 | B68: UX700 | C68: 802 | D68: Verifone | E68: 44226 | F68: 44226 | G68: 5505528.6 | H68: 0 | I68: 0 | J68: 0 | K68: 0 | L68: 0 | M68: 0 | N68: 0 | O68: 0 | P68: 38494.93 | Q68: 0 | R68: 0 | S68: 38494.93 | T68: -38494.93 | U68: 0 | V68: 0 | W68: 0 | X68: -38494.93 | Y68: =VLOOKUP(D68,'TKP 终端汇总'!A:A,1,0) -> Verifone
A69: P819002 | B69: N536/K536 | C69: C819 | D69: 佛吉亚 | E69: 44392 | F69: 44407 | G69: 8698360 | H69: 0 | I69: 0 | J69: 0 | K69: 0 | L69: 0 | M69: 0 | N69: 0 | O69: 0 | P69: 0 | Q69: 0 | R69: 0 | S69: 0 | T69: 0 | U69: 802.91 | V69: 10541.28 | W69: 11344.19 | X69: -11344.19 | Y69: =VLOOKUP(D69,'TKP 终端汇总'!A:A,1,0) -> 佛吉亚
A70: P831001 | B70: PANDORA | C70: C831 | D70: August | E70: 44264 | F70: 44288 | G70: 11536523 | H70: 0 | I70: 0 | J70: 2755.7 | K70: 0 | L70: 0 | M70: 2755.7 | N70: 0 | O70: 0 | P70: 6022.62 | Q70: 9070.46 | R70: 0 | S70: 15093.08 | T70: -12337.38 | U70: 0 | V70: 17481.01 | W70: 17481.01 | X70: -29818.39 | Y70: =VLOOKUP(D70,'TKP 终端汇总'!A:A,1,0) -> August
A71: P404014 | B71: BISMUTH | C71: 404 | D71: Google | E71: 44334 | F71: 43328 | G71: 67325484 | H71: 3424206.2 | I71: 0 | J71: 150826.55 | K71: 384922 | L71: 0 | M71: 3959954.8 | N71: 3360312.1 | O71: 0 | P71: 39847.12 | Q71: 142087.84 | R71: 279059.81 | S71: 3821306.9 | T71: 138647.85 | U71: 169919.18 | V71: 81626.3 | W71: 251545.48 | X71: -112897.63 | Y71: =VLOOKUP(D71,'TKP 终端汇总'!A:A,1,0) -> Google
A72: P809002 | B72: RINCON | C72: C809 | D72: 歌尔 | E72: 44226 | F72: 44238 | G72: 175000 | H72: 0 | I72: 0 | J72: 0 | K72: 0 | L72: 0 | M72: 0 | N72: 0 | O72: 0 | P72: 0 | Q72: 0 | R72: 0 | S72: 0 | T72: 0 | U72: 0 | V72: 1098.26 | W72: 1098.26 | X72: -1098.26 | Y72: =VLOOKUP(D72,'TKP 终端汇总'!A:A,1,0) -> 歌尔
A73: P814002 | B73: MAPLE | C73: C814 | D73: Pax Labs | E73: 44226 | F73: 43969 | G73: 7800000 | H73: 0 | I73: 0 | J73: 0 | K73: 0 | L73: 0 | M73: 0 | N73: 0 | O73: 0 | P73: 3169.49 | Q73: 0 | R73: 0 | S73: 3169.49 | T73: -3169.49 | U73: 0 | V73: 0 | W73: 0 | X73: -3169.49 | Y73: =VLOOKUP(D73,'TKP 终端汇总'!A:A,1,0) -> Pax Labs
A74: P824002 | B74: TF1601A | C74: C824 | D74: BAT | E74: 44226 | F74: 44344 | G74: 4125000 | H74: 0 | I74: 0 | J74: 0 | K74: 0 | L74: 0 | M74: 0 | N74: 180377.83 | O74: 0 | P74: 3246.84 | Q74: 0 | R74: 0 | S74: 183624.67 | T74: -183624.67 | U74: 0 | V74: 4121.15 | W74: 4121.15 | X74: -187745.82 | Y74: =VLOOKUP(D74,'TKP 终端汇总'!A:A,1,0) -> BAT
A75: P437032 | B75: RENO | C75: 437 | D75: FITBIT | E75: 44488 | F75: 44774 | G75: 1460200 | H75: 33076.59 | I75: 0 | J75: 0 | K75: 0 | L75: 0 | M75: 33076.59 | N75: 0 | O75: 0 | P75: 0 | Q75: 0 | R75: 0 | S75: 0 | T75: 33076.59 | U75: 0 | V75: 2663.46 | W75: 2663.46 | X75: 30413.13 | Y75: =VLOOKUP(D75,'TKP 终端汇总'!A:A,1,0) -> FITBIT
A76: P824005 | B76: MODERN DISPOSABLE TX500 | C76: C824 | D76: BAT | E76: 44588 | F76: 44791 | G76: 32574420 | H76: 47905.55 | I76: 0 | J76: 0 | K76: 0 | L76: 0 | M76: 47905.55 | N76: 2230151 | O76: 0 | P76: 117430.36 | Q76: 0 | R76: 0 | S76: 2347581.3 | T76: -2299675.8 | U76: 0 | V76: 0 | W76: 0 | X76: -2299675.8 | Y76: =VLOOKUP(D76,'TKP 终端汇总'!A:A,1,0) -> BAT
A77: P813001 | B77: FRAZIER3 | C77: C813 | D77: Lifescan | E77: 44226 | F77: 44362 | G77: 0 | H77: 82005 | I77: 0 | J77: 0 | K77: 0 | L77: 0 | M77: 82005 | N77: 50929.01 | O77: 0 | P77: 13594.86 | Q77: 0 | R77: 0 | S77: 64523.87 | T77: 17481.13 | U77: 0 | V77: 17586.16 | W77: 17586.16 | X77: -105.03 | Y77: =VLOOKUP(D77,'TKP 终端汇总'!A:A,1,0) -> Lifescan
A78: P807001 | B78: HSL-4 | C78: C807 | D78: 喜利得 | E78: 44226 | F78: 43950 | G78: 0 | H78: 0 | I78: 0 | J78: 0 | K78: 0 | L78: 0 | M78: 0 | N78: 53159.13 | O78: 0 | P78: 0 | Q78: 0 | R78: 0 | S78: 53159.13 | T78: -53159.13 | U78: 0 | V78: 0 | W78: 0 | X78: -53159.13 | Y78: =VLOOKUP(D78,'TKP 终端汇总'!A:A,1,0) -> 喜利得
A79: P805012 | B79: P63B | C79: C805 | D79: 合元 | E79: 44226 | F79: 44208 | G79: 0 | H79: 0 | I79: 0 | J79: 0 | K79: 0 | L79: 0 | M79: 0 | N79: 90423.05 | O79: 0 | P79: 55725.33 | Q79: 0 | R79: 0 | S79: 146148.38 | T79: -146148.38 | U79: 0 | V79: 0 | W79: 0 | X79: -146148.38 | Y79: =VLOOKUP(D79,'TKP 终端汇总'!A:A,1,0) -> 合元
A80: P805004 | B80: PANDORA | C80: C805 | D80: 合元 | E80: 44226 | F80: 44006 | G80: 0 | H80: 0 | I80: 0 | J80: 0 | K80: 0 | L80: 0 | M80: 0 | N80: 0 | O80: 0 | P80: 5798.75 | Q80: 0 | R80: 0 | S80: 5798.75 | T80: -5798.75 | U80: 0 | V80: 0 | W80: 0 | X80: -5798.75 | Y80: =VLOOKUP(D80,'TKP 终端汇总'!A:A,1,0) -> 合元
A81: P802004 | B81: M440 | C81: 802 | D81: Verifone | E81: 44226 | F81: 43959 | G81: 0 | H81: 0 | I81: 0 | J81: 0 | K81: 0 | L81: 0 | M81: 0 | N81: 0 | O81: 0 | P81: 0 | Q81: 0 | R81: 0 | S81: 0 | T81: 0 | U81: 0 | V81: 0 | W81: 0 | X81: 0 | Y81: =VLOOKUP(D81,'TKP 终端汇总'!A:A,1,0) -> Verifone
A82: P781004 | B82: Rhodos | C82: 781 | D82: ECOBEE | E82: 44226 | F82: 43696 | G82: 0 | H82: 0 | I82: 0 | J82: 0 | K82: 0 | L82: 0 | M82: 0 | N82: 0 | O82: 0 | P82: 0 | Q82: 0 | R82: 0 | S82: 0 | T82: 0 | U82: 3886.75 | V82: 2045.97 | W82: 5932.72 | X82: -5932.72 | Y82: =VLOOKUP(D82,'TKP 终端汇总'!A:A,1,0) -> ECOBEE
A83: P460009 | B83: CORAL | C83: 460 | D83: AMAZON | E83: 44226 | F83: 44382 | G83: 26098356 | H83: 0 | I83: 0 | J83: 0 | K83: 0 | L83: 0 | M83: 0 | N83: 0 | O83: 0 | P83: 30702.01 | Q83: 8087.44 | R83: 0 | S83: 38789.45 | T83: -38789.45 | U83: 0 | V83: -2747.83 | W83: -2747.83 | X83: -36041.62 | Y83: =VLOOKUP(D83,'TKP 终端汇总'!A:A,1,0) -> AMAZON
A84: P460005 | B84: THEIA | C84: 460 | D84: AMAZON | E84: 44226 | F84: 44127 | G84: 0 | H84: 0 | I84: 0 | J84: 0 | K84: 0 | L84: 0 | M84: 0 | N84: 0 | O84: 0 | P84: 8541.87 | Q84: 463.91 | R84: 0 | S84: 9005.78 | T84: -9005.78 | U84: 1092.12 | V84: 6587.95 | W84: 7680.07 | X84: -16685.85 | Y84: =VLOOKUP(D84,'TKP 终端汇总'!A:A,1,0) -> AMAZON
A85: P440052 | B85: SBA-0041 | C85: 440 | D85: OTTERBOX | E85: 44226 | F85: 44336 | G85: 0 | H85: 0 | I85: 0 | J85: 0 | K85: 0 | L85: 0 | M85: 0 | N85: 0 | O85: 0 | P85: 0 | Q85: 0 | R85: 0 | S85: 0 | T85: 0 | U85: 100423.38 | V85: 0 | W85: 100423.38 | X85: -100423.38 | Y85: =VLOOKUP(D85,'TKP 终端汇总'!A:A,1,0) -> OTTERBOX
A86: P438037 | B86: XIAN | C86: 438 | D86: PHILIPS | E86: 44226 | F86: 44005 | G86: 0 | H86: 0 | I86: 0 | J86: 0 | K86: 0 | L86: 0 | M86: 0 | N86: 8010.38 | O86: 0 | P86: 3514.81 | Q86: 0 | R86: 0 | S86: 11525.19 | T86: -11525.19 | U86: 0 | V86: 10650.4 | W86: 10650.4 | X86: -22175.59 | Y86: =VLOOKUP(D86,'TKP 终端汇总'!A:A,1,0) -> PHILIPS
A87: P438035 | B87: APA | C87: 438 | D87: PHILIPS | E87: 44226 | F87: 44054 | G87: 0 | H87: 0 | I87: 0 | J87: 0 | K87: 0 | L87: 0 | M87: 0 | N87: 0 | O87: 0 | P87: 18447.75 | Q87: 0 | R87: 4282.82 | S87: 22730.57 | T87: -22730.57 | U87: 0 | V87: 782.37 | W87: 782.37 | X87: -23512.94 | Y87: =VLOOKUP(D87,'TKP 终端汇总'!A:A,1,0) -> PHILIPS
A88: P438032 | B88: Hobart | C88: 438 | D88: PHILIPS | E88: 44226 | F88: 43420 | G88: 0 | H88: 0 | I88: 0 | J88: 0 | K88: 0 | L88: 0 | M88: 0 | N88: 0 | O88: 0 | P88: 26399.09 | Q88: 0 | R88: 0 | S88: 26399.09 | T88: -26399.09 | U88: 0 | V88: 0 | W88: 0 | X88: -26399.09 | Y88: =VLOOKUP(D88,'TKP 终端汇总'!A:A,1,0) -> PHILIPS
A89: P438026 | B89: U-tube | C89: 438 | D89: PHILIPS | E89: 44226 | F89: 43124 | G89: 120006.6 | H89: 0 | I89: 0 | J89: 0 | K89: 0 | L89: 0 | M89: 0 | N89: 9208.88 | O89: 0 | P89: 22590.2 | Q89: 0 | R89: 0 | S89: 31799.08 | T89: -31799.08 | U89: 0 | V89: 0 | W89: 0 | X89: -31799.08 | Y89: =VLOOKUP(D89,'TKP 终端汇总'!A:A,1,0) -> PHILIPS
A90: P438024 | B90: Sydney | C90: 438 | D90: PHILIPS | E90: 44226 | F90: 43118 | G90: 0 | H90: 0 | I90: 0 | J90: 0 | K90: 0 | L90: 0 | M90: 0 | N90: 0 | O90: 0 | P90: 70867.8 | Q90: 0 | R90: 0 | S90: 70867.8 | T90: -70867.8 | U90: 0 | V90: 31438.71 | W90: 31438.71 | X90: -102306.51 | Y90: =VLOOKUP(D90,'TKP 终端汇总'!A:A,1,0) -> PHILIPS
A91: P438023 | B91: Shanghai | C91: 438 | D91: PHILIPS | E91: 44226 | F91: 42909 | G91: 7442400 | H91: 0 | I91: 0 | J91: 0 | K91: 0 | L91: 0 | M91: 0 | N91: 3270.48 | O91: 0 | P91: 3857.89 | Q91: 0 | R91: 0 | S91: 7128.37 | T91: -7128.37 | U91: 86338.09 | V91: 878.64 | W91: 87216.73 | X91: -94345.1 | Y91: =VLOOKUP(D91,'TKP 终端汇总'!A:A,1,0) -> PHILIPS
A92: P438018 | B92: Doutzen | C92: 438 | D92: PHILIPS | E92: 44226 | F92: 42936 | G92: 0 | H92: 0 | I92: 0 | J92: 0 | K92: 0 | L92: 0 | M92: 0 | N92: 0 | O92: 0 | P92: 0 | Q92: 0 | R92: 0 | S92: 0 | T92: 0 | U92: 0 | V92: 0 | W92: 0 | X92: 0 | Y92: =VLOOKUP(D92,'TKP 终端汇总'!A:A,1,0) -> PHILIPS
... A100: P330014 | B100: YOSHI | C100: 330 | D100: GN | E100: 44226 | F100: 43969 | G100: 0 | H100: 0 | I100: 0 | J100: 0 | K100: 0 | L100: 0 | M100: 0 | N100: 0 | O100: 0 | P100: 0 | Q100: 0 | R100: 0 | S100: 0 | T100: 0 | U100: 0 | V100: 0 | W100: 0 | X100: 0 | Y100: =VLOOKUP(D100,'TKP 终端汇总'!A:A,1,0) -> GN
A101: P017001 | B101: FAIRFIELD | C101: C017 | D101: Sensirion | E101: 44226 | F101: 42718 | G101: 1705000 | H101: 143648.33 | I101: 0 | J101: 106.64 | K101: 0 | L101: 0 | M101: 143754.97 | N101: 15308.37 | O101: 0 | P101: 0 | Q101: 0 | R101: 0 | S101: 15308.37 | T101: 128446.6 | U101: 229.12 | V101: 0 | W101: 229.12 | X101: 128217.48 | Y101: =VLOOKUP(D101,'TKP 终端汇总'!A:A,1,0) -> Sensirion
A102: P024087 | B102: Skyline Base&Entry | C102: C024 | D102: POLYCOM | E102: 44226 | F102: 43259 | G102: 4700000 | H102: 0 | I102: 0 | J102: 0 | K102: 0 | L102: 0 | M102: 0 | N102: 9651.12 | O102: 0 | P102: 0 | Q102: 0 | R102: 0 | S102: 9651.12 | T102: -9651.12 | U102: 0 | V102: 6094.93 | W102: 6094.93 | X102: -15746.05 | Y102: =VLOOKUP(D102,'TKP 终端汇总'!A:A,1,0) -> POLYCOM
A103: P024095 | B103: MX681 | C103: C024 | D103: POLYCOM | E103: 44226 | F103: 43922 | G103: 1156250 | H103: 0 | I103: 0 | J103: 0 | K103: 0 | L103: 0 | M103: 0 | N103: 27151.34 | O103: 0 | P103: 5402.56 | Q103: 0 | R103: 0 | S103: 32553.9 | T103: -32553.9 | U103: 0 | V103: 0 | W103: 0 | X103: -32553.9 | Y103: =VLOOKUP(D103,'TKP 终端汇总'!A:A,1,0) -> POLYCOM
A104: P024096 | B104: HDT611 | C104: C024 | D104: POLYCOM | E104: 44226 | F104: 44375 | G104: 0 | H104: 0 | I104: 0 | J104: 374400 | K104: 0 | L104: 0 | M104: 374400 | N104: 189194.26 | O104: 0 | P104: 2984.41 | Q104: 0 | R104: 0 | S104: 192178.67 | T104: 182221.33 | U104: 0 | V104: 62932.71 | W104: 62932.71 | X104: 119288.62 | Y104: =VLOOKUP(D104,'TKP 终端汇总'!A:A,1,0) -> POLYCOM
A105: P024102 | B105: Crystal | C105: C024 | D105: POLYCOM | E105: 44226 | F105: 44452 | G105: 9765075 | H105: 0 | I105: 0 | J105: 0 | K105: 0 | L105: 0 | M105: 0 | N105: 309.92 | O105: 0 | P105: 0 | Q105: 0 | R105: 851.3 | S105: 1161.22 | T105: -1161.22 | U105: 4104.77 | V105: 15.22 | W105: 4119.99 | X105: -5281.21 | Y105: =VLOOKUP(D105,'TKP 终端汇总'!A:A,1,0) -> POLYCOM
A106: P024103 | B106: P30 | C106: C024 | D106: POLYCOM | E106: 44226 | F106: 44209 | G106: 0 | H106: 0 | I106: 0 | J106: 0 | K106: 0 | L106: 0 | M106: 0 | N106: 0 | O106: 0 | P106: 0 | Q106: 0 | R106: 0 | S106: 0 | T106: 0 | U106: 0 | V106: 0 | W106: 0 | X106: 0 | Y106: =VLOOKUP(D106,'TKP 终端汇总'!A:A,1,0) -> POLYCOM
A107: P024105 | B107: PENGUIN | C107: C024 | D107: POLYCOM | E107: 44226 | F107: 44442 | G107: 7459500 | H107: 0 | I107: 0 | J107: 0 | K107: 0 | L107: 0 | M107: 0 | N107: 2276.8 | O107: 0 | P107: 0 | Q107: 0 | R107: 1805.68 | S107: 4082.48 | T107: -4082.48 | U107: 12075.37 | V107: 1551.74 | W107: 13627.11 | X107: -17709.59 | Y107: =VLOOKUP(D107,'TKP 终端汇总'!A:A,1,0) -> POLYCOM
...

Sheet 按BU汇总
A1: TK项目号 | B1: 项目名称 | C1: 利润中心 | D1: 事业部 | E1: 终端客户 | F1: 终端客户名称 | G1: 创建日期 | H1: 量产日期 | I1: NPI预算收入 | J1: 注塑模具收入 | K1: 其他模具收入 | L1: 样板费收入 | M1: 夹治具收入 | N1: 其它杂项收入 | O1: 量产前收入 | P1: 注塑模具成本 | Q1: 其他模具成本 | R1: 自费模具摊销 | S1: 量产前夹治具成本 | T1: 试模成本 | U1: 量产前成本 | V1: 量产前收益 | W1: 量产后夹治具成本 | X1: 量产后打样成本 | Y1: 量产后成本
A2: P208003 | B2: VIE | C2: 100 | D2: 高效一 | E2: C208 | F2: 深圳市韶音科技有限公司 | G2: 44226 | H2: 44223 | I2: 1144000 | J2: 1674505.5 | K2: 0 | L2: 25419.56 | M2: 205803.66 | N2: 0 | O2: =SUM(J2:N2) -> 1905728.7 | P2: 2599941.2 | Q2: 0 | R2: 28874.55 | S2: 48321.4 | T2: 28886.58 | U2: =SUM(P2:T2) -> 2706023.7 | V2: =O2-U2 -> -800295.05 | W2: 187017.73 | X2: 46061.7 | Y2: 233079.43
A3: P330041 | B3: WILLOW | C3: 100 | D3: 高效一 | E3: 330 | F3: GN Audio A/S(GSC) | G3: 44487 | I3: 8394500 | J3: 0 | K3: 0 | L3: 33810.83 | M3: 0 | N3: 0 | O3: =SUM(J3:N3) -> 33810.83 | P3: 0 | Q3: 0 | R3: 0 | S3: 201918.66 | T3: 161321.99 | U3: =SUM(P3:T3) -> 363240.65 | V3: =O3-U3 -> -329429.82 | W3: 0 | X3: 0 | Y3: 0
A4: P435004 | B4: Dublin MONO | C4: 100 | D4: 高效一 | E4: 330 | F4: GN Audio A/S(GSC) | G4: 44226 | H4: 42181 | I4: 0 | J4: 0 | K4: 0 | L4: 0 | M4: 0 | N4: 0 | O4: =SUM(J4:N4) -> 0 | P4: 0 | Q4: 0 | R4: 5012.85 | S4: 60779.34 | T4: 4286.79 | U4: =SUM(P4:T4) -> 70078.98 | V4: =O4-U4 -> -70078.98 | W4: 0 | X4: 4972.78 | Y4: 4972.78
A5: P330020 | B5: Leo | C5: 100 | D5: 高效一 | E5: 330 | F5: GN Audio A/S(GSC) | G5: 44226 | H5: 44371 | I5: 0 | J5: 0 | K5: 0 | L5: 0 | M5: 0 | N5: 0 | O5: =SUM(J5:N5) -> 0 | P5: 0 | Q5: 0 | R5: 7894.22 | S5: 0 | T5: 0 | U5: =SUM(P5:T5) -> 7894.22 | V5: =O5-U5 -> -7894.22 | W5: 0 | X5: 1818.99 | Y5: 1818.99
A6: P360009 | B6: SABRINA | C6: 100 | D6: 高效一 | E6: 360 | F6: Google Inc. | G6: 44226 | H6: 43999 | I6: 0 | J6: 0 | K6: 0 | L6: 0 | M6: 0 | N6: 0 | O6: =SUM(J6:N6) -> 0 | P6: 0 | Q6: 0 | R6: 18943.218 | S6: 0 | T6: 0 | U6: =SUM(P6:T6) -> 18943.218 | V6: =O6-U6 -> -18943.218 | W6: 0 | X6: 0 | Y6: 0
A7: P360020 | B7: BOREAL | C7: 100 | D7: 高效一 | E7: 360 | F7: Google Inc. | G7: 44226 | H7: 42620 | I7: 2631434.3 | J7: 1817343 | K7: 0 | L7: 23329.8 | M7: 0 | N7: 0 | O7: =SUM(J7:N7) -> 1840672.8 | P7: 2104704 | Q7: 0 | R7: 0 | S7: 0 | T7: 10620.57 | U7: =SUM(P7:T7) -> 2115324.6 | V7: =O7-U7 -> -274651.77 | W7: 0 | X7: -5131.68 | Y7: -5131.68
A8: P250064 | B8: CZ460 | C8: 100 | D8: 高效一 | E8: 250 | F8: Western Digital Technologies,I | G8: 44226 | H8: 43566 | I8: 0 | J8: 0 | K8: 0 | L8: 0 | M8: 0 | N8: 0 | O8: =SUM(J8:N8) -> 0 | P8: 0 | Q8: 0 | R8: 0 | S8: 0 | T8: 0 | U8: =SUM(P8:T8) -> 0 | V8: =O8-U8 -> 0 | W8: 0 | X8: 288.39 | Y8: 288.39
A9: P330021 | B9: ASTRA | C9: 100 | D9: 高效一 | E9: 330 | F9: GN Audio A/S(GSC) | G9: 44226 | H9: 42328 | I9: 13469900 | J9: 13059715 | K9: 0 | L9: 831090.09 | M9: 0 | N9: 0 | O9: =SUM(J9:N9) -> 13890805 | P9: 12779048 | Q9: 0 | R9: 36326.51 | S9: 2166.36 | T9: 117492.9 | U9: =SUM(P9:T9) -> 12935034 | V9: =O9-U9 -> 955771.08 | W9: 75511.66 | X9: 66706.02 | Y9: 142217.68
A10: P268033 | B10: C77/C65/A131/A136 | C10: 100 | D10: 高效一 | E10: C268 | F10: Apple Inc. | G10: 44226 | H10: 44012 | I10: 0 | J10: 0 | K10: 0 | L10: 0 | M10: 0 | N10: 0 | O10: =SUM(J10:N10) -> 0 | P10: 0 | Q10: 0 | R10: 0 | S10: 1830.56 | T10: 0 | U10: =SUM(P10:T10) -> 1830.56 | V10: =O10-U10 -> -1830.56 | W10: 0 | X10: 0 | Y10: 0
A11: P208001 | B11: 韶音 | C11: 100 | D11: 高效一 | E11: C208 | F11: 深圳市韶音科技有限公司 | G11: 44226 | H11: 44004 | I11: 0 | J11: 19583.84 | K11: 0 | L11: 0 | M11: 0 | N11: 0 | O11: =SUM(J11:N11) -> 19583.84 | P11: 18359.86 | Q11: 0 | R11: 0 | S11: 0 | T11: 0 | U11: =SUM(P11:T11) -> 18359.86 | V11: =O11-U11 -> 1223.98 | W11: 0 | X11: 0 | Y11: 0
A12: P330010 | B12: Spiderman | C12: 100 | D12: 高效一 | E12: 330 | F12: GN Audio A/S(GSC) | G12: 44226 | H12: 44180 | I12: 8800 | J12: 252704.4 | K12: 0 | L12: 0 | M12: 0 | N12: 0 | O12: =SUM(J12:N12) -> 252704.4 | P12: 286413.71 | Q12: 0 | R12: 28705.24 | S12: 0 | T12: 3119.09 | U12: =SUM(P12:T12) -> 318238.04 | V12: =O12-U12 -> -65533.64 | W12: 0 | X12: 1168.45 | Y12: 1168.45
A13: P862001 | B13: PSC56一体机 | C13: 100 | D13: 高效一 | E13: C862 | F13: 影石创新科技股份有限公司 | G13: 44606 | I13: 1670294 | J13: 0 | K13: 0 | L13: 14864.56 | M13: 0 | N13: 0 | O13: =SUM(J13:N13) -> 14864.56 | P13: 0 | Q13: 0 | R13: 0 | S13: 41030.21 | T13: 35767.54 | U13: =SUM(P13:T13) -> 76797.75 | V13: =O13-U13 -> -61933.19 | W13: 0 | X13: 0 | Y13: 0
A14: P208002 | B14: SE | C14: 100 | D14: 高效一 | E14: C208 | F14: 深圳市韶音科技有限公司 | G14: 44226 | H14: 43888 | I14: 444114 | J14: 122071.52 | K14: 0 | L14: 815.8 | M14: 0 | N14: 0 | O14: =SUM(J14:N14) -> 122887.32 | P14: 143033.29 | Q14: 0 | R14: 9643.58 | S14: 3263.86 | T14: 35686.13 | U14: =SUM(P14:T14) -> 191626.86 | V14: =O14-U14 -> -68739.54 | W14: 0 | X14: 722.98 | Y14: 722.98
A15: P330043 | B15: STELLA | C15: 100 | D15: 高效一 | E15: 330 | F15: GN Audio A/S(GSC) | G15: 44662 | I15: 220000 | J15: 258814.08 | K15: 0 | L15: 0 | M15: 27561.6 | N15: 0 | O15: =SUM(J15:N15) -> 286375.68 | P15: 206623.2 | Q15: 0 | R15: 0 | S15: 0 | T15: 6191.12 | U15: =SUM(P15:T15) -> 212814.32 | V15: =O15-U15 -> 73561.36 | W15: 0 | X15: 0 | Y15: 0
A16: P330014 | B16: YOSHI | C16: 100 | D16: 高效一 | E16: 330 | F16: GN Audio A/S(GSC) | G16: 44226 | H16: 43969 | I16: 0 | J16: 0 | K16: 0 | L16: 0 | M16: 0 | N16: 0 | O16: =SUM(J16:N16) -> 0 | P16: 0 | Q16: 0 | R16: 76680.39 | S16: 0 | T16: 0 | U16: =SUM(P16:T16) -> 76680.39 | V16: =O16-U16 -> -76680.39 | W16: 0 | X16: 596.31 | Y16: 596.31
A17: P330036 | B17: COBRANDING-SPIDERMAN | C17: 100 | D17: 高效一 | E17: 330 | F17: GN Audio A/S(GSC) | G17: 44271 | H17: 42431 | I17: 257400 | J17: 0 | K17: 0 | L17: 0 | M17: 0 | N17: 0 | O17: =SUM(J17:N17) -> 0 | P17: 0 | Q17: 0 | R17: 0 | S17: 0 | T17: 0 | U17: =SUM(P17:T17) -> 0 | V17: =O17-U17 -> 0 | W17: 2860.31 | X17: 0 | Y17: 2860.31
A18: P208004 | B18: TT0 | C18: 100 | D18: 高效一 | E18: C208 | F18: 深圳市韶音科技有限公司 | G18: 44306 | H18: 44403 | I18: 1058000 | J18: 0 | K18: 0 | L18: 58861.71 | M18: 6497.93 | N18: 0 | O18: =SUM(J18:N18) -> 65359.64 | P18: 0 | Q18: 0 | R18: 0 | S18: 4207.97 | T18: 18480.02 | U18: =SUM(P18:T18) -> 22687.99 | V18: =O18-U18 -> 42671.65 | W18: 9564.21 | X18: 0 | Y18: 9564.21
A19: P208008 | B19: PARIS | C19: 100 | D19: 高效一 | E19: C208 | F19: 深圳市韶音科技有限公司 | G19: 44628 | I19: 765000 | J19: 0 | K19: 0 | L19: 2964.44 | M19: 0 | N19: 0 | O19: =SUM(J19:N19) -> 2964.44 | P19: 3127.06 | Q19: 0 | R19: 0 | S19: 56258.79 | T19: 53169.69 | U19: =SUM(P19:T19) -> 112555.54 | V19: =O19-U19 -> -109591.1 | W19: 0 | X19: 0 | Y19: 0
A20: P826001 | B20: BH72 | C20: 100 | D20: 高效一 | E20: C826 | F20: 厦门亿联网络技术股份有限公司 | G20: 44226 | H20: 44151 | I20: 0 | J20: 437209.3 | K20: 0 | L20: 0 | M20: 0 | N20: 0 | O20: =SUM(J20:N20) -> 437209.3 | P20: 644308.44 | Q20: 0 | R20: 11030.22 | S20: 0 | T20: 0 | U20: =SUM(P20:T20) -> 655338.66 | V20: =O20-U20 -> -218129.36 | W20: 0 | X20: 196.38 | Y20: 196.38
A21: P860001 | B21: HERCULES | C21: 100 | D21: 高效一 | E21: C860 | F21: 通力科技股份有限公司 | G21: 44546 | I21: 1147800 | J21: 580419.58 | K21: 0 | L21: 115844.7 | M21: 98452.38 | N21: 0 | O21: =SUM(J21:N21) -> 794716.66 | P21: 524475.53 | Q21: 0 | R21: 0 | S21: 8599.22 | T21: 71119.36 | U21: =SUM(P21:T21) -> 604194.11 | V21: =O21-U21 -> 190522.55 | W21: 9826.57 | X21: 0 | Y21: 9826.57
A22: P268029 | B22: FH001 | C22: 100 | D22: 高效一 | E22: C268 | F22: Apple Inc. | G22: 44226 | H22: 43357 | I22: 0 | J22: 0 | K22: 0 | L22: 0 | M22: 0 | N22: 1010070 | O22: =SUM(J22:N22) -> 1010070 | P22: 0 | Q22: 0 | R22: 0 | S22: 0 | T22: 0 | U22: =SUM(P22:T22) -> 0 | V22: =O22-U22 -> 1010070 | W22: 0 | X22: 0 | Y22: 0
A23: P291002 | B23: Dummy ED | C23: 100 | D23: 高效一 | E23: 291 | F23: Phonak AG | G23: 44226 | I23: 0 | J23: 0 | K23: 0 | L23: 0 | M23: 0 | N23: 0 | O23: =SUM(J23:N23) -> 0 | P23: 7347.6 | Q23: 0 | R23: 0 | S23: 0 | T23: 0 | U23: =SUM(P23:T23) -> 7347.6 | V23: =O23-U23 -> -7347.6 | W23: 0 | X23: 197.32 | Y23: 197.32
A24: P831001 | B24: PANDORA | C24: 100 | D24: 高效一 | E24: C831 | F24: August Home, Inc. | G24: 44264 | H24: 44288 | I24: 1922753.8 | J24: 245047.04 | K24: 0 | L24: 173982.87 | M24: 0 | N24: 0 | O24: =SUM(J24:N24) -> 419029.91 | P24: 209171.2 | Q24: 0 | R24: 0 | S24: 3787 | T24: 39859.64 | U24: =SUM(P24:T24) -> 252817.84 | V24: =O24-U24 -> 166212.07 | W24: 0 | X24: 0 | Y24: 0
A25: P268043 | B25: E23 | C25: 100 | D25: 高效一 | E25: C268 | F25: Apple Inc. | G25: 44543 | I25: 0 | J25: 0 | K25: 0 | L25: 0 | M25: 0 | N25: 0 | O25: =SUM(J25:N25) -> 0 | P25: 0 | Q25: 0 | R25: 0 | S25: 636.9 | T25: 0 | U25: =SUM(P25:T25) -> 636.9 | V25: =O25-U25 -> -636.9 | W25: 0 | X25: 0 | Y25: 0
A26: P268044 | B26: HP030 | C26: 100 | D26: 高效一 | E26: C268 | F26: Apple Inc. | G26: 44553 | I26: 15000 | J26: 0 | K26: 0 | L26: 0 | M26: 0 | N26: 0 | O26: =SUM(J26:N26) -> 0 | P26: 0 | Q26: 0 | R26: 0 | S26: 710.56 | T26: 13525.1 | U26: =SUM(P26:T26) -> 14235.66 | V26: =O26-U26 -> -14235.66 | W26: 0 | X26: 0 | Y26: 0
A27: P208007 | B27: WHARF左右耳挂 | C27: 100 | D27: 高效一 | E27: C208 | F27: 深圳市韶音科技有限公司 | G27: 44613 | I27: 242000 | J27: 0 | K27: 0 | L27: 4351.2 | M27: 0 | N27: 0 | O27: =SUM(J27:N27) -> 4351.2 | P27: 0 | Q27: 0 | R27: 0 | S27: 2001.7 | T27: 839.59 | U27: =SUM(P27:T27) -> 2841.29 | V27: =O27-U27 -> 1509.91 | W27: 0 | X27: 0 | Y27: 0
A28: P268042 | B28: A139 BOOT | C28: 100 | D28: 高效一 | E28: C268 | F28: Apple Inc. | G28: 44441 | I28: 20000 | J28: 0 | K28: 0 | L28: 0 | M28: 0 | N28: 0 | O28: =SUM(J28:N28) -> 0 | P28: 0 | Q28: 0 | R28: 0 | S28: -6032.23 | T28: 0 | U28: =SUM(P28:T28) -> -6032.23 | V28: =O28-U28 -> 6032.23 | W28: 0 | X28: 0 | Y28: 0
A29: P831003 | B29: NEST 1.5 | C29: 100 | D29: 高效一 | E29: C831 | F29: August Home, Inc. | G29: 44411 | I29: 1561780 | J29: 0 | K29: 0 | L29: 9971.2 | M29: 0 | N29: 0 | O29: =SUM(J29:N29) -> 9971.2 | P29: 0 | Q29: 0 | R29: 0 | S29: 0 | T29: 0 | U29: =SUM(P29:T29) -> 0 | V29: =O29-U29 -> 9971.2 | W29: 0 | X29: 0 | Y29: 0
A30: P330038 | B30: MAPLE | C30: 100 | D30: 高效一 | E30: 330 | F30: GN Audio A/S(GSC) | G30: 44307 | H30: 42198 | I30: 1122000 | J30: 0 | K30: 0 | L30: 48546 | M30: 0 | N30: 0 | O30: =SUM(J30:N30) -> 48546 | P30: 0 | Q30: 0 | R30: 0 | S30: 0 | T30: 0 | U30: =SUM(P30:T30) -> 0 | V30: =O30-U30 -> 48546 | W30: 0 | X30: 0 | Y30: 0
A31: P460009 | B31: CORAL | C31: 601 | D31: 高效二 | E31: 460 | F31: Amazon com, Inc | G31: 44226 | H31: 44382 | I31: 4349725.9 | J31: 0 | K31: 0 | L31: 0 | M31: 0 | N31: 0 | O31: =SUM(J31:N31) -> 0 | P31: 0 | Q31: 0 | R31: 279883.9 | S31: 56841.87 | T31: 1965.14 | U31: =SUM(P31:T31) -> 338690.91 | V31: =O31-U31 -> -338690.91 | W31: 9846.29 | X31: 30890.11 | Y31: 40736.4
A32: P460012 | B32: MARLIN | C32: 601 | D32: 高效二 | E32: 460 | F32: Amazon com, Inc | G32: 44431 | H32: 44770 | I32: 3950325.7 | J32: 2091712 | K32: 0 | L32: 224672.23 | M32: 223661.42 | N32: 15862.48 | O32: =SUM(J32:N32) -> 2555908.1 | P32: 2469521.6 | Q32: 0 | R32: 8595.57 | S32: 69525.97 | T32: 136589.39 | U32: =SUM(P32:T32) -> 2684232.5 | V32: =O32-U32 -> -128324.4 | W32: 40703.51 | X32: 29357.25 | Y32: 70060.76
A33: P460004 | B33: POWELL | C33: 601 | D33: 高效二 | E33: 460 | F33: Amazon com, Inc | G33: 44226 | H33: 44410 | I33: 0 | J33: 0 | K33: 0 | L33: 0 | M33: 0 | N33: 0 | O33: =SUM(J33:N33) -> 0 | P33: 0 | Q33: 0 | R33: 4380.2 | S33: 0 | T33: 11170.63 | U33: =SUM(P33:T33) -> 15550.83 | V33: =O33-U33 -> -15550.83 | W33: 0 | X33: 30935.73 | Y33: 30935.73
A34: P460003 | B34: SPRINKLE | C34: 601 | D34: 高效二 | E34: 460 | F34: Amazon com, Inc | G34: 44226 | H34: 43620 | I34: 0 | J34: 0 | K34: 0 | L34: 0 | M34: 0 | N34: 0 | O34: =SUM(J34:N34) -> 0 | P34: 0 | Q34: 0 | R34: 0 | S34: 0 | T34: 0 | U34: =SUM(P34:T34) -> 0 | V34: =O34-U34 -> 0 | W34: 2167.1 | X34: 2165.99 | Y34: 4333.09
A35: P821002 | B35: S3 | C35: 601 | D35: 高效二 | E35: C821 | F35: Square Inc. | G35: 44226 | H35: 44133 | I35: 0 | J35: 0 | K35: 0 | L35: 141849.65 | M35: 0 | N35: 0 | O35: =SUM(J35:N35) -> 141849.65 | P35: 0 | Q35: 0 | R35: 163503.19 | S35: 19644.78 | T35: 51621.69 | U35: =SUM(P35:T35) -> 234769.66 | V35: =O35-U35 -> -92920.01 | W35: 56824.8 | X35: 29225.11 | Y35: 86049.91
A36: P460002 | B36: Project Vesta | C36: 601 | D36: 高效二 | E36: 460 | F36: Amazon com, Inc | G36: 44226 | H36: 44407 | I36: 0 | J36: 0 | K36: 0 | L36: 38291.88 | M36: 0 | N36: 0 | O36: =SUM(J36:N36) -> 38291.88 | P36: 0 | Q36: 0 | R36: 26496.05 | S36: 0 | T36: 4594.01 | U36: =SUM(P36:T36) -> 31090.06 | V36: =O36-U36 -> 7201.82 | W36: 16231.55 | X36: 20458.34 | Y36: 36689.89
A37: P460011 | B37: CRUSH | C37: 601 | D37: 高效二 | E37: 460 | F37: Amazon com, Inc | G37: 44350 | H37: 44369 | I37: 3460402 | J37: 3396616 | K37: 0 | L37: 34473.85 | M37: 9684.4 | N37: 0 | O37: =SUM(J37:N37) -> 3440774.2 | P37: 4062531.8 | Q37: 0 | R37: 1558.56 | S37: 31301.64 | T37: 30471.27 | U37: =SUM(P37:T37) -> 4125863.3 | V37: =O37-U37 -> -685089.02 | W37: 3820.94 | X37: 9481.93 | Y37: 13302.87
A38: P821003 | B38: S3 MOUNT | C38: 601 | D38: 高效二 | E38: C821 | F38: Square Inc. | G38: 44480 | I38: 2180000 | J38: 0 | K38: 0 | L38: 0 | M38: 0 | N38: 513162.54 | O38: =SUM(J38:N38) -> 513162.54 | P38: 0 | Q38: 0 | R38: 0 | S38: 28218.91 | T38: 113723.7 | U38: =SUM(P38:T38) -> 141942.61 | V38: =O38-U38 -> 371219.93 | W38: 11345.58 | X38: 2043.05 | Y38: 13388.63
A39: P268032 | B39: HP025 | C39: 601 | D39: 高效二 | E39: C268 | F39: Apple Inc. | G39: 44226 | H39: 43632 | I39: 0 | J39: 0 | K39: 0 | L39: 0 | M39: 0 | N39: -310315.19 | O39: =SUM(J39:N39) -> -310315.19 | P39: 0 | Q39: 0 | R39: 0 | S39: 0 | T39: 0 | U39: =SUM(P39:T39) -> 0 | V39: =O39-U39 -> -310315.19 | W39: 4453.91 | X39: 360784.34 | Y39: 365238.25
A40: P460005 | B40: THEIA | C40: 601 | D40: 高效二 | E40: 460 | F40: Amazon com, Inc | G40: 44226 | H40: 44127 | I40: 0 | J40: 0 | K40: 0 | L40: 0 | M40: 0 | N40: 0 | O40: =SUM(J40:N40) -> 0 | P40: 4103.17 | Q40: 0 | R40: 27904.43 | S40: 1095.25 | T40: 0 | U40: =SUM(P40:T40) -> 33102.85 | V40: =O40-U40 -> -33102.85 | W40: 1990.51 | X40: 42787.96 | Y40: 44778.47
A41: P293011 | B41: Jbay | C41: 601 | D41: 高效二 | E41: 293 | F41: GoPro, Inc. | G41: 44226 | H41: 43717 | I41: 0 | J41: 0 | K41: 0 | L41: 0 | M41: 0 | N41: 0 | O41: =SUM(J41:N41) -> 0 | P41: 0 | Q41: 0 | R41: 0 | S41: 0 | T41: 0 | U41: =SUM(P41:T41) -> 0 | V41: =O41-U41 -> 0 | W41: 0 | X41: 50.21 | Y41: 50.21
A42: P863001 | B42: WTH13 | C42: 601 | D42: 高效二 | E42: C863 | F42: Stripe Inc. | G42: 44628 | I42: 1870000 | J42: 0 | K42: 0 | L42: 0 | M42: 0 | N42: 0 | O42: =SUM(J42:N42) -> 0 | P42: 0 | Q42: 0 | R42: 0 | S42: 17427.57 | T42: 68407.75 | U42: =SUM(P42:T42) -> 85835.32 | V42: =O42-U42 -> -85835.32 | W42: 0 | X42: 0 | Y42: 0
A43: P330019 | B43: ERASMUS | C43: 701 | D43: 高效三 | E43: 330 | F43: GN Audio A/S(GSC) | G43: 44226 | H43: 42198 | I43: 913000 | J43: 2178747.7 | K43: 0 | L43: 0 | M43: 0 | N43: 0 | O43: =SUM(J43:N43) -> 2178747.7 | P43: 2165071.2 | Q43: 0 | R43: 174108.93 | S43: 47964.52 | T43: 3034.21 | U43: =SUM(P43:T43) -> 2390178.9 | V43: =O43-U43 -> -211431.17 | W43: 0 | X43: 7315.45 | Y43: 7315.45
A44: P360021 | B44: SIROCCO | C44: 701 | D44: 高效三 | E44: 360 | F44: Google Inc. | G44: 44357 | H44: 42198 | I44: 6124640.5 | J44: 1118520 | K44: 0 | L44: 127722.96 | M44: 0 | N44: 0 | O44: =SUM(J44:N44) -> 1246243 | P44: 1265924.4 | Q44: 0 | R44: 20103.13 | S44: 84981.03 | T44: 323487.21 | U44: =SUM(P44:T44) -> 1694495.8 | V44: =O44-U44 -> -448252.81 | W44: 3105.13 | X44: 29802.2 | Y44: 32907.33
A45: P435002 | B45: Dublin mid | C45: 701 | D45: 高效三 | E45: 330 | F45: GN Audio A/S(GSC) | G45: 44226 | H45: 42181 | I45: 2850000 | J45: 8820.55 | K45: 0 | L45: 0 | M45: 0 | N45: 0 | O45: =SUM(J45:N45) -> 8820.55 | P45: 5507.96 | Q45: 0 | R45: 4010.38 | S45: 0 | T45: 0 | U45: =SUM(P45:T45) -> 9518.34 | V45: =O45-U45 -> -697.79 | W45: 0 | X45: 0 | Y45: 0
A46: P435004 | B46: Dublin MONO | C46: 701 | D46: 高效三 | E46: 330 | F46: GN Audio A/S(GSC) | G46: 44226 | H46: 42181 | I46: 0 | J46: 386736.74 | K46: 0 | L46: 0 | M46: 0 | N46: 0 | O46: =SUM(J46:N46) -> 386736.74 | P46: 451936.53 | Q46: 0 | R46: 10187.53 | S46: 5090.93 | T46: 6521.66 | U46: =SUM(P46:T46) -> 473736.65 | V46: =O46-U46 -> -86999.91 | W46: 0 | X46: 386.12 | Y46: 386.12
A47: P435011 | B47: Rio Headset | C47: 701 | D47: 高效三 | E47: 330 | F47: GN Audio A/S(GSC) | G47: 44226 | H47: 43328 | I47: 1491440 | J47: 0 | K47: 0 | L47: 0 | M47: 0 | N47: 0 | O47: =SUM(J47:N47) -> 0 | P47: 22074 | Q47: 0 | R47: 42450.83 | S47: 3439.75 | T47: 488.6 | U47: =SUM(P47:T47) -> 68453.18 | V47: =O47-U47 -> -68453.18 | W47: 0 | X47: 498.07 | Y47: 498.07
A48: P330037 | B48: COBRANDING-RIO | C48: 701 | D48: 高效三 | E48: 330 | F48: GN Audio A/S(GSC) | G48: 44271 | H48: 43676 | I48: 847975.7 | J48: 818309.46 | K48: 0 | L48: 0 | M48: 0 | N48: 0 | O48: =SUM(J48:N48) -> 818309.46 | P48: 816748.37 | Q48: 0 | R48: 0 | S48: 0 | T48: 0 | U48: =SUM(P48:T48) -> 816748.37 | V48: =O48-U48 -> 1561.09 | W48: 0 | X48: 0 | Y48: 0
A49: P330006 | B49: Rio Base 2 | C49: 701 | D49: 高效三 | E49: 330 | F49: GN Audio A/S(GSC) | G49: 44226 | H49: 43329 | I49: 338772.5 | J49: 101136 | K49: 0 | L49: 0 | M49: 0 | N49: 0 | O49: =SUM(J49:N49) -> 101136 | P49: 113680 | Q49: 0 | R49: 9164.24 | S49: 0 | T49: 0 | U49: =SUM(P49:T49) -> 122844.24 | V49: =O49-U49 -> -21708.24 | W49: 0 | X49: 0 | Y49: 0
A50: P330038 | B50: MAPLE | C50: 701 | D50: 高效三 | E50: 330 | F50: GN Audio A/S(GSC) | G50: 44307 | H50: 42198 | I50: 1122000 | J50: 1627967.2 | K50: 0 | L50: 249150.6 | M50: 44670.51 | N50: 0 | O50: =SUM(J50:N50) -> 1921788.3 | P50: 1243267.2 | Q50: 0 | R50: 2409.01 | S50: 7319.55 | T50: 1531.89 | U50: =SUM(P50:T50) -> 1254527.6 | V50: =O50-U50 -> 667260.66 | W50: 18349.77 | X50: 13731.56 | Y50: 32081.33
A51: P330017 | B51: RIO LW | C51: 701 | D51: 高效三 | E51: 330 | F51: GN Audio A/S(GSC) | G51: 44226 | H51: 44201 | I51: 0 | J51: 0 | K51: 0 | L51: 0 | M51: 0 | N51: 0 | O51: =SUM(J51:N51) -> 0 | P51: 0 | Q51: 0 | R51: 3736.22 | S51: 0 | T51: 0 | U51: =SUM(P51:T51) -> 3736.22 | V51: =O51-U51 -> -3736.22 | W51: 0 | X51: 0 | Y51: 0
A52: P404014 | B52: BISMUTH | C52: 701 | D52: 高效三 | E52: 404 | F52: Google Inc | G52: 44334 | H52: 43328 | I52: 2469500 | J52: 398272 | K52: 0 | L52: 0 | M52: 0 | N52: 0 | O52: =SUM(J52:N52) -> 398272 | P52: 836959.2 | Q52: 0 | R52: 0 | S52: 50470.73 | T52: 132695.46 | U52: =SUM(P52:T52) -> 1020125.4 | V52: =O52-U52 -> -621853.39 | W52: 0 | X52: 6669.79 | Y52: 6669.79
A53: P360016 | B53: ETHEL | C53: 701 | D53: 高效三 | E53: 360 | F53: Google Inc. | G53: 44226 | H53: 42420 | I53: 0 | J53: 0 | K53: 0 | L53: 95648 | M53: 0 | N53: 0 | O53: =SUM(J53:N53) -> 95648 | P53: 0 | Q53: 0 | R53: 0 | S53: 1855.38 | T53: 11048 | U53: =SUM(P53:T53) -> 12903.38 | V53: =O53-U53 -> 82744.62 | W53: 0 | X53: 0 | Y53: 0
A54: P330040 | B54: SAMWISE | C54: 701 | D54: 高效三 | E54: 330 | F54: GN Audio A/S(GSC) | G54: 44482 | I54: 2709641.7 | J54: 396688.32 | K54: 0 | L54: 0 | M54: 0 | N54: 0 | O54: =SUM(J54:N54) -> 396688.32 | P54: 356643.36 | Q54: 0 | R54: 0 | S54: 187374.19 | T54: 76113.53 | U54: =SUM(P54:T54) -> 620131.08 | V54: =O54-U54 -> -223442.76 | W54: 792.09 | X54: 0 | Y54: 792.09
A55: P360019 | B55: L7 | C55: 701 | D55: 高效三 | E55: 360 | F55: Google Inc. | G55: 44226 | H55: 44432 | I55: 5132380 | J55: 0 | K55: 0 | L55: 0 | M55: 0 | N55: 0 | O55: =SUM(J55:N55) -> 0 | P55: 24899.11 | Q55: 0 | R55: 0 | S55: 79245.26 | T55: 110648.13 | U55: =SUM(P55:T55) -> 214792.5 | V55: =O55-U55 -> -214792.5 | W55: 0 | X55: 0 | Y55: 0
A56: P330003 | B56: Dublin | C56: 701 | D56: 高效三 | E56: 330 | F56: GN Audio A/S(GSC) | G56: 44226 | H56: 44400 | I56: 6221713.3 | J56: 2842038 | K56: 0 | L56: 0 | M56: 0 | N56: 0 | O56: =SUM(J56:N56) -> 2842038 | P56: 2835369 | Q56: 0 | R56: 0 | S56: 23425.26 | T56: 0 | U56: =SUM(P56:T56) -> 2858794.3 | V56: =O56-U56 -> -16756.31 | W56: 857.47 | X56: 2473.52 | Y56: 3330.99
A57: P435010 | B57: Rio Base | C57: 701 | D57: 高效三 | E57: 330 | F57: GN Audio A/S(GSC) | G57: 44226 | H57: 42551 | I57: 3166986.9 | J57: 3083056.1 | K57: 0 | L57: 0 | M57: 0 | N57: 0 | O57: =SUM(J57:N57) -> 3083056.1 | P57: 2754308.8 | Q57: 0 | R57: 4897.59 | S57: 25532.59 | T57: 0 | U57: =SUM(P57:T57) -> 2784739 | V57: =O57-U57 -> 298317.08 | W57: 13868.71 | X57: 1030.7 | Y57: 14899.41
A58: P818001 | B58: BHC656 | C58: 701 | D58: 高效三 | E58: C818 | F58: 美律电子（深圳）有限公司 | G58: 44226 | H58: 44195 | I58: 0 | J58: 0 | K58: 0 | L58: 0 | M58: 0 | N58: 0 | O58: =SUM(J58:N58) -> 0 | P58: 0 | Q58: 0 | R58: 2406.21 | S58: 0 | T58: 0 | U58: =SUM(P58:T58) -> 2406.21 | V58: =O58-U58 -> -2406.21 | W58: 0 | X58: 0 | Y58: 0
A59: P330035 | B59: ODIN | C59: 701 | D59: 高效三 | E59: 330 | F59: GN Audio A/S(GSC) | G59: 44258 | H59: 43453 | I59: 1275974.7 | J59: 862400 | K59: 0 | L59: 144300 | M59: 0 | N59: 0 | O59: =SUM(J59:N59) -> 1006700 | P59: 904736 | Q59: 0 | R59: 0 | S59: 30296.21 | T59: 261.37 | U59: =SUM(P59:T59) -> 935293.58 | V59: =O59-U59 -> 71406.42 | W59: 0 | X59: 0 | Y59: 0
A60: P330005 | B60: RIO | C60: 701 | D60: 高效三 | E60: 330 | F60: GN Audio A/S(GSC) | G60: 44226 | H60: 42373 | I60: 0 | J60: 0 | K60: 0 | L60: 0 | M60: 0 | N60: 0 | O60: =SUM(J60:N60) -> 0 | P60: 0 | Q60: 0 | R60: 0 | S60: 27400.49 | T60: 0 | U60: =SUM(P60:T60) -> 27400.49 | V60: =O60-U60 -> -27400.49 | W60: 0 | X60: 1592.36 | Y60: 1592.36
A61: P330002 | B61: Dolphin | C61: 701 | D61: 高效三 | E61: 330 | F61: GN Audio A/S(GSC) | G61: 44226 | H61: 42420 | I61: 0 | J61: 0 | K61: 0 | L61: 0 | M61: 0 | N61: 0 | O61: =SUM(J61:N61) -> 0 | P61: 0 | Q61: 0 | R61: 0 | S61: 3088.07 | T61: 0 | U61: =SUM(P61:T61) -> 3088.07 | V61: =O61-U61 -> -3088.07 | W61: 0 | X61: 0 | Y61: 0
A62: P330042 | B62: PILLOW | C62: 701 | D62: 高效三 | E62: 330 | F62: GN Audio A/S(GSC) | G62: 44496 | I62: 2368200 | J62: 0 | K62: 0 | L62: 1724.58 | M62: 0 | N62: 0 | O62: =SUM(J62:N62) -> 1724.58 | P62: 0 | Q62: 0 | R62: 0 | S62: 7477.78 | T62: 73930.55 | U62: =SUM(P62:T62) -> 81408.33 | V62: =O62-U62 -> -79683.75 | W62: 0 | X62: 0 | Y62: 0
A63: P818002 | B63: HDT666 | C63: 701 | D63: 高效三 | E63: C818 | F63: 美律电子（深圳）有限公司 | G63: 44757 | I63: 419100 | J63: 0 | K63: 0 | L63: 0 | M63: 0 | N63: 0 | O63: =SUM(J63:N63) -> 0 | P63: 0 | Q63: 0 | R63: 0 | S63: 0 | T63: 259.92 | U63: =SUM(P63:T63) -> 259.92 | V63: =O63-U63 -> -259.92 | W63: 0 | X63: 0 | Y63: 0
A64: P330009 | B64: Bezos | C64: 701 | D64: 高效三 | E64: 330 | F64: GN Audio A/S(GSC) | G64: 44226 | H64: 43577 | I64: 0 | J64: 0 | K64: 0 | L64: 0 | M64: 0 | N64: 0 | O64: =SUM(J64:N64) -> 0 | P64: 0 | Q64: 0 | R64: 0 | S64: 0 | T64: 0 | U64: =SUM(P64:T64) -> 0 | V64: =O64-U64 -> 0 | W64: 0 | X64: 47.77 | Y64: 47.77
A65: P360015 | B65: BOWIE | C65: 701 | D65: 高效三 | E65: 360 | F65: Google Inc. | G65: 44226 | H65: 42908 | I65: 0 | J65: 0 | K65: 0 | L65: 7840 | M65: 0 | N65: 0 | O65: =SUM(J65:N65) -> 7840 | P65: 0 | Q65: 0 | R65: 0 | S65: 0 | T65: 4611.71 | U65: =SUM(P65:T65) -> 4611.71 | V65: =O65-U65 -> 3228.29 | W65: 0 | X65: 0 | Y65: 0
A66: P360022 | B66: C9 | C66: 701 | D66: 高效三 | E66: 360 | F66: Google Inc. | G66: 44638 | I66: 2420000 | J66: 0 | K66: 0 | L66: 0 | M66: 0 | N66: 0 | O66: =SUM(J66:N66) -> 0 | P66: 0 | Q66: 0 | R66: 0 | S66: 0 | T66: 26923.05 | U66: =SUM(P66:T66) -> 26923.05 | V66: =O66-U66 -> -26923.05 | W66: 0 | X66: 0 | Y66: 0
A67: P861002 | B67: SQUARE | C67: 901 | D67: 高效四 | E67: C861 | F67: 深圳雾芯科技有限公司 | G67: 44623 | I67: 1304500 | J67: 0 | K67: 0 | L67: 56134.09 | M67: 0 | N67: 0 | O67: =SUM(J67:N67) -> 56134.09 | P67: 0 | Q67: 0 | R67: 0 | S67: 41683.71 | T67: 81460.01 | U67: =SUM(P67:T67) -> 123143.72 | V67: =O67-U67 -> -67009.63 | W67: 12284.01 | X67: 18361.65 | Y67: 30645.66
A68: P805012 | B68: P63B | C68: 901 | D68: 高效四 | E68: C805 | F68: 深圳市合元科技有限公司 | G68: 44226 | H68: 44208 | I68: 0 | J68: 0 | K68: 0 | L68: 12242.33 | M68: 0 | N68: 0 | O68: =SUM(J68:N68) -> 12242.33 | P68: 0 | Q68: 0 | R68: 0 | S68: 3863.84 | T68: 0 | U68: =SUM(P68:T68) -> 3863.84 | V68: =O68-U68 -> 8378.49 | W68: 39173.89 | X68: 67536.92 | Y68: 106710.81
A69: P824001 | B69: TF16 | C69: 901 | D69: 高效四 | E69: C824 | F69: NICOVENTURES TRADING LIMITED | G69: 44226 | H69: 44446 | I69: 0 | J69: 3338566 | K69: 0 | L69: 0 | M69: 0 | N69: 0 | O69: =SUM(J69:N69) -> 3338566 | P69: 2654518.1 | Q69: 0 | R69: 10828614 | S69: 102452.1 | T69: 0 | U69: =SUM(P69:T69) -> 13585585 | V69: =O69-U69 -> -10247019 | W69: 1112885 | X69: -706.73 | Y69: 1112178.3
A70: P805014 | B70: P53A | C70: 901 | D70: 高效四 | E70: C805 | F70: 深圳市合元科技有限公司 | G70: 44226 | H70: 44165 | I70: 0 | J70: 0 | K70: 0 | L70: 26786.98 | M70: 0 | N70: 0 | O70: =SUM(J70:N70) -> 26786.98 | P70: 0 | Q70: 0 | R70: 45725.82 | S70: 2638.12 | T70: 0 | U70: =SUM(P70:T70) -> 48363.94 | V70: =O70-U70 -> -21576.96 | W70: 3004.09 | X70: 11590.31 | Y70: 14594.4
A71: P805027 | B71: COROLLA | C71: 901 | D71: 高效四 | E71: C805 | F71: 深圳市合元科技有限公司 | G71: 44677 | I71: 3304000 | J71: 0 | K71: 0 | L71: 0 | M71: 0 | N71: 0 | O71: =SUM(J71:N71) -> 0 | P71: 0 | Q71: 0 | R71: 0 | S71: 3953.63 | T71: 156247.75 | U71: =SUM(P71:T71) -> 160201.38 | V71: =O71-U71 -> -160201.38 | W71: 177013.81 | X71: 3609.97 | Y71: 180623.78
A72: P814002 | B72: MAPLE | C72: 901 | D72: 高效四 | E72: C814 | F72: Pax Labs, Inc. | G72: 44226 | H72: 43969 | I72: 1950000 | J72: 188760 | K72: 0 | L72: 29338.83 | M72: 0 | N72: 0 | O72: =SUM(J72:N72) -> 218098.83 | P72: 127417.36 | Q72: 0 | R72: 131805.62 | S72: 0 | T72: 11637.7 | U72: =SUM(P72:T72) -> 270860.68 | V72: =O72-U72 -> -52761.85 | W72: 9746.4 | X72: 23863.49 | Y72: 33609.89
A73: P824002 | B73: TF1601A | C73: 901 | D73: 高效四 | E73: C824 | F73: NICOVENTURES TRADING LIMITED | G73: 44226 | H73: 44344 | I73: 825000 | J73: 0 | K73: 0 | L73: 23277.84 | M73: 0 | N73: 0 | O73: =SUM(J73:N73) -> 23277.84 | P73: 362588.98 | Q73: 0 | R73: 908645.44 | S73: 75783.11 | T73: 0 | U73: =SUM(P73:T73) -> 1347017.5 | V73: =O73-U73 -> -1323739.7 | W73: 4753.37 | X73: 2036.61 | Y73: 6789.98
A74: P805004 | B74: PANDORA | C74: 901 | D74: 高效四 | E74: C805 | F74: 深圳市合元科技有限公司 | G74: 44226 | H74: 44006 | I74: 0 | J74: 0 | K74: 0 | L74: 55177.06 | M74: 0 | N74: 0 | O74: =SUM(J74:N74) -> 55177.06 | P74: 0 | Q74: 0 | R74: 0 | S74: 3791.13 | T74: 0 | U74: =SUM(P74:T74) -> 3791.13 | V74: =O74-U74 -> 51385.93 | W74: 5317 | X74: 2274.72 | Y74: 7591.72
A75: P360006 | B75: Newman | C75: 901 | D75: 高效四 | E75: 360 | F75: Google Inc. | G75: 44226 | H75: 43655 | I75: 0 | J75: 0 | K75: 0 | L75: 0 | M75: 5229.28 | N75: 0 | O75: =SUM(J75:N75) -> 5229.28 | P75: 0 | Q75: 0 | R75: 0 | S75: 0 | T75: 0 | U75: =SUM(P75:T75) -> 0 | V75: =O75-U75 -> 5229.28 | W75: 0 | X75: 0 | Y75: 0
A76: P820001 | B76: ACE | C76: 901 | D76: 高效四 | E76: C820 | F76: NJOY, LLC. | G76: 44226 | H76: 44424 | I76: 0 | J76: 187410 | K76: 0 | L76: 0 | M76: 0 | N76: 0 | O76: =SUM(J76:N76) -> 187410 | P76: 183827.56 | Q76: 0 | R76: 130772.39 | S76: 72735.69 | T76: 0 | U76: =SUM(P76:T76) -> 387335.64 | V76: =O76-U76 -> -199925.64 | W76: 69769.27 | X76: -27251.43 | Y76: 42517.84
A77: P805016 | B77: J19 | C77: 901 | D77: 高效四 | E77: C805 | F77: 深圳市合元科技有限公司 | G77: 44226 | H77: 44406 | I77: 0 | J77: 0 | K77: 0 | L77: 0 | M77: 0 | N77: 0 | O77: =SUM(J77:N77) -> 0 | P77: 0 | Q77: 0 | R77: 0 | S77: 0 | T77: 0 | U77: =SUM(P77:T77) -> 0 | V77: =O77-U77 -> 0 | W77: 4184.4 | X77: 2938.31 | Y77: 7122.71
A78: P805022 | B78: HW42410 | C78: 901 | D78: 高效四 | E78: C805 | F78: 深圳市合元科技有限公司 | G78: 44456 | I78: 874800 | J78: 0 | K78: 0 | L78: 23270.59 | M78: 0 | N78: 0 | O78: =SUM(J78:N78) -> 23270.59 | P78: 15814.38 | Q78: 8299.71 | R78: 0 | S78: 4324.68 | T78: 64277.65 | U78: =SUM(P78:T78) -> 92716.42 | V78: =O78-U78 -> -69445.83 | W78: 0 | X78: 0 | Y78: 0
A79: P805024 | B79: PD2 | C79: 901 | D79: 高效四 | E79: C805 | F79: 深圳市合元科技有限公司 | G79: 44558 | I79: 234800 | J79: 174293.75 | K79: 0 | L79: 0 | M79: 0 | N79: 0 | O79: =SUM(J79:N79) -> 174293.75 | P79: 103746.28 | Q79: 0 | R79: 0 | S79: 0 | T79: 960.32 | U79: =SUM(P79:T79) -> 104706.6 | V79: =O79-U79 -> 69587.15 | W79: 0 | X79: 0 | Y79: 0
A80: P861001 | B80: 电子烟底座 | C80: 901 | D80: 高效四 | E80: C861 | F80: 深圳雾芯科技有限公司 | G80: 44588 | I80: 47500 | J80: 25936.58 | K80: 0 | L80: 0 | M80: 0 | N80: 0 | O80: =SUM(J80:N80) -> 25936.58 | P80: 28841.47 | Q80: 0 | R80: 0 | S80: 0 | T80: 0 | U80: =SUM(P80:T80) -> 28841.47 | V80: =O80-U80 -> -2904.89 | W80: 0 | X80: 0 | Y80: 0
A81: P805003 | B81: P52A | C81: 901 | D81: 高效四 | E81: C805 | F81: 深圳市合元科技有限公司 | G81: 44226 | H81: 44012 | I81: 0 | J81: 0 | K81: 0 | L81: 0 | M81: 0 | N81: 0 | O81: =SUM(J81:N81) -> 0 | P81: 0 | Q81: 0 | R81: 16918.63 | S81: 0 | T81: 0 | U81: =SUM(P81:T81) -> 16918.63 | V81: =O81-U81 -> -16918.63 | W81: 0 | X81: 0 | Y81: 0
A82: P824004 | B82: EPODS3 | C82: 901 | D82: 高效四 | E82: C824 | F82: NICOVENTURES TRADING LIMITED | G82: 44543 | I82: 1401100 | J82: 0 | K82: 0 | L82: 138183.14 | M82: 0 | N82: 0 | O82: =SUM(J82:N82) -> 138183.14 | P82: 0 | Q82: 0 | R82: 2012.96 | S82: 14849.39 | T82: 103148.91 | U82: =SUM(P82:T82) -> 120011.26 | V82: =O82-U82 -> 18171.88 | W82: 0 | X82: 74837.28 | Y82: 74837.28
A83: P360009 | B83: SABRINA | C83: 901 | D83: 高效四 | E83: 360 | F83: Google Inc. | G83: 44226 | H83: 43999 | I83: 0 | J83: 0 | K83: 0 | L83: 0 | M83: 0 | N83: 0 | O83: =SUM(J83:N83) -> 0 | P83: 0 | Q83: 0 | R83: -9442.03 | S83: 0 | T83: 0 | U83: =SUM(P83:T83) -> -9442.03 | V83: =O83-U83 -> 9442.03 | W83: 0 | X83: 0 | Y83: 0
A84: P820002 | B84: AK02 | C84: 901 | D84: 高效四 | E84: C820 | F84: NJOY, LLC. | G84: 44487 | I84: 284500 | J84: 195750 | K84: 0 | L84: 0 | M84: 0 | N84: 0 | O84: =SUM(J84:N84) -> 195750 | P84: 176175 | Q84: 0 | R84: 0 | S84: 0 | T84: 0 | U84: =SUM(P84:T84) -> 176175 | V84: =O84-U84 -> 19575 | W84: 0 | X84: 0 | Y84: 0
A85: P805001 | B85: LD 1.5 | C85: 901 | D85: 高效四 | E85: C805 | F85: 深圳市合元科技有限公司 | G85: 44226 | H85: 44012 | I85: 0 | J85: 0 | K85: 0 | L85: 0 | M85: 0 | N85: 0 | O85: =SUM(J85:N85) -> 0 | P85: 0 | Q85: 0 | R85: 0 | S85: 0 | T85: 0 | U85: =SUM(P85:T85) -> 0 | V85: =O85-U85 -> 0 | W85: 14676.25 | X85: 0 | Y85: 14676.25
A86: P805025 | B86: MOTO | C86: 901 | D86: 高效四 | E86: C805 | F86: 深圳市合元科技有限公司 | G86: 44652 | I86: 6218750 | J86: 0 | K86: 0 | L86: 226171.92 | M86: 0 | N86: 0 | O86: =SUM(J86:N86) -> 226171.92 | P86: 0 | Q86: 0 | R86: 0 | S86: 132959.2 | T86: 465247.73 | U86: =SUM(P86:T86) -> 598206.93 | V86: =O86-U86 -> -372035.01 | W86: 8725.86 | X86: 363.11 | Y86: 9088.97
A87: P805023 | B87: KFC | C87: 901 | D87: 高效四 | E87: C805 | F87: 深圳市合元科技有限公司 | G87: 44461 | I87: 136000 | J87: 0 | K87: 0 | L87: 44971.4 | M87: 0 | N87: 0 | O87: =SUM(J87:N87) -> 44971.4 | P87: 0 | Q87: 0 | R87: 0 | S87: 0 | T87: 0 | U87: =SUM(P87:T87) -> 0 | V87: =O87-U87 -> 44971.4 | W87: 0 | X87: 0 | Y87: 0
A88: P391001 | B88: GENEVA | C88: 300 | D88: 特种一 | E88: 391 | F88: Latch Systems, Inc. | G88: 44226 | H88: 44301 | I88: 0 | J88: 0 | K88: 0 | L88: 0 | M88: 0 | N88: 0 | O88: =SUM(J88:N88) -> 0 | P88: 0 | Q88: 0 | R88: 21891.7 | S88: 8622.09 | T88: 0 | U88: =SUM(P88:T88) -> 30513.79 | V88: =O88-U88 -> -30513.79 | W88: 17037.61 | X88: 14007.24 | Y88: =X88+W88 -> 31044.85
A89: P360008 | B89: ELAINE | C89: 300 | D89: 特种一 | E89: 360 | F89: Google Inc. | G89: 44226 | H89: 44237 | I89: 711496.5 | J89: 0 | K89: 0 | L89: 49117.2 | M89: 0 | N89: 10035.2 | O89: =SUM(J89:N89) -> 59152.4 | P89: 0 | Q89: 0 | R89: 60202.31 | S89: 5711.67 | T89: 0 | U89: =SUM(P89:T89) -> 65913.98 | V89: =O89-U89 -> -6761.58 | W89: 51113.61 | X89: 15756.34 | Y89: =X89+W89 -> 66869.95
A90: P404006 | B90: D3 | C90: 300 | D90: 特种一 | E90: 404 | F90: Google Inc | G90: 44226 | H90: 42657 | I90: 0 | J90: 0 | K90: 0 | L90: 0 | M90: 0 | N90: 0 | O90: =SUM(J90:N90) -> 0 | P90: 0 | Q90: 0 | R90: 61248.97 | S90: 3853.05 | T90: 0 | U90: =SUM(P90:T90) -> 65102.02 | V90: =O90-U90 -> -65102.02 | W90: 130920.84 | X90: 21751.13 | Y90: =X90+W90 -> 152671.97
A91: P404003 | B91: BOSS | C91: 300 | D91: 特种一 | E91: 404 | F91: Google Inc | G91: 44226 | H91: 44034 | I91: 0 | J91: 0 | K91: 0 | L91: 0 | M91: 0 | N91: 0 | O91: =SUM(J91:N91) -> 0 | P91: 0 | Q91: 0 | R91: 71803.6 | S91: 3347.99 | T91: 735.31 | U91: =SUM(P91:T91) -> 75886.9 | V91: =O91-U91 -> -75886.9 | W91: 36530.9 | X91: 0 | Y91: =X91+W91 -> 36530.9
A92: P437029 | B92: MORGAN | C92: 300 | D92: 特种一 | E92: 437 | F92: Fitbit Inc. | G92: 44226 | H92: 44407 | I92: 283800 | J92: 0 | K92: 0 | L92: 0 | M92: 0 | N92: 0 | O92: =SUM(J92:N92) -> 0 | P92: 0 | Q92: 0 | R92: 157786.33 | S92: 29302.25 | T92: 0 | U92: =SUM(P92:T92) -> 187088.58 | V92: =O92-U92 -> -187088.58 | W92: 31564.07 | X92: 0 | Y92: =X92+W92 -> 31564.07
A93: P437028 | B93: BUZZ | C93: 300 | D93: 特种一 | E93: 437 | F93: Fitbit Inc. | G93: 44226 | H93: 44364 | I93: 0 | J93: 0 | K93: 0 | L93: 0 | M93: 0 | N93: 0 | O93: =SUM(J93:N93) -> 0 | P93: 0 | Q93: 0 | R93: 18852.24 | S93: 3921.16 | T93: 0 | U93: =SUM(P93:T93) -> 22773.4 | V93: =O93-U93 -> -22773.4 | W93: 9435.12 | X93: 0 | Y93: =X93+W93 -> 9435.12
A94: P437021 | B94: Atlas | C94: 300 | D94: 特种一 | E94: 437 | F94: Fitbit Inc. | G94: 44226 | H94: 44042 | I94: 0 | J94: 0 | K94: 0 | L94: 0 | M94: 0 | N94: 0 | O94: =SUM(J94:N94) -> 0 | P94: 0 | Q94: 0 | R94: 17663.27 | S94: 0 | T94: 0 | U94: =SUM(P94:T94) -> 17663.27 | V94: =O94-U94 -> -17663.27 | W94: 876.12 | X94: 0 | Y94: =X94+W94 -> 876.12
A95: P440057 | B95: RAMV-0041 | C95: 300 | D95: 特种一 | E95: 440 | F95: Otter Products LLC (for mold) | G95: 44329 | H95: 44431 | I95: 3140500 | J95: 0 | K95: 0 | L95: 30151.4 | M95: 0 | N95: 0 | O95: =SUM(J95:N95) -> 30151.4 | P95: 0 | Q95: 0 | R95: 0 | S95: 2599.62 | T95: 186681.1 | U95: =SUM(P95:T95) -> 189280.72 | V95: =O95-U95 -> -159129.32 | W95: 8157.99 | X95: 0 | Y95: =X95+W95 -> 8157.99
A96: P440046 | B96: SHAMROCK | C96: 300 | D96: 特种一 | E96: 440 | F96: Otter Products LLC (for mold) | G96: 44226 | H96: 44169 | I96: 0 | J96: 1223824 | K96: 0 | L96: 0 | M96: 0 | N96: 0 | O96: =SUM(J96:N96) -> 1223824 | P96: 1016064 | Q96: 0 | R96: 0 | S96: 0 | T96: 118.9 | U96: =SUM(P96:T96) -> 1016182.9 | V96: =O96-U96 -> 207641.1 | W96: 829.96 | X96: 0 | Y96: =X96+W96 -> 829.96
A97: P440060 | B97: RAMV-0227 | C97: 300 | D97: 特种一 | E97: 440 | F97: Otter Products LLC (for mold) | G97: 44329 | H97: 44431 | I97: 8536000 | J97: 390432 | K97: 0 | L97: 23128 | M97: 35145 | N97: 0 | O97: =SUM(J97:N97) -> 448705 | P97: 371616 | Q97: 0 | R97: 6540.74 | S97: 28063.98 | T97: 54179.22 | U97: =SUM(P97:T97) -> 460399.94 | V97: =O97-U97 -> -11694.94 | W97: 153342.79 | X97: 3292.86 | Y97: =X97+W97 -> 156635.65
A98: P440068 | B98: FACETOFACE-0041 | C98: 300 | D98: 特种一 | E98: 440 | F98: Otter Products LLC (for mold) | G98: 44446 | H98: 44581 | I98: 3011964 | J98: 3112480 | K98: 0 | L98: 0 | M98: 117000 | N98: 0 | O98: =SUM(J98:N98) -> 3229480 | P98: 2769777.9 | Q98: 0 | R98: 0 | S98: 866.54 | T98: 303206.71 | U98: =SUM(P98:T98) -> 3073851.2 | V98: =O98-U98 -> 155628.83 | W98: 0 | X98: 23329.26 | Y98: =X98+W98 -> 23329.26
A99: P404008 | B99: Onxy | C99: 300 | D99: 特种一 | E99: 404 | F99: Google Inc | G99: 44226 | H99: 43003 | I99: 0 | J99: 0 | K99: 0 | L99: 0 | M99: 0 | N99: 0 | O99: =SUM(J99:N99) -> 0 | P99: 0 | Q99: 0 | R99: 0 | S99: 0 | T99: 0 | U99: =SUM(P99:T99) -> 0 | V99: =O99-U99 -> 0 | W99: 8037.92 | X99: 0 | Y99: =X99+W99 -> 8037.92
... A108: P437020 | B108: MIRA | C108: 300 | D108: 特种一 | E108: 437 | F108: Fitbit Inc. | G108: 44226 | H108: 43993 | I108: 0 | J108: 0 | K108: 0 | L108: 0 | M108: 0 | N108: 0 | O108: =SUM(J108:N108) -> 0 | P108: 0 | Q108: 0 | R108: 178818.16 | S108: 0 | T108: 0 | U108: =SUM(P108:T108) -> 178818.16 | V108: =O108-U108 -> -178818.16 | W108: 4015.52 | X108: 0 | Y108: =X108+W108 -> 4015.52
...

Sheet HP1
A1: HP1 2024年1-6月NPI明细
A2: 币别:HKD
A3: TK项目号 | B3: 项目名称 | C3: 利润中心 | D3: 事业部 | E3: 终端客户 | F3: 终端客户名称 | G3: 创建日期 | H3: 量产日期 | I3: NPI预算收入 | J3: 注塑模具收入 | K3: 其他模具收入 | L3: 样板费收入 | M3: 夹治具收入 | N3: 其它杂项收入 | O3: 量产前收入 | P3: 注塑模具成本 | Q3: 其他模具成本 | R3: 自费模具摊销 | S3: 量产前夹治具成本 | T3: 试模成本 | U3: 量产前成本 | V3: 量产前收益 | W3: 量产后夹治具成本 | X3: 量产后打样成本 | Y3: 量产后成本 | Z3: 项目收益
A4: P208001 | B4: 韶音 | C4: 100 | D4: 高效一 | E4: C208 | F4: 深圳市韶音科技有限公司 | G4: 44226 | H4: 44004 | I4: 0 | J4: 0 | K4: 0 | L4: 36330.73 | M4: 0 | N4: 0 | O4: 36330.73 | P4: 0 | Q4: 0 | R4: 2984.41 | S4: 0 | T4: 0 | U4: 2984.41 | V4: 33346.32 | W4: 0 | X4: 0 | Y4: 0 | Z4: =V4-Y4 -> 33346.32
A5: P208002 | B5: SE | C5: 100 | D5: 高效一 | E5: C208 | F5: 深圳市韶音科技有限公司 | G5: 44226 | H5: 43888 | I5: 2664684 | J5: 9708.74 | K5: 0 | L5: 0 | M5: 0 | N5: 0 | O5: 9708.74 | P5: 0 | Q5: 0 | R5: 2355.01 | S5: 0 | T5: 0 | U5: 2355.01 | V5: 7353.73 | W5: 0 | X5: 68.2 | Y5: 68.2 | Z5: =V5-Y5 -> 7285.53
A6: P208003 | B6: VIE | C6: 100 | D6: 高效一 | E6: C208 | F6: 深圳市韶音科技有限公司 | G6: 44226 | H6: 44223 | I6: 9839800 | J6: 40021.57 | K6: 0 | L6: 0 | M6: 0 | N6: 0 | O6: 40021.57 | P6: 31503.28 | Q6: 0 | R6: 21366.23 | S6: 0 | T6: 0 | U6: 52869.51 | V6: -12847.94 | W6: 0 | X6: 41912.38 | Y6: 41912.38 | Z6: =V6-Y6 -> -54760.32
A7: P208004 | B7: TT0 | C7: 100 | D7: 高效一 | E7: C208 | F7: 深圳市韶音科技有限公司 | G7: 44306 | H7: 44403 | I7: 1058000 | J7: 0 | K7: 0 | L7: -3.24 | M7: 0 | N7: 0 | O7: -3.24 | P7: 0 | Q7: 0 | R7: 0 | S7: 0 | T7: 0 | U7: 0 | V7: -3.24 | W7: 0 | X7: 0 | Y7: 0 | Z7: =V7-Y7 -> -3.24
A8: P208008 | B8: PARIS | C8: 100 | D8: 高效一 | E8: C208 | F8: 深圳市韶音科技有限公司 | G8: 44628 | I8: 3825000 | J8: 7055.03 | K8: 0 | L8: 0 | M8: 0 | N8: 0 | O8: 7055.03 | P8: 0 | Q8: 0 | R8: 5660.3 | S8: 0 | T8: 0 | U8: 5660.3 | V8: 1394.73 | W8: 0 | X8: 275.41 | Y8: 275.41 | Z8: =V8-Y8 -> 1119.32
A9: P208009 | B9: HSD | C9: 100 | D9: 高效一 | E9: C208 | F9: 深圳市韶音科技有限公司 | G9: 44799 | I9: 2874000 | J9: 4314.99 | K9: 0 | L9: -1441.24 | M9: 0 | N9: 0 | O9: 2873.75 | P9: 0 | Q9: 0 | R9: 7318.74 | S9: 0 | T9: 0 | U9: 7318.74 | V9: -4444.99 | W9: 0 | X9: 395.44 | Y9: 395.44 | Z9: =V9-Y9 -> -4840.43
A10: P208010 | B10: CWS | C10: 100 | D10: 高效一 | E10: C208 | F10: 深圳市韶音科技有限公司 | G10: 44883 | I10: 18946800 | J10: 194150.34 | K10: 0 | L10: -62091.47 | M10: 0 | N10: 0 | O10: 132058.87 | P10: 206267.3 | Q10: 0 | R10: 87427.72 | S10: 477.32 | T10: 0 | U10: 294172.34 | V10: -162113.47 | W10: 0 | X10: 25997.1 | Y10: 25997.1 | Z10: =V10-Y10 -> -188110.57
A11: P330010 | B11: Spiderman | C11: 100 | D11: 高效一 | E11: 330 | F11: GN Audio A/S(GSC) | G11: 44226 | H11: 44180 | I11: 94000 | J11: 0 | K11: 0 | L11: 0 | M11: 0 | N11: 0 | O11: 0 | P11: 0 | Q11: 0 | R11: 1267.94 | S11: 0 | T11: 0 | U11: 1267.94 | V11: -1267.94 | W11: 0 | X11: 0 | Y11: 0 | Z11: =V11-Y11 -> -1267.94
A12: P330014 | B12: YOSHI | C12: 100 | D12: 高效一 | E12: 330 | F12: GN Audio A/S(GSC) | G12: 44226 | H12: 43969 | I12: 0 | J12: 0 | K12: 0 | L12: 0 | M12: 0 | N12: 0 | O12: 0 | P12: 0 | Q12: 0 | R12: 0 | S12: 0 | T12: 0 | U12: 0 | V12: 0 | W12: 0 | X12: 0 | Y12: 0 | Z12: =V12-Y12 -> 0
A13: P330021 | B13: ASTRA | C13: 100 | D13: 高效一 | E13: 330 | F13: GN Audio A/S(GSC) | G13: 44226 | H13: 42328 | I13: 80819400 | J13: 0 | K13: 0 | L13: 0 | M13: 0 | N13: 0 | O13: 0 | P13: 0 | Q13: 0 | R13: 2344.7 | S13: 27211.28 | T13: 0 | U13: 29555.98 | V13: -29555.98 | W13: 0 | X13: 0 | Y13: 0 | Z13: =V13-Y13 -> -29555.98
A14: P330036 | B14: COBRANDING-SPIDERMAN | C14: 100 | D14: 高效一 | E14: 330 | F14: GN Audio A/S(GSC) | G14: 44271 | H14: 42431 | I14: 0 | J14: 0 | K14: 0 | L14: 0 | M14: 0 | N14: 0 | O14: 0 | P14: 0 | Q14: 0 | R14: 0 | S14: 0 | T14: 0 | U14: 0 | V14: 0 | W14: 0 | X14: 0 | Y14: 0 | Z14: =V14-Y14 -> 0
A15: P330041 | B15: WILLOW | C15: 100 | D15: 高效一 | E15: 330 | F15: GN Audio A/S(GSC) | G15: 44487 | H15: 44928 | I15: 50367000 | J15: 43635.9 | K15: 0 | L15: 0 | M15: 0 | N15: 0 | O15: 43635.9 | P15: 42091.21 | Q15: 0 | R15: 21652.58 | S15: 20047.54 | T15: 0 | U15: 83791.33 | V15: -40155.43 | W15: 0 | X15: 2116.79 | Y15: 2116.79 | Z15: =V15-Y15 -> -42272.22
A16: P360020 | B16: BOREAL | C16: 100 | D16: 高效一 | E16: 360 | F16: Google Inc. | G16: 44226 | H16: 42620 | I16: 0 | J16: 0 | K16: 0 | L16: 0 | M16: 0 | N16: 0 | O16: 0 | P16: 0 | Q16: 0 | R16: 0 | S16: 0 | T16: 0 | U16: 0 | V16: 0 | W16: 0 | X16: 0 | Y16: 0 | Z16: =V16-Y16 -> 0
A17: P435004 | B17: Dublin MONO | C17: 100 | D17: 高效一 | E17: 330 | F17: GN Audio A/S(GSC) | G17: 44226 | H17: 42181 | I17: 0 | J17: 1926748.6 | K17: 0 | L17: 0 | M17: 0 | N17: 0 | O17: 1926748.6 | P17: 1138252 | Q17: 0 | R17: 25728.59 | S17: 41557.25 | T17: 0 | U17: 1205537.8 | V17: 721210.76 | W17: 0 | X17: 2192 | Y17: 2192 | Z17: =V17-Y17 -> 719018.76
A18: P831001 | B18: PANDORA | C18: 100 | D18: 高效一 | E18: C831 | F18: August Home, Inc. | G18: 44264 | H18: 44288 | I18: 11536523 | J18: 0 | K18: 0 | L18: 2755.7 | M18: 0 | N18: 0 | O18: 2755.7 | P18: 0 | Q18: 0 | R18: 6022.62 | S18: 6587.04 | T18: 0 | U18: 12609.66 | V18: -9853.96 | W18: 0 | X18: 17481.01 | Y18: 17481.01 | Z18: =V18-Y18 -> -27334.97
A19: P860005 | B19: PELICAN | C19: 100 | D19: 高效一 | E19: C860 | F19: 通力科技股份有限公司 | G19: 44818 | I19: 6430600 | J19: 32327.59 | K19: 0 | L19: 0 | M19: 0 | N19: 0 | O19: 32327.59 | P19: 60665.25 | Q19: 0 | R19: 35172.61 | S19: 4773.22 | T19: 31671.48 | U19: 132282.56 | V19: -99954.97 | W19: 0 | X19: 3581.82 | Y19: 3581.82 | Z19: =V19-Y19 -> -103536.79
A20: P862001 | B20: PSC56一体机 | C20: 100 | D20: 高效一 | E20: C862 | F20: 影石创新科技股份有限公司 | G20: 44606 | I20: 10261764 | J20: 71780.15 | K20: 0 | L20: 2357.61 | M20: 0 | N20: 0 | O20: 74137.76 | P20: 14455.23 | Q20: 0 | R20: 10491.48 | S20: 19378.5 | T20: 0 | U20: 44325.21 | V20: 29812.55 | W20: 0 | X20: 0 | Y20: 0 | Z20: =V20-Y20 -> 29812.55
A21: P862002 | B21: IAC2 | C21: 100 | D21: 高效一 | E21: C862 | F21: 影石创新科技股份有限公司 | G21: 44776 | I21: 7687368 | J21: 1116823.7 | K21: 0 | L21: 449.11 | M21: 0 | N21: 0 | O21: 1117272.8 | P21: 1275993.2 | Q21: 0 | R21: 8878.75 | S21: 0 | T21: 549.65 | U21: 1285421.6 | V21: -168148.78 | W21: 0 | X21: 11459.88 | Y21: 11459.88 | Z21: =V21-Y21 -> -179608.66
A22: P869003 | B22: FI05 | C22: 100 | D22: 高效一 | E22: C869 | F22: 深圳市爱立康医疗股份有限公司 | G22: 44825 | I22: 1059000 | J22: 248207.23 | K22: 0 | L22: 0 | M22: 0 | N22: 2863.94 | O22: 251071.17 | P22: 401510.24 | Q22: 0 | R22: 493.89 | S22: 0 | T22: -487.47 | U22: 401516.66 | V22: -150445.49 | W22: 0 | X22: 0 | Y22: 0 | Z22: =V22-Y22 -> -150445.49
A23: P884001 | B23: GFD | C23: 100 | D23: 高效一 | E23: C884 | F23: Glowforge,Inc. | G23: 44931 | I23: 3574500 | J23: 0 | K23: 0 | L23: 4084.5 | M23: 0 | N23: 0 | O23: 4084.5 | P23: 0 | Q23: 0 | R23: 3038.72 | S23: 0 | T23: 0 | U23: 3038.72 | V23: 1045.78 | W23: 0 | X23: 0 | Y23: 0 | Z23: =V23-Y23 -> 1045.78
A24: P869001 | B24: FI02 | C24: 100 | D24: 高效一 | E24: C869 | F24: 深圳市爱立康医疗股份有限公司 | G24: 44777 | I24: 214700 | J24: 0 | K24: 0 | L24: 0 | M24: 0 | N24: 0 | O24: 0 | P24: 0 | Q24: 0 | R24: 0 | S24: 0 | T24: 0 | U24: 0 | V24: 0 | W24: 0 | X24: 0 | Y24: 0 | Z24: =V24-Y24 -> 0
A25: P330044 | B25: ELFIN | C25: 100 | D25: 高效一 | E25: 330 | F25: GN Audio A/S(GSC) | G25: 44973 | I25: 44000 | J25: 0 | K25: 0 | L25: 0 | M25: 0 | N25: 0 | O25: 0 | P25: 0 | Q25: 0 | R25: 0 | S25: 0 | T25: 0 | U25: 0 | V25: 0 | W25: 0 | X25: 0 | Y25: 0 | Z25: =V25-Y25 -> 0
A26: P208007 | B26: WHARF左右耳挂 | C26: 100 | D26: 高效一 | E26: C208 | F26: 深圳市韶音科技有限公司 | G26: 44613 | I26: 242000 | J26: 0 | K26: 0 | L26: 0 | M26: 0 | N26: 0 | O26: 0 | P26: 0 | Q26: 0 | R26: 0 | S26: 0 | T26: -527.39 | U26: -527.39 | V26: 527.39 | W26: 0 | X26: 0 | Y26: 0 | Z26: =V26-Y26 -> 527.39
A27: P208011 | B27: HUGO | C27: 100 | D27: 高效一 | E27: C208 | F27: 深圳市韶音科技有限公司 | G27: 44971 | I27: 212600 | J27: 245709.88 | K27: 0 | L27: -38.13 | M27: 0 | N27: 0 | O27: 245671.75 | P27: 217391.3 | Q27: 0 | R27: 0 | S27: 0 | T27: 0 | U27: 217391.3 | V27: 28280.45 | W27: 0 | X27: 0 | Y27: 0 | Z27: =V27-Y27 -> 28280.45
A28: P330020 | B28: Leo | C28: 100 | D28: 高效一 | E28: 330 | F28: GN Audio A/S(GSC) | G28: 44226 | H28: 44371 | I28: 0 | J28: 0 | K28: 0 | L28: 0 | M28: 0 | N28: 0 | O28: 0 | P28: 0 | Q28: 0 | R28: 0 | S28: 0 | T28: -11074.03 | U28: -11074.03 | V28: 11074.03 | W28: 0 | X28: 0 | Y28: 0 | Z28: =V28-Y28 -> 11074.03
A29: P860006 | B29: TM04 | C29: 100 | D29: 高效一 | E29: C860 | F29: 通力科技股份有限公司 | G29: 44977 | I29: 222200 | J29: 153985.87 | K29: 0 | L29: 0 | M29: 0 | N29: 0 | O29: 153985.87 | P29: 0 | Q29: 0 | R29: 0 | S29: 0 | T29: 0 | U29: 0 | V29: 153985.87 | W29: 0 | X29: 0 | Y29: 0 | Z29: =V29-Y29 -> 153985.87
A30: P860008 | B30: SONY HDX2981 | C30: 100 | D30: 高效一 | E30: C860 | F30: 通力科技股份有限公司 | G30: 45049 | I30: 2457000 | J30: 2419782.6 | K30: 0 | L30: 25587.07 | M30: 0 | N30: 0 | O30: 2445369.7 | P30: 3999366.5 | Q30: 0 | R30: 8283.06 | S30: -58335.24 | T30: 149873.15 | U30: 4099187.5 | V30: -1653817.8 | W30: 0 | X30: 20725.47 | Y30: 20725.47 | Z30: =V30-Y30 -> -1674543.3
A31: P330008 | B31: Binary HB | C31: 100 | D31: 高效一 | E31: 330 | F31: GN Audio A/S(GSC) | G31: 44226 | H31: 43266 | I31: 0 | J31: 0 | K31: 0 | L31: 0 | M31: 0 | N31: 0 | O31: 0 | P31: 0 | Q31: 0 | R31: 2445.26 | S31: 0 | T31: 0 | U31: 2445.26 | V31: -2445.26 | W31: 0 | X31: 0 | Y31: 0 | Z31: =V31-Y31 -> -2445.26
A32: P831003 | B32: NEST 1.5 | C32: 100 | D32: 高效一 | E32: C831 | F32: August Home, Inc. | G32: 44411 | I32: 1611280 | J32: 0 | K32: 0 | L32: 0 | M32: 0 | N32: 0 | O32: 0 | P32: 0 | Q32: 0 | R32: 5750.9 | S32: 0 | T32: 0 | U32: 5750.9 | V32: -5750.9 | W32: 0 | X32: 0 | Y32: 0 | Z32: =V32-Y32 -> -5750.9
A33: P208005 | B33: MYLEZ | C33: 100 | D33: 高效一 | E33: C208 | F33: 深圳市韶音科技有限公司 | G33: 44526 | I33: 0 | J33: 0 | K33: 0 | L33: 0 | M33: 0 | N33: 0 | O33: 0 | P33: 0 | Q33: 0 | R33: 0 | S33: 0 | T33: 0 | U33: 0 | V33: 0 | W33: 0 | X33: 0 | Y33: 0 | Z33: =V33-Y33 -> 0
A34: P330047 | B34: ASTRA PRO | C34: 100 | D34: 高效一 | E34: 330 | F34: GN Audio A/S(GSC) | G34: 45145 | I34: 0 | J34: 54600 | K34: 0 | L34: 639.6 | M34: 0 | N34: 0 | O34: 55239.6 | P34: 51480 | Q34: 0 | R34: 0 | S34: 8878.21 | T34: 1243.98 | U34: 61602.19 | V34: -6362.59 | W34: 0 | X34: 4937.84 | Y34: 4937.84 | Z34: =V34-Y34 -> -11300.43
A35: P250064 | B35: CZ460 | C35: 100 | D35: 高效一 | E35: 250 | F35: Western Digital Technologies,I | G35: 44226 | H35: 43566 | I35: 0 | J35: 0 | K35: 0 | L35: 0 | M35: 0 | N35: 0 | O35: 0 | P35: 0 | Q35: 0 | R35: 0 | S35: 0 | T35: 0 | U35: 0 | V35: 0 | W35: 0 | X35: 0 | Y35: 0 | Z35: =V35-Y35 -> 0
A36: P370001 | B36: Wrist Worn | C36: 100 | D36: 高效一 | E36: 370 | F36: Ava AG | G36: 44226 | H36: 43630 | I36: 616000 | J36: 0 | K36: 0 | L36: 0 | M36: 0 | N36: 0 | O36: 0 | P36: 0 | Q36: 0 | R36: 0 | S36: 0 | T36: 0 | U36: 0 | V36: 0 | W36: 0 | X36: 0 | Y36: 0 | Z36: =V36-Y36 -> 0
A37: P250059 | B37: CZ57 | C37: 100 | D37: 高效一 | E37: 25001 | F37: Western Digital Technologies,Inc. | G37: 0 | H37: 0 | I37: 0 | J37: 0 | K37: 0 | L37: 0 | M37: 0 | N37: 0 | O37: 0 | P37: 0 | Q37: 0 | R37: 0 | S37: 0 | T37: 0 | U37: 0 | V37: 0 | W37: 0 | X37: 0 | Y37: 0 | Z37: =V37-Y37 -> 0
A38: P250063 | B38: Rugged | C38: 100 | D38: 高效一 | E38: 25011 | F38: Western Digital Technologies,Inc. | G38: 0 | H38: 0 | J38: 0 | K38: 0 | L38: 0 | M38: 0 | N38: 0 | O38: 0 | P38: 0 | Q38: 0 | R38: 0 | S38: 0 | T38: 0 | U38: 0 | V38: 0 | W38: 0 | X38: 0 | Y38: 0 | Z38: =V38-Y38 -> 0
A39: P360004 | B39: Gotham | C39: 100 | D39: 高效一 | E39: 360 | F39: Google Inc. | G39: 44226 | H39: 43761 | I39: 0 | J39: 0 | K39: 0 | L39: 0 | M39: 0 | N39: 0 | O39: 0 | P39: 0 | Q39: 0 | R39: 7221.44 | S39: 0 | T39: 0 | U39: 7221.44 | V39: -7221.44 | W39: 0 | X39: 0 | Y39: 0 | Z39: =V39-Y39 -> -7221.44
A40: P876001 | B40: BHP701 | C40: 100 | D40: 高效一 | E40: C876 | F40: Sonos, Inc. | G40: 44830 | I40: 13348000 | J40: 0 | K40: 0 | L40: 0 | M40: 0 | N40: 0 | O40: 0 | P40: 0 | Q40: 0 | R40: 0 | S40: 0 | T40: 0 | U40: 0 | V40: 0 | W40: 0 | X40: 0 | Y40: 0 | Z40: =V40-Y40 -> 0
A41: P268033 | B41: C77/C65/A131/A136 | C41: 100 | D41: 高效一 | E41: C268 | F41: Apple Inc. | G41: 44226 | H41: 44012 | I41: 0 | J41: 0 | K41: 0 | L41: 0 | M41: 0 | N41: 0 | O41: 0 | P41: 0 | Q41: 0 | R41: 0 | S41: 0 | T41: 0 | U41: 0 | V41: 0 | W41: 0 | X41: 0 | Y41: 0 | Z41: =V41-Y41 -> 0
A42: P330012 | B42: TITAN | C42: 100 | D42: 高效一 | E42: 330 | F42: GN Audio A/S(GSC) | G42: 44226 | H42: 43941 | I42: 0 | J42: 0 | K42: 0 | L42: 0 | M42: 0 | N42: 0 | O42: 0 | P42: 0 | Q42: 0 | R42: 130993.87 | S42: 0 | T42: 0 | U42: 130993.87 | V42: -130993.87 | W42: 0 | X42: 0 | Y42: 0 | Z42: =V42-Y42 -> -130993.87
A43: P208013 | B43: BOS | C43: 100 | D43: 高效一 | E43: C208 | F43: 深圳市韶音科技有限公司 | G43: 45212 | I43: 1554800 | J43: 0 | K43: 0 | L43: 143819.1 | M43: 0 | N43: 0 | O43: 143819.1 | P43: 0 | Q43: 0 | R43: 0 | S43: 64443.36 | T43: 143522.28 | U43: 207965.64 | V43: -64146.54 | W43: 240.31 | X43: 0 | Y43: 240.31 | Z43: =V43-Y43 -> -64386.85
A44: P208012 | B44: CCT | C44: 100 | D44: 高效一 | E44: C208 | F44: 深圳市韶音科技有限公司 | G44: 45175 | I44: 1030000 | J44: 0 | K44: 0 | L44: 3774.12 | M44: 0 | N44: 0 | O44: 3774.12 | P44: 0 | Q44: 0 | R44: 0 | S44: 19340.93 | T44: 49922.07 | U44: 69263 | V44: -65488.88 | W44: 0 | X44: 25278.62 | Y44: 25278.62 | Z44: =V44-Y44 -> -90767.5
A45: P330045 | B45: DUBLIN | C45: 100 | D45: 高效一 | E45: 330 | F45: GN Audio A/S(GSC) | G45: 45086 | I45: 589600 | J45: 598527.16 | K45: 0 | L45: 0 | M45: 0 | N45: 0 | O45: 598527.16 | P45: 574816 | Q45: 0 | R45: 0 | S45: 0 | T45: 0 | U45: 574816 | V45: 23711.16 | W45: 0 | X45: 127.34 | Y45: 127.34 | Z45: =V45-Y45 -> 23583.82
A46: P330048 | B46: POLARIS | C46: 100 | D46: 高效一 | E46: 330 | F46: GN Audio A/S(GSC) | G46: 45247 | I46: 690000 | J46: 19859.55 | K46: 0 | L46: 4825.47 | M46: 0 | N46: 0 | O46: 24685.02 | P46: 9130 | Q46: 0 | R46: 388.01 | S46: 0 | T46: 12263.69 | U46: 21781.7 | V46: 2903.32 | W46: 0 | X46: 975.2 | Y46: 975.2 | Z46: =V46-Y46 -> 1928.12
A47: P208014 | B47: SEAL | C47: 100 | D47: 高效一 | E47: C208 | F47: 深圳市韶音科技有限公司 | G47: 45212 | I47: 188500 | J47: 139224.13 | K47: 0 | L47: 33402.65 | M47: 11455.74 | N47: 0 | O47: 184082.52 | P47: 146681.03 | Q47: 0 | R47: 0 | S47: 26407.66 | T47: 5903.83 | U47: 178992.52 | V47: 5090 | W47: 0 | X47: 0 | Y47: 0 | Z47: =V47-Y47 -> 5090
A48: P907002 | B48: 668 | C48: 100 | D48: 高效一 | E48: C907 | F48: 索尼电子 | G48: 45282 | I48: 1140000 | J48: 999025.87 | K48: 0 | L48: 33272.32 | M48: 0 | N48: 0 | O48: 1032298.2 | P48: 1063793.1 | Q48: 0 | R48: 2810.7 | S48: 7096.56 | T48: 43775.84 | U48: 1117476.2 | V48: -85178.02 | W48: 0 | X48: 0 | Y48: 0 | Z48: =V48-Y48 -> -85178.02
A49: P330016 | B49: FREJA | C49: 100 | D49: 高效一 | E49: 330 | F49: GN Audio A/S(GSC) | G49: 44226 | H49: 44209 | I49: 0 | J49: 0 | K49: 0 | L49: 0 | M49: 0 | N49: 0 | O49: 0 | P49: 0 | Q49: 0 | R49: 7923.72 | S49: 0 | T49: 0 | U49: 7923.72 | V49: -7923.72 | W49: 0 | X49: 0 | Y49: 0 | Z49: =V49-Y49 -> -7923.72
A50: P330049 | B50: ARECA | C50: 100 | D50: 高效一 | E50: 330 | F50: GN Audio A/S(GSC) | G50: 45286 | I50: 4360000 | J50: 0 | K50: 0 | L50: 0 | M50: 0 | N50: 0 | O50: 0 | P50: 0 | Q50: 0 | R50: 0 | S50: 34720.17 | T50: 79894.57 | U50: 114614.74 | V50: -114614.74 | W50: 0 | X50: 3858.22 | Y50: 3858.22 | Z50: =V50-Y50 -> -118472.96
A51: P860001 | B51: HERCULES | C51: 100 | D51: 高效一 | E51: C860 | F51: 通力科技股份有限公司 | G51: 44546 | I51: 1147800 | J51: 0 | K51: 0 | L51: 0 | M51: 0 | N51: 0 | O51: 0 | P51: 0 | Q51: 0 | R51: 0 | S51: 1641.98 | T51: 0 | U51: 1641.98 | V51: -1641.98 | W51: 0 | X51: 0 | Y51: 0 | Z51: =V51-Y51 -> -1641.98
A52: P869002 | B52: FI08 | C52: 100 | D52: 高效一 | E52: C869 | F52: 深圳市爱立康医疗股份有限公司 | G52: 44825 | I52: 353000 | J52: 250594.94 | K52: 0 | L52: 0 | M52: 0 | N52: 0 | O52: 250594.94 | P52: 340884.57 | Q52: 0 | R52: 0 | S52: 0 | T52: 0 | U52: 340884.57 | V52: -90289.63 | W52: 0 | X52: 0 | Y52: 0 | Z52: =V52-Y52 -> -90289.63
A53: P884002 | B53: GFD BASIC | C53: 100 | D53: 高效一 | E53: C884 | F53: Glowforge,Inc. | G53: 45371 | I53: 316008 | J53: 0 | K53: 0 | L53: 0 | M53: 0 | N53: 0 | O53: 0 | P53: 0 | Q53: 0 | R53: 0 | S53: 0 | T53: 24030.71 | U53: 24030.71 | V53: -24030.71 | W53: 0 | X53: 0 | Y53: 0 | Z53: =V53-Y53 -> -24030.71
A54: P208015 | B54: THK | C54: 100 | D54: 高效一注塑 | E54: C208 | F54: 深圳市韶音科技有限公司 | G54: 45435 | I54: 1480000 | J54: 0 | K54: 0 | L54: 0 | M54: 0 | N54: 0 | O54: 0 | P54: 0 | Q54: 0 | R54: 0 | S54: 0 | T54: 771.73 | U54: 771.73 | V54: -771.73 | W54: 0 | X54: 0 | Y54: 0 | Z54: =V54-Y54 -> -771.73
A55: P208016 | B55: UCS | C55: 100 | D55: 高效一注塑 | E55: C208 | F55: 深圳市韶音科技有限公司 | G55: 45442 | I55: 1790000 | J55: 0 | K55: 0 | L55: 0 | M55: 0 | N55: 0 | O55: 0 | P55: 0 | Q55: 0 | R55: 0 | S55: 0 | T55: 92.88 | U55: 92.88 | V55: -92.88 | W55: 0 | X55: 0 | Y55: 0 | Z55: =V55-Y55 -> -92.88
A56: P862003 | B56: 影石X4 | C56: 100 | D56: 高效一注塑 | E56: C862 | F56: 影石创新科技股份有限公司 | G56: 44799 | I56: 0 | J56: 0 | K56: 0 | L56: 424.83 | M56: 0 | N56: 0 | O56: 424.83 | P56: 0 | Q56: 0 | R56: 0 | S56: 0 | T56: 0 | U56: 0 | V56: 424.83 | W56: 0 | X56: 0 | Y56: 0 | Z56: =V56-Y56 -> 424.83
A57: VIP返利 | C57: 100 | D57: 高效一 | I57: 0 | J57: 0 | K57: 0 | L57: 0 | M57: 0 | N57: 0 | O57: 0 | P57: 0 | Q57: 0 | R57: 0 | S57: 0 | T57: 0 | U57: 0 | V57: 0 | W57: 0 | X57: 0 | Y57: 0 | Z57: =V57-Y57 -> 0
A58: 合计 | I58: =SUM(I4:I57) -> 2.4464593e+08 | J58: =SUM(J4:J57) -> 8576083.8 | K58: =SUM(K4:K57) -> 0 | L58: =SUM(L4:L57) -> 228148.73 | M58: =SUM(M4:M57) -> 11455.74 | N58: =SUM(N4:N57) -> 2863.94 | O58: =SUM(O4:O57) -> 8818552.2 | P58: =SUM(P4:P57) -> 9574280.2 | ... Y58: =SUM(Y4:Y57) -> 161623.03 | Z58: =V58-Y58 -> -2081025

Sheet HP2
A1: HP2 2024年1-2月NPI报表明细
A2: TK项目号 | B2: 项目名称 | C2: 利润中心 | D2: 事业部 | E2: 终端客户 | F2: 终端客户名称 | G2: 创建日期 | H2: 量产日期 | I2: NPI预算收入 | J2: 注塑模具收入 | K2: 其他模具收入 | L2: 样板费收入 | M2: 夹治具收入 | N2: 其它杂项收入 | O2: 量产前收入 | P2: 注塑模具成本 | Q2: 其他模具成本 | R2: 自费模具摊销 | S2: 量产前夹治具成本 | T2: 试模成本 | U2: 量产前成本 | V2: 量产前收益 | W2: 量产后夹治具成本 | X2: 量产后打样成本 | Y2: 量产后成本
A3: P293011 | B3: Jbay | C3: 601 | D3: 高效二 | E3: 293 | F3: GoPro, Inc. | G3: 44226 | H3: 43717 | I3: 0 | J3: 0 | K3: 0 | L3: 0 | M3: 0 | N3: 0 | O3: 0 | P3: 0 | Q3: 0 | R3: 0 | S3: 0 | T3: 0 | U3: 0 | V3: 0 | W3: 0 | X3: 0 | Y3: 0
A4: P460002 | B4: Project Vesta | C4: 601 | D4: 高效二 | E4: 460 | F4: Amazon com, Inc | G4: 44226 | H4: 44407 | I4: 0 | J4: 0 | K4: 0 | L4: 0 | M4: 0 | N4: 0 | O4: 0 | P4: 0 | Q4: 0 | R4: 0 | S4: 0 | T4: 0 | U4: 0 | V4: 0 | W4: 0 | X4: 0 | Y4: 0
A5: P460005 | B5: THEIA | C5: 601 | D5: 高效二 | E5: 460 | F5: Amazon com, Inc | G5: 44226 | H5: 44127 | I5: 0 | J5: 0 | K5: 0 | L5: 0 | M5: 0 | N5: 0 | O5: 0 | P5: 0 | Q5: 0 | R5: 0 | S5: 0 | T5: 0 | U5: 0 | V5: 0 | W5: 0 | X5: 0 | Y5: 0
A6: P460009 | B6: CORAL | C6: 601 | D6: 高效二 | E6: 460 | F6: Amazon com, Inc | G6: 44226 | H6: 44382 | I6: 0 | J6: 0 | K6: 0 | L6: 0 | M6: 0 | N6: 0 | O6: 0 | P6: 0 | Q6: 0 | R6: 0 | S6: 0 | T6: 0 | U6: 0 | V6: 0 | W6: 0 | X6: 0 | Y6: 0
A7: P460011 | B7: CRUSH | C7: 601 | D7: 高效二 | E7: 460 | F7: Amazon com, Inc | G7: 44350 | H7: 44369 | I7: 0 | J7: 0 | K7: 0 | L7: 0 | M7: 0 | N7: 0 | O7: 0 | P7: 0 | Q7: 0 | R7: 0 | S7: 0 | T7: 0 | U7: 0 | V7: 0 | W7: 0 | X7: 0 | Y7: 0
A8: P460012 | B8: MARLIN | C8: 601 | D8: 高效二 | E8: 460 | F8: Amazon com, Inc | G8: 44431 | H8: 44770 | I8: 0 | J8: 0 | K8: 0 | L8: 0 | M8: 0 | N8: 0 | O8: 0 | P8: 0 | Q8: 0 | R8: 0 | S8: 0 | T8: 0 | U8: 0 | V8: 0 | W8: 0 | X8: 0 | Y8: 0
A9: P460013 | B9: GERALD | C9: 601 | D9: 高效二 | E9: 460 | F9: Amazon com, Inc | G9: 44851 | I9: 7305383 | J9: 0 | K9: 0 | L9: 0 | M9: 0 | N9: 0 | O9: 0 | P9: 0 | Q9: 0 | R9: 0.02 | S9: 0 | T9: 0 | U9: 0.02 | V9: -0.02 | W9: 0 | X9: 0 | Y9: 0
A10: P460014 | B10: CITRINE | C10: 601 | D10: 高效二 | E10: 460 | F10: Amazon com, Inc | G10: 44872 | I10: 0 | J10: 0 | K10: 0 | L10: 0 | M10: 0 | N10: 0 | O10: 0 | P10: 0 | Q10: 0 | R10: 0 | S10: 0 | T10: 0 | U10: 0 | V10: 0 | W10: 0 | X10: 0 | Y10: 0
A11: P821002 | B11: S3 | C11: 601 | D11: 高效二 | E11: C821 | F11: Square Inc. | G11: 44226 | H11: 44133 | I11: 0 | J11: 0 | K11: 0 | L11: 0 | M11: 0 | N11: 0 | O11: 0 | P11: 0 | Q11: 0 | R11: 0 | S11: 0 | T11: 0 | U11: 0 | V11: 0 | W11: 0 | X11: 0 | Y11: 0
A12: P821003 | B12: S3 MOUNT | C12: 601 | D12: 高效二 | E12: C821 | F12: Square Inc. | G12: 44480 | I12: 0 | J12: 0 | K12: 0 | L12: 0 | M12: 0 | N12: 0 | O12: 0 | P12: 0 | Q12: 0 | R12: 0 | S12: 0 | T12: 0 | U12: 0 | V12: 0 | W12: 0 | X12: 0 | Y12: 0
A13: P821004 | B13: S3B | C13: 601 | D13: 高效二 | E13: C821 | F13: Square Inc. | G13: 44894 | I13: 0 | J13: 0 | K13: 0 | L13: 0 | M13: 0 | N13: 0 | O13: 0 | P13: 0 | Q13: 0 | R13: 0 | S13: 0 | T13: 0 | U13: 0 | V13: 0 | W13: 0 | X13: 0 | Y13: 0
A14: P831006 | B14: TITAN | C14: 601 | D14: 高效二 | E14: C831 | F14: August Home, Inc. | G14: 44770 | I14: 0 | J14: 0 | K14: 0 | L14: 0 | M14: 0 | N14: 0 | O14: 0 | P14: 0 | Q14: 0 | R14: 0 | S14: 0 | T14: 0 | U14: 0 | V14: 0 | W14: 0 | X14: 0 | Y14: 0
A15: P856001 | B15: NT02 | C15: 601 | D15: 高效二 | E15: C856 | F15: 微软(中国)有限公司 | G15: 44767 | I15: 0 | J15: 0 | K15: 0 | L15: 0 | M15: 0 | N15: 0 | O15: 0 | P15: 0 | Q15: 0 | R15: 0 | S15: 0 | T15: 0 | U15: 0 | V15: 0 | W15: 0 | X15: 0 | Y15: 0
A16: P860004 | B16: Q60 | C16: 601 | D16: 高效二 | E16: C860 | F16: 通力科技股份有限公司 | G16: 44784 | I16: 0 | J16: 0 | K16: 0 | L16: 0 | M16: 0 | N16: 0 | O16: 0 | P16: 0 | Q16: 0 | R16: 0 | S16: 0 | T16: 0 | U16: 0 | V16: 0 | W16: 0 | X16: 0 | Y16: 0
A17: P863001 | B17: WTH13 | C17: 601 | D17: 高效二 | E17: C863 | F17: Stripe Inc. | G17: 44628 | I17: 0 | J17: 0 | K17: 0 | L17: 0 | M17: 0 | N17: 0 | O17: 0 | P17: 0 | Q17: 0 | R17: 0 | S17: 0 | T17: 0 | U17: 0 | V17: 0 | W17: 0 | X17: 0 | Y17: 0
A18: P863002 | B18: M2 | C18: 601 | D18: 高效二 | E18: C863 | F18: Stripe Inc. | G18: 44775 | I18: 0 | J18: 0 | K18: 0 | L18: 0 | M18: 0 | N18: 0 | O18: 0 | P18: 0 | Q18: 0 | R18: 0 | S18: 0 | T18: 0 | U18: 0 | V18: 0 | W18: 0 | X18: 0 | Y18: 0
A19: P268002 | B19: B60 | C19: 601 | D19: 高效二 | E19: C268 | F19: Apple Inc. | G19: 44226 | H19: 42198 | I19: 0 | J19: 0 | K19: 0 | L19: 0 | M19: 0 | N19: 0 | O19: 0 | P19: 0 | Q19: 0 | R19: 0 | S19: 0 | T19: 0 | U19: 0 | V19: 0 | W19: 0 | X19: 0 | Y19: 0
A20: P460003 | B20: SPRINKLE | C20: 601 | D20: 高效二 | E20: 460 | F20: Amazon com, Inc | G20: 44226 | H20: 43620 | I20: 0 | J20: 0 | K20: 0 | L20: 0 | M20: 0 | N20: 0 | O20: 0 | P20: 0 | Q20: 0 | R20: 0 | S20: 0 | T20: 0 | U20: 0 | V20: 0 | W20: 0 | X20: 0 | Y20: 0
A21: P460004 | B21: POWELL | C21: 601 | D21: 高效二 | E21: 460 | F21: Amazon com, Inc | G21: 44226 | H21: 44410 | I21: 0 | J21: 0 | K21: 0 | L21: 0 | M21: 0 | N21: 0 | O21: 0 | P21: 0 | Q21: 0 | R21: 0 | S21: 0 | T21: 0 | U21: 0 | V21: 0 | W21: 0 | X21: 0 | Y21: 0
A22: P879002 | B22: LIZARD | C22: 601 | D22: 高效二 | E22: C879 | F22: teenage engineering | G22: 45069 | I22: 0 | J22: 0 | K22: 0 | L22: 0 | M22: 0 | N22: 0 | O22: 0 | P22: 0 | Q22: 0 | R22: 0 | S22: 0 | T22: 0 | U22: 0 | V22: 0 | W22: 0 | X22: 0 | Y22: 0
A23: P831007 | B23: MATRIX | C23: 601 | D23: 高效二 | E23: C831 | F23: August Home, Inc. | G23: 45107 | I23: 78155 | J23: 0 | K23: 0 | L23: 0 | M23: 0 | N23: 0 | O23: 0 | P23: 0 | Q23: 0 | R23: 0 | S23: 0 | T23: 0 | U23: 0 | V23: 0 | W23: 0 | X23: 0 | Y23: 0
A24: VIP返利 | C24: 601 | D24: 高效二 | I24: 0 | J24: 0 | K24: 0 | L24: 0 | M24: 0 | N24: 0 | O24: 0 | P24: 0 | Q24: 0 | R24: 0 | S24: 0 | T24: 0 | U24: 0 | V24: 0 | W24: 0 | X24: 0 | Y24: 0
A25: 合计 | I25: =SUM(I3:I24) -> 7383538 | J25: =SUM(J3:J24) -> 0 | K25: =SUM(K3:K24) -> 0 | L25: =SUM(L3:L24) -> 0 | M25: =SUM(M3:M24) -> 0 | N25: =SUM(N3:N24) -> 0 | O25: =SUM(O3:O24) -> 0 | P25: =SUM(P3:P24) -> 0 | ... Y25: =SUM(Y3:Y24) -> 0

Sheet HP3
A1: HP3 2024年1-6月NPI报表明细
A2: 币别:HKD
A3: TK项目号 | B3: 项目名称 | C3: 利润中心 | D3: 事业部 | E3: 终端客户 | F3: 终端客户名称 | G3: 创建日期 | H3: 量产日期 | I3: NPI预算收入 | J3: 注塑模具收入 | K3: 其他模具收入 | L3: 样板费收入 | M3: 夹治具收入 | N3: 其它杂项收入 | O3: 量产前收入 | P3: 注塑模具成本 | Q3: 其他模具成本 | R3: 自费模具摊销 | S3: 量产前夹治具成本 | T3: 试模成本 | U3: 量产前成本 | V3: 量产前收益 | W3: 量产后夹治具成本 | X3: 量产后打样成本 | Y3: 量产后成本 | Z3: 项目收益
A4: P028008 | B4: BOSE SERENA | C4: 701 | D4: 高效三 | E4: 28 | F4: Bose Corporation | G4: 44817 | I4: 7833000 | J4: 886099.17 | K4: 0 | L4: 6538.04 | M4: 0 | N4: 0 | O4: 892637.21 | P4: 755601.88 | Q4: 0 | R4: 0 | S4: 9449.54 | T4: 24946.52 | U4: 789997.94 | V4: 102639.27 | W4: 0 | X4: 30523.4 | Y4: 30523.4 | Z4: =V4-Y4 -> 72115.87
A5: P028009 | B5: SCOTTY | C5: 701 | D5: 高效三 | E5: 28 | F5: Bose Corporation | G5: 44859 | I5: 5958000 | J5: 0 | K5: 0 | L5: 0 | M5: 0 | N5: 0 | O5: 0 | P5: 0 | Q5: 0 | R5: 16188.24 | S5: 7275.35 | T5: 28777.66 | U5: 52241.25 | V5: -52241.25 | W5: 0 | X5: 0 | Y5: 0 | Z5: =V5-Y5 -> -52241.25
A6: P330019 | B6: ERASMUS | C6: 701 | D6: 高效三 | E6: 330 | F6: GN Audio A/S(GSC) | G6: 44226 | H6: 42198 | I6: 5478000 | J6: 391861.44 | K6: 0 | L6: 14898 | M6: 0 | N6: 0 | O6: 406759.44 | P6: 298990.02 | Q6: 0 | R6: 13361.66 | S6: 0 | T6: 0 | U6: 312351.68 | V6: 94407.76 | W6: 5727.88 | X6: 3450.25 | Y6: 9178.13 | Z6: =V6-Y6 -> 85229.63
A7: P330038 | B7: MAPLE | C7: 701 | D7: 高效三 | E7: 330 | F7: GN Audio A/S(GSC) | G7: 44307 | H7: 42198 | I7: 5610000 | J7: 0 | K7: 0 | L7: 0 | M7: 0 | N7: 0 | O7: 0 | P7: 0 | Q7: 0 | R7: 0 | S7: 0 | T7: 0 | U7: 0 | V7: 0 | W7: 0 | X7: 3391.41 | Y7: 3391.41 | Z7: =V7-Y7 -> -3391.41
A8: P330040 | B8: SAMWISE | C8: 701 | D8: 高效三 | E8: 330 | F8: GN Audio A/S(GSC) | G8: 44482 | H8: 44945 | I8: 19323850 | J8: 178849 | K8: 0 | L8: 13557.21 | M8: 0 | N8: 0 | O8: 192406.21 | P8: 106233.68 | Q8: 0 | R8: 9788.82 | S8: 0 | T8: 10150.58 | U8: 126173.08 | V8: 66233.13 | W8: 2079.44 | X8: 425.67 | Y8: 2505.11 | Z8: =V8-Y8 -> 63728.02
A9: P330042 | B9: PILLOW | C9: 701 | D9: 高效三 | E9: 330 | F9: GN Audio A/S(GSC) | G9: 44496 | H9: 44867 | I9: 7104600 | J9: 0 | K9: 0 | L9: 0 | M9: 0 | N9: 0 | O9: 0 | P9: 0 | Q9: 0 | R9: 1845.53 | S9: 0 | T9: 0 | U9: 1845.53 | V9: -1845.53 | W9: 0 | X9: 289.66 | Y9: 289.66 | Z9: =V9-Y9 -> -2135.19
A10: P360016 | B10: ETHEL | C10: 701 | D10: 高效三 | E10: 360 | F10: Google Inc. | G10: 44226 | H10: 42420 | I10: 0 | J10: 0 | K10: 0 | L10: 0 | M10: 0 | N10: 0 | O10: 0 | P10: 0 | Q10: 0 | R10: 0 | S10: 0 | T10: 0 | U10: 0 | V10: 0 | W10: 0 | X10: 0 | Y10: 0 | Z10: =V10-Y10 -> 0
A11: P360021 | B11: SIROCCO | C11: 701 | D11: 高效三 | E11: 360 | F11: Google Inc. | G11: 44357 | H11: 42198 | I11: 0 | J11: 0 | K11: 0 | L11: 0 | M11: 0 | N11: 0 | O11: 0 | P11: 0 | Q11: 0 | R11: 0 | S11: 0 | T11: 0 | U11: 0 | V11: 0 | W11: 0 | X11: 0 | Y11: 0 | Z11: =V11-Y11 -> 0
A12: P360022 | B12: C9 | C12: 701 | D12: 高效三 | E12: 360 | F12: Google Inc. | G12: 44638 | I12: 2420000 | J12: 0 | K12: 0 | L12: 0 | M12: 0 | N12: 0 | O12: 0 | P12: 0 | Q12: 0 | R12: 868.98 | S12: 0 | T12: 0 | U12: 868.98 | V12: -868.98 | W12: 0 | X12: 0 | Y12: 0 | Z12: =V12-Y12 -> -868.98
A13: P404014 | B13: BISMUTH | C13: 701 | D13: 高效三 | E13: 404 | F13: Google Inc | G13: 44334 | H13: 43328 | I13: 67325484 | J13: 2879571.2 | K13: 0 | L13: 10754.37 | M13: 154822 | N13: 0 | O13: 3045147.6 | P13: 2745315.4 | Q13: 0 | R13: 37730.88 | S13: 48258.38 | T13: 53782.04 | U13: 2885086.7 | V13: 160060.83 | W13: 722.22 | X13: 18733.09 | Y13: 19455.31 | Z13: =V13-Y13 -> 140605.52
A14: P435002 | B14: Dublin mid | C14: 701 | D14: 高效三 | E14: 330 | F14: GN Audio A/S(GSC) | G14: 44226 | H14: 42181 | I14: 0 | J14: 0 | K14: 0 | L14: 0 | M14: 0 | N14: 0 | O14: 0 | P14: 0 | Q14: 0 | R14: 0 | S14: 0 | T14: 0 | U14: 0 | V14: 0 | W14: 0 | X14: 0 | Y14: 0 | Z14: =V14-Y14 -> 0
A15: P435004 | B15: Dublin MONO | C15: 701 | D15: 高效三 | E15: 330 | F15: GN Audio A/S(GSC) | G15: 44226 | H15: 42181 | I15: 0 | J15: 0 | K15: 0 | L15: 0 | M15: 0 | N15: 0 | O15: 0 | P15: 0 | Q15: 0 | R15: 0 | S15: 0 | T15: 4489.44 | U15: 4489.44 | V15: -4489.44 | W15: 0 | X15: 62.94 | Y15: 62.94 | Z15: =V15-Y15 -> -4552.38
A16: P435011 | B16: Rio Headset | C16: 701 | D16: 高效三 | E16: 330 | F16: GN Audio A/S(GSC) | G16: 44226 | H16: 43328 | I16: 1491440 | J16: 51892.6 | K16: 0 | L16: 0 | M16: 0 | N16: 0 | O16: 51892.6 | P16: 38122 | Q16: 0 | R16: 0 | S16: 0 | T16: 0 | U16: 38122 | V16: 13770.6 | W16: 0 | X16: 0 | Y16: 0 | Z16: =V16-Y16 -> 13770.6
A17: P818002 | B17: HDT666 | C17: 701 | D17: 高效三 | E17: C818 | F17: 美律电子（深圳）有限公司 | G17: 44757 | I17: 21578100 | J17: 23064.6 | K17: 0 | L17: 1762.11 | M17: 0 | N17: 0 | O17: 24826.71 | P17: 18546.06 | Q17: 0 | R17: 36388.43 | S17: 41718.65 | T17: 15796.86 | U17: 112450 | V17: -87623.29 | W17: 3174.29 | X17: 356.02 | Y17: 3530.31 | Z17: =V17-Y17 -> -91153.6
A18: P330008 | B18: Binary HB | C18: 701 | D18: 高效三 | E18: 330 | F18: GN Audio A/S(GSC) | G18: 44226 | H18: 43266 | I18: 0 | J18: 0 | K18: 0 | L18: 0 | M18: 0 | N18: 0 | O18: 0 | P18: 0 | Q18: 0 | R18: 0 | S18: 0 | T18: 0 | U18: 0 | V18: 0 | W18: 0 | X18: 0 | Y18: 0 | Z18: =V18-Y18 -> 0
A19: P435010 | B19: Rio Base | C19: 701 | D19: 高效三 | E19: 330 | F19: GN Audio A/S(GSC) | G19: 44226 | H19: 42551 | I19: 6333973.8 | J19: 22367.5 | K19: 0 | L19: 0 | M19: 0 | N19: 0 | O19: 22367.5 | P19: 16338 | Q19: 0 | R19: 0 | S19: 0 | T19: 0 | U19: 16338 | V19: 6029.5 | W19: 4385.79 | X19: 0 | Y19: 4385.79 | Z19: =V19-Y19 -> 1643.71
A20: P330007 | B20: Super Mario | C20: 701 | D20: 高效三 | E20: 330 | F20: GN Audio A/S(GSC) | G20: 44226 | H20: 42207 | I20: 0 | J20: 0 | K20: 0 | L20: 0 | M20: 0 | N20: 0 | O20: 0 | P20: 0 | Q20: 0 | R20: 0 | S20: 0 | T20: 0 | U20: 0 | V20: 0 | W20: 0 | X20: 0 | Y20: 0 | Z20: =V20-Y20 -> 0
A21: P360004 | B21: Gotham | C21: 701 | D21: 高效三 | E21: 360 | F21: Google Inc. | G21: 44226 | H21: 43761 | I21: 0 | J21: 0 | K21: 0 | L21: 0 | M21: 0 | N21: 0 | O21: 0 | P21: 0 | Q21: 0 | R21: 0 | S21: 0 | T21: 0 | U21: 0 | V21: 0 | W21: 0 | X21: 0 | Y21: 0 | Z21: =V21-Y21 -> 0
A22: P330009 | B22: Bezos | C22: 701 | D22: 高效三 | E22: 330 | F22: GN Audio A/S(GSC) | G22: 44226 | H22: 43577 | I22: 0 | J22: 0 | K22: 0 | L22: 0 | M22: 0 | N22: 0 | O22: 0 | P22: 0 | Q22: 0 | R22: 8788.13 | S22: 0 | T22: 0 | U22: 8788.13 | V22: -8788.13 | W22: 0 | X22: 0 | Y22: 0 | Z22: =V22-Y22 -> -8788.13
A23: P330006 | B23: Rio Base 2 | C23: 701 | D23: 高效三 | E23: 330 | F23: GN Audio A/S(GSC) | G23: 44226 | H23: 43329 | I23: 338772.5 | J23: 142202.84 | K23: 0 | L23: 0 | M23: 0 | N23: 0 | O23: 142202.84 | P23: 115144 | Q23: 0 | R23: 0 | S23: 0 | T23: 0 | U23: 115144 | V23: 27058.84 | W23: 0 | X23: 2763.2 | Y23: 2763.2 | Z23: =V23-Y23 -> 24295.64
A24: P293011 | B24: Jbay | C24: 701 | D24: 高效三 | E24: 293 | F24: GoPro, Inc. | G24: 44226 | H24: 43717 | I24: 0 | J24: 0 | K24: 0 | L24: 0 | M24: 0 | N24: 0 | O24: 0 | P24: 0 | Q24: 0 | R24: 0 | S24: 0 | T24: 0 | U24: 0 | V24: 0 | W24: 0 | X24: 0 | Y24: 0 | Z24: =V24-Y24 -> 0
A25: P330010 | B25: Spiderman | C25: 701 | D25: 高效三 | E25: 330 | F25: GN Audio A/S(GSC) | G25: 0 | H25: 0 | I25: 0 | J25: 0 | K25: 0 | L25: 0 | M25: 0 | N25: 0 | O25: 0 | P25: 0 | Q25: 0 | R25: 0 | S25: 0 | T25: 0 | U25: 0 | V25: 0 | W25: 0 | X25: 0 | Y25: 0 | Z25: =V25-Y25 -> 0
A26: P821002 | B26: S3 | C26: 701 | D26: 高效三 | E26: C821 | F26: Square Inc. | G26: 44226 | H26: 44133 | I26: 0 | J26: 0 | K26: 0 | L26: 0 | M26: 0 | N26: 0 | O26: 0 | P26: 0 | Q26: 0 | R26: 17857.79 | S26: 0 | T26: 0 | U26: 17857.79 | V26: -17857.79 | W26: 1002.37 | X26: 117.61 | Y26: 1119.98 | Z26: =V26-Y26 -> -18977.77
A27: P821003 | B27: S3 MOUNT | C27: 701 | D27: 高效三 | E27: C821 | F27: Square Inc. | G27: 44480 | I27: 2180000 | J27: 0 | K27: 0 | L27: 0 | M27: 0 | N27: 0 | O27: 0 | P27: 0 | Q27: 0 | R27: 9094.98 | S27: 0 | T27: 0 | U27: 9094.98 | V27: -9094.98 | W27: 0 | X27: 0 | Y27: 0 | Z27: =V27-Y27 -> -9094.98
A28: P821004 | B28: S3B | C28: 701 | D28: 高效三 | E28: C821 | F28: Square Inc. | G28: 44894 | I28: 2622471.5 | J28: 0 | K28: 0 | L28: 0 | M28: 0 | N28: 0 | O28: 0 | P28: 0 | Q28: 0 | R28: 72331.91 | S28: 369.37 | T28: 21418.57 | U28: 94119.85 | V28: -94119.85 | W28: 0 | X28: 0 | Y28: 0 | Z28: =V28-Y28 -> -94119.85
A29: P824010 | B29: MIMOSA | C29: 701 | D29: 高效三 | E29: C824 | F29: NICOVENTURES TRADING LIMITED | G29: 44935 | I29: 69500 | J29: 0 | K29: 0 | L29: 0 | M29: 0 | N29: 0 | O29: 0 | P29: 0 | Q29: 0 | R29: 0 | S29: 0 | T29: 0 | U29: 0 | V29: 0 | W29: 0 | X29: 0 | Y29: 0 | Z29: =V29-Y29 -> 0
A30: P831001 | B30: PANDORA | C30: 701 | D30: 高效三 | E30: C831 | F30: August Home, Inc. | G30: 44264 | H30: 44288 | I30: 1922753.8 | J30: 0 | K30: 0 | L30: 0 | M30: 0 | N30: 0 | O30: 0 | P30: 0 | Q30: 0 | R30: 0 | S30: 0 | T30: 0 | U30: 0 | V30: 0 | W30: 0 | X30: 0 | Y30: 0 | Z30: =V30-Y30 -> 0
A31: P831003 | B31: NEST 1.5 | C31: 701 | D31: 高效三 | E31: C831 | F31: August Home, Inc. | G31: 44411 | I31: 1611280 | J31: 0 | K31: 0 | L31: 0 | M31: 0 | N31: 0 | O31: 0 | P31: 0 | Q31: 0 | R31: 0 | S31: 0 | T31: 0 | U31: 0 | V31: 0 | W31: 0 | X31: 0 | Y31: 0 | Z31: =V31-Y31 -> 0
A32: P831006 | B32: TITAN | C32: 701 | D32: 高效三 | E32: C831 | F32: August Home, Inc. | G32: 44770 | H32: 45093 | I32: 1509200 | J32: 0 | K32: 0 | L32: 0 | M32: 0 | N32: 0 | O32: 0 | P32: 0 | Q32: 0 | R32: 1122.05 | S32: 0 | T32: 0 | U32: 1122.05 | V32: -1122.05 | W32: 0 | X32: 0 | Y32: 0 | Z32: =V32-Y32 -> -1122.05
A33: P860004 | B33: Q60 | C33: 701 | D33: 高效三 | E33: C860 | F33: 通力科技股份有限公司 | G33: 44784 | I33: 370000 | J33: 0 | K33: 0 | L33: 0 | M33: 0 | N33: 0 | O33: 0 | P33: 0 | Q33: 0 | R33: 2938.59 | S33: 0 | T33: 0 | U33: 2938.59 | V33: -2938.59 | W33: 0 | X33: 0 | Y33: 0 | Z33: =V33-Y33 -> -2938.59
A34: P860005 | B34: PELICAN | C34: 701 | D34: 高效三 | E34: C860 | F34: 通力科技股份有限公司 | G34: 44818 | H34: 45183 | I34: 870100 | J34: 0 | K34: 0 | L34: 0 | M34: 0 | N34: 0 | O34: 0 | P34: 0 | Q34: 0 | R34: 0 | S34: 0 | T34: 0 | U34: 0 | V34: 0 | W34: 0 | X34: 0 | Y34: 0 | Z34: =V34-Y34 -> 0
A35: P860008 | B35: SONY HDX2981 | C35: 701 | D35: 高效三 | E35: C860 | F35: 通力科技股份有限公司 | G35: 45049 | I35: 3687000 | J35: 0 | K35: 0 | L35: 0 | M35: 0 | N35: 0 | O35: 0 | P35: 0 | Q35: 0 | R35: 0 | S35: 0 | T35: 0 | U35: 0 | V35: 0 | W35: 0 | X35: 0 | Y35: 0 | Z35: =V35-Y35 -> 0
A36: P862001 | B36: PSC56一体机 | C36: 701 | D36: 高效三 | E36: C862 | F36: 影石创新科技股份有限公司 | G36: 44606 | H36: 45177 | I36: 1710294 | J36: 0 | K36: 0 | L36: 0 | M36: 0 | N36: 0 | O36: 0 | P36: 0 | Q36: 0 | R36: 0 | S36: 0 | T36: 0 | U36: 0 | V36: 0 | W36: 0 | X36: 0 | Y36: 0 | Z36: =V36-Y36 -> 0
A37: P863001 | B37: WTH13 | C37: 701 | D37: 高效三 | E37: C863 | F37: Stripe Inc. | G37: 44628 | H37: 45051 | I37: 2560910 | J37: 0 | K37: 0 | L37: 4657.88 | M37: 4686 | N37: 0 | O37: 9343.88 | P37: 0 | Q37: 0 | R37: 185333.27 | S37: 0 | T37: 2749.9 | U37: 188083.17 | V37: -178739.29 | W37: 369.77 | X37: 10195.97 | Y37: 10565.74 | Z37: =V37-Y37 -> -189305.03
A38: P831007 | B38: MATRIX | C38: 701 | D38: 高效三 | E38: C831 | F38: August Home, Inc. | G38: 45107 | I38: 78155 | J38: 0 | K38: 0 | L38: 0 | M38: 0 | N38: 0 | O38: 0 | P38: 0 | Q38: 0 | R38: 0 | S38: -3083.7 | T38: 0 | U38: -3083.7 | V38: 3083.7 | W38: 0 | X38: 0 | Y38: 0 | Z38: =V38-Y38 -> 3083.7
A39: P879002 | B39: LIZARD | C39: 701 | D39: 高效三 | E39: C879 | F39: teenage engineering | G39: 45069 | I39: 2573429.6 | J39: 0 | K39: 0 | L39: 460.79 | M39: 0 | N39: 0 | O39: 460.79 | P39: 0 | Q39: 0 | R39: 0 | S39: 8237.02 | T39: 39559.65 | U39: 47796.67 | V39: -47335.88 | W39: 0 | X39: 3045.68 | Y39: 3045.68 | Z39: =V39-Y39 -> -50381.56
A40: P435013 | B40: Rio lightweight | C40: 701 | D40: 高效三 | E40: 330 | F40: GN Audio A/S(GSC) | G40: 44226 | H40: 43277 | I40: 2201000 | J40: 105107.8 | K40: 0 | L40: 0 | M40: 0 | N40: 0 | O40: 105107.8 | P40: 85424.4 | Q40: 0 | R40: 0 | S40: 0 | T40: 0 | U40: 85424.4 | V40: 19683.4 | W40: 0 | X40: 0 | Y40: 0 | Z40: =V40-Y40 -> 19683.4
A41: P910001 | B41: SHUFFLE CASE | C41: 701 | D41: 高效三 | E41: C910 | F41: Opal Camera, Inc. | G41: 45251 | I41: 547967.2 | J41: 190944 | K41: 0 | L41: 107856.65 | M41: 0 | N41: 0 | O41: 298800.65 | P41: 184080 | Q41: 4725.49 | R41: 0 | S41: 18991.23 | T41: 10560.1 | U41: 218356.82 | V41: 80443.83 | W41: 0 | X41: 0 | Y41: 0 | Z41: =V41-Y41 -> 80443.83
A42: P856001 | B42: NT02 | C42: 701 | D42: 高效三 | E42: C856 | F42: 微软(中国)有限公司 | G42: 44767 | I42: 3052770 | J42: 352319.3 | K42: 0 | L42: 6442.55 | M42: 94172.98 | N42: 0 | O42: 452934.83 | P42: 0 | Q42: 0 | R42: 23228.67 | S42: 0 | T42: 10190.94 | U42: 33419.61 | V42: 419515.22 | W42: 0 | X42: 0 | Y42: 0 | Z42: =V42-Y42 -> 419515.22
A43: P330046 | B43: BLIZZARD | C43: 701 | D43: 高效三 | E43: 330 | F43: GN Audio A/S(GSC) | G43: 45133 | I43: 1815592.9 | J43: 0 | K43: 0 | L43: 49904.95 | M43: 0 | N43: 0 | O43: 49904.95 | P43: 0 | Q43: 0 | R43: 0 | S43: 17047.4 | T43: 30361.62 | U43: 47409.02 | V43: 2495.93 | W43: 6582.59 | X43: 4477.72 | Y43: 11060.31 | Z43: =V43-Y43 -> -8564.38
A44: P821005 | B44: R42 | C44: 701 | D44: 高效三 | E44: C821 | F44: Square Inc. | G44: 45273 | I44: 803000 | J44: 0 | K44: 0 | L44: 0 | M44: 0 | N44: 0 | O44: 0 | P44: 0 | Q44: 0 | R44: 0 | S44: 2040.42 | T44: 23113.85 | U44: 25154.27 | V44: -25154.27 | W44: 0 | X44: 970.84 | Y44: 970.84 | Z44: =V44-Y44 -> -26125.11
A45: P330012 | B45: TITAN | C45: 701 | D45: 高效三 | E45: 330 | F45: GN Audio A/S(GSC) | G45: 44226 | H45: 43941 | I45: 0 | J45: 0 | K45: 0 | L45: 0 | M45: 0 | N45: 0 | O45: 0 | P45: 0 | Q45: 0 | R45: 3601.67 | S45: 0 | T45: 0 | U45: 3601.67 | V45: -3601.67 | W45: 0 | X45: 0 | Y45: 0 | Z45: =V45-Y45 -> -3601.67
A46: P435001 | B46: FLASH | C46: 701 | D46: 高效三 | E46: 330 | F46: GN Audio A/S(GSC) | G46: 44226 | H46: 42207 | I46: 0 | J46: 0 | K46: 0 | L46: 0 | M46: 0 | N46: 0 | O46: 0 | P46: 0 | Q46: 0 | R46: 2341.13 | S46: 0 | T46: 0 | U46: 2341.13 | V46: -2341.13 | W46: 0 | X46: 0 | Y46: 0 | Z46: =V46-Y46 -> -2341.13
A47: P330020 | B47: Leo | C47: 701 | D47: 高效三 | E47: 330 | F47: GN Audio A/S(GSC) | G47: 44226 | H47: 44371 | I47: 0 | J47: 0 | K47: 0 | L47: 0 | M47: 0 | N47: 0 | O47: 0 | P47: 0 | Q47: 0 | R47: 0 | S47: 0 | T47: 3644.66 | U47: 3644.66 | V47: -3644.66 | W47: 704.11 | X47: 595.9 | Y47: 1300.01 | Z47: =V47-Y47 -> -4944.67
A48: P809009 | B48: AG10AG20 | C48: 701 | D48: 高效三 | E48: C809 | F48: 歌尔股份有限公司 | G48: 45273 | I48: 2428000 | J48: 0 | K48: 0 | L48: 0 | M48: 0 | N48: 0 | O48: 0 | P48: 0 | Q48: 0 | R48: 0 | S48: 4167.79 | T48: 42937 | U48: 47104.79 | V48: -47104.79 | W48: 0 | X48: 0 | Y48: 0 | Z48: =V48-Y48 -> -47104.79
A49: P879003 | B49: GIBBON-D | C49: 701 | D49: 高效三 | E49: C879 | F49: teenage engineering | G49: 45321 | I49: 1554696 | J49: 0 | K49: 0 | L49: 0 | M49: 106080 | N49: 0 | O49: 106080 | P49: 0 | Q49: 0 | R49: 0 | S49: 0 | T49: 17338.6 | U49: 17338.6 | V49: 88741.4 | W49: 0 | X49: 0 | Y49: 0 | Z49: =V49-Y49 -> 88741.4
A50: P028011 | B50: BOSE PRINCE | C50: 701 | D50: 高效三 | E50: 28 | F50: Bose Corporation | G50: 45406 | I50: 902000 | J50: 0 | K50: 0 | L50: 0 | M50: 0 | N50: 0 | O50: 0 | P50: 0 | Q50: 0 | R50: 0 | S50: 0 | T50: 8987.76 | U50: 8987.76 | V50: -8987.76 | W50: 0 | X50: 0 | Y50: 0 | Z50: =V50-Y50 -> -8987.76
A51: P330050 | B51: FIRE FOOT | C51: 701 | D51: 高效三 | E51: 330 | F51: GN Audio A/S(GSC) | G51: 45404 | I51: 1452000 | J51: 0 | K51: 0 | L51: 0 | M51: 0 | N51: 0 | O51: 0 | P51: 0 | Q51: 0 | R51: 0 | S51: 2622.45 | T51: 4499.52 | U51: 7121.97 | V51: -7121.97 | W51: 2622.45 | X51: 0 | Y51: 2622.45 | Z51: =V51-Y51 -> -9744.42
A52: P876002 | B52: ROUNDHOUSE | C52: 701 | D52: 高效三 | E52: C876 | F52: Sonos, Inc. | G52: 45432 | I52: 2530000 | J52: 0 | K52: 0 | L52: 0 | M52: 0 | N52: 0 | O52: 0 | P52: 0 | Q52: 0 | R52: 0 | S52: 0 | T52: 2614.16 | U52: 2614.16 | V52: -2614.16 | W52: 0 | X52: 0 | Y52: 0 | Z52: =V52-Y52 -> -2614.16
A53: P923001 | B53: PH02 PADS | C53: 701 | D53: 高效三 | E53: C923 | F53: Backbone Labs | G53: 45373 | I53: 551600 | J53: 0 | K53: 0 | L53: 0 | M53: 0 | N53: 0 | O53: 0 | P53: 0 | Q53: 0 | R53: 0 | S53: 0 | T53: 3855.82 | U53: 3855.82 | V53: -3855.82 | W53: 0 | X53: 0 | Y53: 0 | Z53: =V53-Y53 -> -3855.82
A54: VIP返利 | C54: 701 | D54: 高效三 | F54: VIP返利 | I54: 0 | J54: 0 | K54: 0 | L54: 0 | M54: 0 | N54: 0 | O54: 0 | P54: 0 | Q54: 0 | R54: 0 | S54: 0 | T54: 0 | U54: 0 | V54: 0 | W54: 0 | X54: 0 | Y54: 0 | Z54: =V54-Y54 -> 0
A55: 合计 | I55: =SUM(I4:I54) -> 1.9039894e+08 | J55: =SUM(J4:J54) -> 5224279.4 | K55: =SUM(K4:K54) -> 0 | L55: =SUM(L4:L54) -> 216832.55 | M55: =SUM(M4:M54) -> 359760.98 | N55: =SUM(N4:N54) -> 0 | O55: =SUM(O4:O54) -> 5800873 | P55: =SUM(P4:P54) -> 4363795.5 | ... Z55: =SUM(Z4:Z54) -> 365901.86

Sheet HP4
A1: HP4 2024年1-6月NPI报表明细
A2: 币别:HKD
A3: TK项目号 | B3: 项目名称 | C3: 利润中心 | D3: 事业部 | E3: 终端客户 | F3: 终端客户名称 | G3: 创建日期 | H3: 量产日期 | I3: NPI预算收入 | J3: 注塑模具收入 | K3: 其他模具收入 | L3: 样板费收入 | M3: 夹治具收入 | N3: 其它杂项收入 | O3: 量产前收入 | P3: 注塑模具成本 | Q3: 其他模具成本 | R3: 自费模具摊销 | S3: 量产前夹治具成本 | T3: 试模成本 | U3: 量产前成本 | V3: 量产前收益 | W3: 量产后夹治具成本 | X3: 量产后打样成本 | Y3: 量产后成本 | Z3: 项目收益
A4: P805004 | B4: PANDORA | C4: 901 | D4: 高效四 | E4: C805 | F4: 深圳市合元科技有限公司 | G4: 44226 | H4: 44006 | I4: 0 | J4: 0 | K4: 0 | L4: 0 | M4: 0 | N4: 0 | O4: 0 | P4: 0 | Q4: 0 | R4: 5798.75 | S4: 0 | T4: 0 | U4: 5798.75 | V4: -5798.75 | W4: 0 | X4: 0 | Y4: 0 | Z4: =V4-Y4 -> -5798.75
A5: P805012 | B5: P63B | C5: 901 | D5: 高效四 | E5: C805 | F5: 深圳市合元科技有限公司 | G5: 44226 | H5: 44208 | I5: 0 | J5: 0 | K5: 0 | L5: 0 | M5: 0 | N5: 0 | O5: 0 | P5: 90423.05 | Q5: 0 | R5: 55725.33 | S5: 0 | T5: 0 | U5: 146148.38 | V5: -146148.38 | W5: 0 | X5: 0 | Y5: 0 | Z5: =V5-Y5 -> -146148.38
A6: P805014 | B6: P53A | C6: 901 | D6: 高效四 | E6: C805 | F6: 深圳市合元科技有限公司 | G6: 44226 | H6: 44165 | I6: 0 | J6: 300951.75 | K6: 0 | L6: 0 | M6: 0 | N6: 0 | O6: 300951.75 | P6: 0 | Q6: 0 | R6: 23951.32 | S6: 0 | T6: 0 | U6: 23951.32 | V6: 277000.43 | W6: 0 | X6: 0 | Y6: 0 | Z6: =V6-Y6 -> 277000.43
A7: P805022 | B7: HW42410 | C7: 901 | D7: 高效四 | E7: C805 | F7: 深圳市合元科技有限公司 | G7: 44456 | I7: 874800 | J7: 10119.23 | K7: 0 | L7: 0 | M7: 0 | N7: 0 | O7: 10119.23 | P7: 0 | Q7: 0 | R7: 0 | S7: 0 | T7: 0 | U7: 0 | V7: 10119.23 | W7: 0 | X7: 0 | Y7: 0 | Z7: =V7-Y7 -> 10119.23
A8: P805023 | B8: KFC | C8: 901 | D8: 高效四 | E8: C805 | F8: 深圳市合元科技有限公司 | G8: 44461 | I8: 136000 | J8: 0 | K8: 0 | L8: 0 | M8: 0 | N8: 0 | O8: 0 | P8: 0 | Q8: 0 | R8: 308.58 | S8: 0 | T8: 0 | U8: 308.58 | V8: -308.58 | W8: 0 | X8: 0 | Y8: 0 | Z8: =V8-Y8 -> -308.58
A9: P805024 | B9: PD2 | C9: 901 | D9: 高效四 | E9: C805 | F9: 深圳市合元科技有限公司 | G9: 44558 | I9: 0 | J9: 0 | K9: 0 | L9: 0 | M9: 0 | N9: 0 | O9: 0 | P9: 0 | Q9: 0 | R9: 0 | S9: 0 | T9: 0 | U9: 0 | V9: 0 | W9: 0 | X9: 0 | Y9: 0 | Z9: =V9-Y9 -> 0
A10: P805025 | B10: MOTO | C10: 901 | D10: 高效四 | E10: C805 | F10: 深圳市合元科技有限公司 | G10: 44652 | H10: 45027 | I10: 55264500 | J10: 1262215.6 | K10: 0 | L10: 0 | M10: 0 | N10: 0 | O10: 1262215.6 | P10: 3050194.4 | Q10: 0 | R10: 492296.86 | S10: 0 | T10: 3052.5 | U10: 3545543.7 | V10: -2283328.1 | W10: 0 | X10: 395.32 | Y10: 395.32 | Z10: =V10-Y10 -> -2283723.4
A11: P805027 | B11: COROLLA | C11: 901 | D11: 高效四 | E11: C805 | F11: 深圳市合元科技有限公司 | G11: 44677 | H11: 44905 | I11: 20095000 | J11: 205248.64 | K11: 0 | L11: 0 | M11: 0 | N11: 0 | O11: 205248.64 | P11: 25122.16 | Q11: 0 | R11: 37023.95 | S11: 0 | T11: 0 | U11: 62146.11 | V11: 143102.53 | W11: 0 | X11: 40.42 | Y11: 40.42 | Z11: =V11-Y11 -> 143062.11
A12: P805028 | B12: ARTEMIS | C12: 901 | D12: 高效四 | E12: C805 | F12: 深圳市合元科技有限公司 | G12: 44788 | I12: 54455280 | J12: 1296147.6 | K12: 0 | L12: 0 | M12: 0 | N12: 0 | O12: 1296147.6 | P12: 1116696 | Q12: 85766.64 | R12: 356969.75 | S12: 0 | T12: 0 | U12: 1559432.4 | V12: -263284.78 | W12: 0 | X12: 0 | Y12: 0 | Z12: =V12-Y12 -> -263284.78
A13: P805030 | B13: KD | C13: 901 | D13: 高效四 | E13: C805 | F13: 深圳市合元科技有限公司 | G13: 44859 | I13: 495000 | J13: 11001.32 | K13: 0 | L13: 0 | M13: 0 | N13: 0 | O13: 11001.32 | P13: 0 | Q13: 0 | R13: 0 | S13: 0 | T13: 0 | U13: 0 | V13: 11001.32 | W13: 0 | X13: 0 | Y13: 0 | Z13: =V13-Y13 -> 11001.32
A14: P805031 | B14: MAX-1500 | C14: 901 | D14: 高效四 | E14: C805 | F14: 深圳市合元科技有限公司 | G14: 44875 | I14: 0 | J14: 0 | K14: 0 | L14: 0 | M14: 0 | N14: 0 | O14: 0 | P14: 0 | Q14: 0 | R14: 0 | S14: 0 | T14: 0 | U14: 0 | V14: 0 | W14: 0 | X14: 0 | Y14: 0 | Z14: =V14-Y14 -> 0
A15: P805032 | B15: BW42487 | C15: 901 | D15: 高效四 | E15: C805 | F15: 深圳市合元科技有限公司 | G15: 44882 | I15: 14962200 | J15: 0 | K15: 0 | L15: 4677.47 | M15: 0 | N15: 0 | O15: 4677.47 | P15: 747934.53 | Q15: 0 | R15: 0 | S15: 0 | T15: 0 | U15: 747934.53 | V15: -743257.06 | W15: 3158.51 | X15: 12672.96 | Y15: 15831.47 | Z15: =V15-Y15 -> -759088.53
A16: P814002 | B16: MAPLE | C16: 901 | D16: 高效四 | E16: C814 | F16: Pax Labs, Inc. | G16: 44226 | H16: 43969 | I16: 7800000 | J16: 0 | K16: 0 | L16: 0 | M16: 0 | N16: 0 | O16: 0 | P16: 0 | Q16: 0 | R16: 3169.49 | S16: 0 | T16: 0 | U16: 3169.49 | V16: -3169.49 | W16: 0 | X16: 0 | Y16: 0 | Z16: =V16-Y16 -> -3169.49
A17: P820001 | B17: ACE | C17: 901 | D17: 高效四 | E17: C820 | F17: NJOY, LLC. | G17: 44226 | H17: 44424 | I17: 0 | J17: 0 | K17: 0 | L17: 0 | M17: 0 | N17: 0 | O17: 0 | P17: 0 | Q17: 0 | R17: 0 | S17: 0 | T17: 0 | U17: 0 | V17: 0 | W17: 0 | X17: 1373.71 | Y17: 1373.71 | Z17: =V17-Y17 -> -1373.71
A18: P824001 | B18: TF16 | C18: 901 | D18: 高效四 | E18: C824 | F18: NICOVENTURES TRADING LIMITED | G18: 44226 | H18: 44446 | I18: 0 | J18: 0 | K18: 0 | L18: 2354.73 | M18: 0 | N18: 0 | O18: 2354.73 | P18: 288674.43 | Q18: 0 | R18: 15306.18 | S18: 0 | T18: 0 | U18: 303980.61 | V18: -301625.88 | W18: 0 | X18: 0 | Y18: 0 | Z18: =V18-Y18 -> -301625.88
A19: P824002 | B19: TF1601A | C19: 901 | D19: 高效四 | E19: C824 | F19: NICOVENTURES TRADING LIMITED | G19: 44226 | H19: 44344 | I19: 4125000 | J19: 0 | K19: 0 | L19: 0 | M19: 0 | N19: 0 | O19: 0 | P19: 180377.83 | Q19: 0 | R19: 3246.84 | S19: 0 | T19: 0 | U19: 183624.67 | V19: -183624.67 | W19: 0 | X19: 4121.15 | Y19: 4121.15 | Z19: =V19-Y19 -> -187745.82
A20: P824004 | B20: EPODS3 | C20: 901 | D20: 高效四 | E20: C824 | F20: NICOVENTURES TRADING LIMITED | G20: 44543 | I20: 52956600 | J20: 130045.96 | K20: 0 | L20: 224867.61 | M20: 0 | N20: 0 | O20: 354913.57 | P20: 5469595.1 | Q20: 0 | R20: 184235.24 | S20: 0 | T20: -2361.51 | U20: 5651468.8 | V20: -5296555.3 | W20: 35385.36 | X20: 33086.97 | Y20: 68472.33 | Z20: =V20-Y20 -> -5365027.6
A21: P824007 | B21: VD1.0 | C21: 901 | D21: 高效四 | E21: C824 | F21: NICOVENTURES TRADING LIMITED | G21: 44788 | I21: 19153200 | J21: 150997.31 | K21: 0 | L21: 0 | M21: 0 | N21: 0 | O21: 150997.31 | P21: 13201583 | Q21: 0 | R21: 857544.48 | S21: 0 | T21: 0 | U21: 14059127 | V21: -13908130 | W21: 0 | X21: 12025.06 | Y21: 12025.06 | Z21: =V21-Y21 -> -13920155
A22: P861002 | B22: SQUARE | C22: 901 | D22: 高效四 | E22: C861 | F22: 深圳雾芯科技有限公司 | G22: 44623 | H22: 44964 | I22: 13134000 | J22: 295939.9 | K22: 0 | L22: 0 | M22: 0 | N22: 0 | O22: 295939.9 | P22: 149728.26 | Q22: 0 | R22: 3148.49 | S22: 0 | T22: 0 | U22: 152876.75 | V22: 143063.15 | W22: 2711.199 | X22: 4644.01 | Y22: 7355.209 | Z22: =V22-Y22 -> 135707.94
A23: P861003 | B23: P31A | C23: 901 | D23: 高效四 | E23: C861 | F23: 深圳雾芯科技有限公司 | G23: 44811 | I23: 1792500 | J23: 224153.76 | K23: 0 | L23: 0 | M23: 0 | N23: 0 | O23: 224153.76 | P23: 288183.66 | Q23: 0 | R23: 17181.05 | S23: 0 | T23: 0 | U23: 305364.71 | V23: -81210.95 | W23: 0 | X23: 1800.29 | Y23: 1800.29 | Z23: =V23-Y23 -> -83011.24
A24: P820002 | B24: AK02 | C24: 901 | D24: 高效四 | E24: C820 | F24: NJOY, LLC. | G24: 44487 | I24: 284500 | J24: 0 | K24: 0 | L24: 0 | M24: 0 | N24: 0 | O24: 0 | P24: 0 | Q24: 0 | R24: 0 | S24: 0 | T24: 0 | U24: 0 | V24: 0 | W24: 0 | X24: 0 | Y24: 0 | Z24: =V24-Y24 -> 0
A25: P824009 | B25: X2-AIR | C25: 901 | D25: 高效四 | E25: C824 | F25: NICOVENTURES TRADING LIMITED | G25: 44925 | I25: 200000 | J25: 0 | K25: 0 | L25: 0 | M25: 0 | N25: 0 | O25: 0 | P25: 0 | Q25: 0 | R25: 0 | S25: 0 | T25: 0 | U25: 0 | V25: 0 | W25: 0 | X25: 0 | Y25: 0 | Z25: =V25-Y25 -> 0
A26: P824010 | B26: MIMOSA | C26: 901 | D26: 高效四 | E26: C824 | F26: NICOVENTURES TRADING LIMITED | G26: 44935 | I26: 69500 | J26: 42912.73 | K26: 0 | L26: 8433.39 | M26: 0 | N26: 0 | O26: 51346.12 | P26: 0 | Q26: 0 | R26: 2183.97 | S26: 840.09 | T26: 1221.74 | U26: 4245.8 | V26: 47100.32 | W26: 0 | X26: 0 | Y26: 0 | Z26: =V26-Y26 -> 47100.32
A27: P805016 | B27: J19 | C27: 901 | D27: 高效四 | E27: C805 | F27: 深圳市合元科技有限公司 | G27: 44226 | H27: 44406 | I27: 0 | J27: 0 | K27: 0 | L27: 0 | M27: 0 | N27: 0 | O27: 0 | P27: 0 | Q27: 0 | R27: 0 | S27: 0 | T27: 0 | U27: 0 | V27: 0 | W27: 0 | X27: 0 | Y27: 0 | Z27: =V27-Y27 -> 0
A28: P891001 | B28: 美容修复仪喷嘴 | C28: 901 | D28: 高效四 | E28: C891 | F28: 深圳麦克韦尔科技有限公司 | G28: 45015 | I28: 208350 | J28: 213421.45 | K28: 0 | L28: 4311.58 | M28: 0 | N28: 0 | O28: 217733.03 | P28: 101605.66 | Q28: 0 | R28: 0 | S28: 0 | T28: 411.89 | U28: 102017.55 | V28: 115715.48 | W28: 0 | X28: 0 | Y28: 0 | Z28: =V28-Y28 -> 115715.48
A29: P805033 | B29: X9 | C29: 901 | D29: 高效四 | E29: C805 | F29: 深圳市合元科技有限公司 | G29: 45091 | I29: 485600 | J29: 161161.64 | K29: 0 | L29: 0 | M29: 0 | N29: 0 | O29: 161161.64 | P29: 234913.8 | Q29: 0 | R29: 5037.72 | S29: 5798.99 | T29: 34428.78 | U29: 280179.29 | V29: -119017.65 | W29: 0 | X29: 0 | Y29: 0 | Z29: =V29-Y29 -> -119017.65
A30: P805013 | B30: SP03 | C30: 901 | D30: 高效四 | E30: C805 | F30: 深圳市合元科技有限公司 | G30: 44226 | H30: 44195 | I30: 0 | J30: 0 | K30: 0 | L30: 0 | M30: 0 | N30: 0 | O30: 0 | P30: 0 | Q30: 0 | R30: 0 | S30: 0 | T30: 0 | U30: 0 | V30: 0 | W30: 0 | X30: 0 | Y30: 0 | Z30: =V30-Y30 -> 0
A31: P861004 | B31: SQ-X1 | C31: 901 | D31: 高效四 | E31: C861 | F31: 深圳雾芯科技有限公司 | G31: 44887 | I31: 200000 | J31: 0 | K31: 0 | L31: 0 | M31: 0 | N31: 0 | O31: 0 | P31: 0 | Q31: 0 | R31: 0 | S31: 0 | T31: 0 | U31: 0 | V31: 0 | W31: 0 | X31: 2176.32 | Y31: 2176.32 | Z31: =V31-Y31 -> -2176.32
A32: P805041 | B32: ARTEMIS 1.1 PRO | C32: 901 | D32: 高效四 | E32: C805 | F32: 深圳市合元科技有限公司 | G32: 45240 | I32: 1542670 | J32: 0 | K32: 0 | L32: 267082.47 | M32: 0 | N32: 0 | O32: 267082.47 | P32: 470554.89 | Q32: 0 | R32: 0 | S32: 4045.05 | T32: 111828.52 | U32: 586428.46 | V32: -319345.99 | W32: 0 | X32: 0 | Y32: 0 | Z32: =V32-Y32 -> -319345.99
A33: P805036 | B33: TIGER2 | C33: 901 | D33: 高效四 | E33: C805 | F33: 深圳市合元科技有限公司 | G33: 45167 | H33: 45343 | I33: 3258000 | J33: 2596633.9 | K33: 0 | L33: 0 | M33: 0 | N33: 0 | O33: 2596633.9 | P33: 3340512.6 | Q33: 0 | R33: 0 | S33: 33731.64 | T33: 2432.26 | U33: 3376676.5 | V33: -780042.61 | W33: 60441.27 | X33: 13895.76 | Y33: 74337.03 | Z33: =V33-Y33 -> -854379.64
A34: P824012 | B34: MODI 1K BOX ENTRY | C34: 901 | D34: 高效四 | E34: C824 | F34: NICOVENTURES TRADING LIMITED | G34: 45219 | I34: 5755200 | J34: 0 | K34: 0 | L34: 448457.07 | M34: 0 | N34: 0 | O34: 448457.07 | P34: 1236473.7 | Q34: 0 | R34: 556672.07 | S34: 209005.84 | T34: 180908.72 | U34: 2183060.4 | V34: -1734603.3 | W34: 3815.5 | X34: 4031.31 | Y34: 7846.81 | Z34: =V34-Y34 -> -1742450.1
A35: P824013 | B35: MODI 5K BOX FULL | C35: 901 | D35: 高效四 | E35: C824 | F35: NICOVENTURES TRADING LIMITED | G35: 45230 | I35: 748000 | J35: 0 | K35: 0 | L35: 490821.76 | M35: 0 | N35: 0 | O35: 490821.76 | P35: 890122.74 | Q35: 0 | R35: 245869.26 | S35: 201791.4 | T35: 241779.69 | U35: 1579563.1 | V35: -1088741.3 | W35: 3089.72 | X35: 43566.55 | Y35: 46656.27 | Z35: =V35-Y35 -> -1135397.6
A36: P805040 | B36: 合元-加热不燃烧项目-F5427-实验模具启动 | C36: 901 | D36: 高效四 | E36: C805 | F36: 深圳市合元科技有限公司 | G36: 45233 | I36: 410000 | J36: 0 | K36: 0 | L36: 0 | M36: 0 | N36: 0 | O36: 0 | P36: 1047.32 | Q36: 0 | R36: 0 | S36: 11757.32 | T36: 45578.37 | U36: 58383.01 | V36: -58383.01 | W36: 0 | X36: 180.25 | Y36: 180.25 | Z36: =V36-Y36 -> -58563.26
A37: P824014 | B37: MODI 1K BOX FULL | C37: 901 | D37: 高效四 | E37: C824 | F37: NICOVENTURES TRADING LIMITED | G37: 45230 | I37: 447700 | J37: 0 | K37: 0 | L37: 223341.81 | M37: 0 | N37: 0 | O37: 223341.81 | P37: 320542.31 | Q37: 0 | R37: 75610.64 | S37: 37731.2 | T37: -22588.91 | U37: 411295.24 | V37: -187953.43 | W37: 3086.86 | X37: 5117.63 | Y37: 8204.49 | Z37: =V37-Y37 -> -196157.92
A38: P805038 | B38: DOVE-电子烟 | C38: 901 | D38: 高效四 | E38: C805 | F38: 深圳市合元科技有限公司 | G38: 45219 | I38: 562900 | J38: 0 | K38: 0 | L38: 61185.32 | M38: 0 | N38: 0 | O38: 61185.32 | P38: 2693.35 | Q38: 0 | R38: 0 | S38: 4473.97 | T38: 12389.94 | U38: 19557.26 | V38: 41628.06 | W38: 0 | X38: 0 | Y38: 0 | Z38: =V38-Y38 -> 41628.06
A39: P805037 | B39: F5433 | C39: 901 | D39: 高效四 | E39: C805 | F39: 深圳市合元科技有限公司 | G39: 45183 | I39: 458500 | J39: 0 | K39: 0 | L39: 0 | M39: 0 | N39: 0 | O39: 0 | P39: 0 | Q39: 0 | R39: 0 | S39: 0 | T39: 0 | U39: 0 | V39: 0 | W39: 0 | X39: 0 | Y39: 0 | Z39: =V39-Y39 -> 0
A40: P824015 | B40: HESTIA | C40: 901 | D40: 高效四 | E40: C824 | F40: NICOVENTURES TRADING LIMITED | G40: 45257 | I40: 2673000 | J40: 0 | K40: 0 | L40: 10124.76 | M40: 0 | N40: 0 | O40: 10124.76 | P40: 47808.82 | Q40: 0 | R40: 0 | S40: 90569.79 | T40: -4197.69 | U40: 134180.92 | V40: -124056.16 | W40: 12213.36 | X40: 60466.75 | Y40: 72680.11 | Z40: =V40-Y40 -> -196736.27
A41: P824016 | B41: MODI 2.0 1K BOX ESG | C41: 901 | D41: 高效四 | E41: C824 | F41: NICOVENTURES TRADING LIMITED | G41: 45271 | I41: 989000 | J41: 0 | K41: 0 | L41: 50354.72 | M41: 0 | N41: 0 | O41: 50354.72 | P41: 402478.44 | Q41: 0 | R41: 125.72 | S41: 859.18 | T41: 3663.61 | U41: 407126.95 | V41: -356772.23 | W41: 0 | X41: 0 | Y41: 0 | Z41: =V41-Y41 -> -356772.23
A42: P824020 | B42: MODI 8K BOX FULL | C42: 901 | D42: 高效四 | E42: C824 | F42: NICOVENTURES TRADING LIMITED | G42: 45304 | I42: 640000 | J42: 0 | K42: 0 | L42: 9570.3 | M42: 0 | N42: 0 | O42: 9570.3 | P42: 0 | Q42: 0 | R42: 0 | S42: 0 | T42: 2056.58 | U42: 2056.58 | V42: 7513.72 | W42: 0 | X42: 0 | Y42: 0 | Z42: =V42-Y42 -> 7513.72
A43: P824017 | B43: MODI 1K PEN DEFAULT | C43: 901 | D43: 高效四 | E43: C824 | F43: NICOVENTURES TRADING LIMITED | G43: 45304 | I43: 7788000 | J43: 0 | K43: 0 | L43: 0 | M43: 0 | N43: 0 | O43: 0 | P43: 170682.99 | Q43: 0 | R43: 203125 | S43: 184500.17 | T43: 35266.13 | U43: 593574.29 | V43: -593574.29 | W43: 20884.19 | X43: 0 | Y43: 20884.19 | Z43: =V43-Y43 -> -614458.48
A44: P805026 | B44: PLUZE 1.5 | C44: 901 | D44: 高效四 | E44: C805 | F44: 深圳市合元科技有限公司 | G44: 44670 | H44: 45009 | I44: 4467880 | J44: 0 | K44: 0 | L44: 0 | M44: 0 | N44: 0 | O44: 0 | P44: 19433.15 | Q44: 0 | R44: 0 | S44: 0 | T44: 355.1 | U44: 19788.25 | V44: -19788.25 | W44: 0 | X44: 6417.38 | Y44: 6417.38 | Z44: =V44-Y44 -> -26205.63
A45: P805017 | B45: DM1 | C45: 901 | D45: 高效四 | E45: C805 | F45: 深圳市合元科技有限公司 | G45: 44226 | H45: 44364 | I45: 0 | J45: 38185.79 | K45: 0 | L45: 0 | M45: 0 | N45: 0 | O45: 38185.79 | P45: 0 | Q45: 0 | R45: 4079.78 | S45: 0 | T45: 0 | U45: 4079.78 | V45: 34106.01 | W45: 0 | X45: 0 | Y45: 0 | Z45: =V45-Y45 -> 34106.01
A46: P805039 | B46: LYRA BASIC | C46: 901 | D46: 高效四 | E46: C805 | F46: 深圳市合元科技有限公司 | G46: 45226 | I46: 267800 | J46: 0 | K46: 0 | L46: 0 | M46: 0 | N46: 0 | O46: 0 | P46: 429.59 | Q46: 0 | R46: 0 | S46: 3054.87 | T46: 27287.96 | U46: 30772.42 | V46: -30772.42 | W46: 0 | X46: 818.63 | Y46: 818.63 | Z46: =V46-Y46 -> -31591.05
A47: P824018 | B47: MODI 1K PEN FULL | C47: 901 | D47: 高效四 | E47: C824 | F47: NICOVENTURES TRADING LIMITED | G47: 45304 | I47: 8698190 | J47: 0 | K47: 0 | L47: 11628.85 | M47: 0 | N47: 0 | O47: 11628.85 | P47: 18452.48 | Q47: 0 | R47: 0 | S47: 45133.69 | T47: 16331.07 | U47: 79917.24 | V47: -68288.39 | W47: 0 | X47: 1562.28 | Y47: 1562.28 | Z47: =V47-Y47 -> -69850.67
A48: P922001 | B48: ALPHA | C48: 901 | D48: 高效四 | E48: C922 | F48: Philip Morris Asia Limited | G48: 45362 | I48: 1025000 | J48: 0 | K48: 0 | L48: 0 | M48: 0 | N48: 0 | O48: 0 | P48: 0 | Q48: 0 | R48: 0 | S48: 0 | T48: 15232.68 | U48: 15232.68 | V48: -15232.68 | W48: 0 | X48: 0 | Y48: 0 | Z48: =V48-Y48 -> -15232.68
A49: P824021 | B49: CLYDE | C49: 901 | D49: 高效四 | E49: C824 | F49: NICOVENTURES TRADING LIMITED | G49: 45323 | I49: 1055900 | J49: 0 | K49: 0 | L49: 0 | M49: 0 | N49: 0 | O49: 0 | P49: 0 | Q49: 0 | R49: 0 | S49: 2673.01 | T49: 76203.66 | U49: 78876.67 | V49: -78876.67 | W49: 0 | X49: 0 | Y49: 0 | Z49: =V49-Y49 -> -78876.67
A50: P824023 | B50: MD2.0-3K BOX | C50: 901 | D50: 高效四 | E50: C824 | F50: NICOVENTURES TRADING LIMITED | G50: 45393 | I50: 388200 | J50: 0 | K50: 0 | L50: 2371.81 | M50: 0 | N50: 0 | O50: 2371.81 | P50: 0 | Q50: 0 | R50: 0 | S50: 0 | T50: 12596.7 | U50: 12596.7 | V50: -10224.89 | W50: 0 | X50: 0 | Y50: 0 | Z50: =V50-Y50 -> -10224.89
A51: P805034 | B51: KUGA | C51: 901 | D51: 高效四 | E51: C805 | F51: 深圳市合元科技有限公司 | G51: 45133 | I51: 648900 | J51: 0 | K51: 0 | L51: 0 | M51: 0 | N51: 0 | O51: 0 | P51: 0 | Q51: 0 | R51: 318030.04 | S51: 0 | T51: 0 | U51: 318030.04 | V51: -318030.04 | W51: 0 | X51: 0 | Y51: 0 | Z51: =V51-Y51 -> -318030.04
A52: P824019 | B52: MODI 5K BOX FULL-ESG | C52: 901 | D52: 高效四 | E52: C824 | F52: NICOVENTURES TRADING LIMITED | G52: 45304 | I52: 750000 | J52: 0 | K52: 0 | L52: 0 | M52: 0 | N52: 0 | O52: 0 | P52: 0 | Q52: 0 | R52: 0 | S52: 0 | T52: 0 | U52: 0 | V52: 0 | W52: 0 | X52: 1635.7 | Y52: 1635.7 | Z52: =V52-Y52 -> -1635.7
A53: P824024 | B53: HESTIA 1.1 | C53: 901 | D53: 高效四 | E53: C824 | F53: NICOVENTURES TRADING LIMITED | G53: 45393 | I53: 445500 | J53: 0 | K53: 0 | L53: 60883.61 | M53: 0 | N53: 0 | O53: 60883.61 | P53: 0 | Q53: 0 | R53: 0 | S53: 0 | T53: 1402.49 | U53: 1402.49 | V53: 59481.12 | W53: 0 | X53: 0 | Y53: 0 | Z53: =V53-Y53 -> 59481.12
A54: P891002 | B54: T65F | C54: 901 | D54: 高效四 | E54: C891 | F54: 深圳麦克韦尔科技有限公司 | G54: 45408 | I54: 176000 | J54: 0 | K54: 0 | L54: 0 | M54: 0 | N54: 0 | O54: 0 | P54: 2097.95 | Q54: 0 | R54: 0 | S54: 0 | T54: 0 | U54: 2097.95 | V54: -2097.95 | W54: 0 | X54: 0 | Y54: 0 | Z54: =V54-Y54 -> -2097.95
A55: 合计 | I55: =SUM(I4:I54) -> 289888370 | J55: =SUM(J4:J54) -> 6939136.6 | K55: =SUM(K4:K54) -> 0 | L55: =SUM(L4:L54) -> 1880467.3 | M55: =SUM(M4:M54) -> 0 | N55: =SUM(N4:N54) -> 0 | O55: =SUM(O4:O54) -> 8819603.8 | P55: =SUM(P4:P54) -> 31868362 | ... Z55: =SUM(Z4:Z54) -> -28587226

Sheet SD1
A1: SD1 2024年1-6月NPI报表明细
A2: 币别:HKD
A3: TK项目号 | B3: 项目名称 | C3: 利润中心 | D3: 事业部 | E3: 终端客户 | F3: 终端客户名称 | G3: 创建日期 | H3: 量产日期 | I3: NPI预算收入 | J3: 注塑模具收入 | K3: 其他模具收入 | L3: 样板费收入 | M3: 夹治具收入 | N3: 其它杂项收入 | O3: 量产前收入 | P3: 注塑模具成本 | Q3: 其他模具成本 | R3: 自费模具摊销 | S3: 量产前夹治具成本 | T3: 试模成本 | U3: 量产前成本 | V3: 量产前收益 | W3: 量产后夹治具成本 | X3: 量产后打样成本 | Y3: 量产后成本 | Z3: 项目收益
A4: P360008 | B4: ELAINE | C4: 300 | D4: 特种一 | E4: 360 | F4: Google Inc. | G4: 44226 | H4: 44237 | I4: 0 | J4: 0 | K4: 0 | L4: 0 | M4: 0 | N4: 0 | O4: 0 | P4: 0 | Q4: 0 | R4: 0 | S4: 0 | T4: 0 | U4: 0 | V4: 0 | W4: 0 | X4: 0 | Y4: 0 | Z4: =V4-Y4 -> 0
A5: P360012 | B5: SENSOR FLEX BRACKET | C5: 300 | D5: 特种一 | E5: 360 | F5: Google Inc. | G5: 44226 | H5: 42181 | I5: 0 | J5: 0 | K5: 0 | L5: 0 | M5: 0 | N5: 0 | O5: 0 | P5: 0 | Q5: 0 | R5: 3277.54 | S5: 0 | T5: 0 | U5: 3277.54 | V5: -3277.54 | W5: 0 | X5: 0 | Y5: 0 | Z5: =V5-Y5 -> -3277.54
A6: P360018 | B6: ECHO | C6: 300 | D6: 特种一 | E6: 360 | F6: Google Inc. | G6: 44226 | H6: 42373 | I6: 0 | J6: 0 | K6: 0 | L6: 0 | M6: 0 | N6: 0 | O6: 0 | P6: 0 | Q6: 0 | R6: 0 | S6: 0 | T6: 0 | U6: 0 | V6: 0 | W6: 0 | X6: 0 | Y6: 0 | Z6: =V6-Y6 -> 0
A7: P360023 | B7: ZERO DRAFT ADAPTOR | C7: 300 | D7: 特种一 | E7: 360 | F7: Google Inc. | G7: 44657 | H7: (空白) | I7: 836000 | J7: 0 | K7: 0 | L7: 0 | M7: 0 | N7: 0 | O7: 0 | P7: 0 | Q7: 0 | R7: 2484.52 | S7: 0 | T7: 0 | U7: 2484.52 | V7: -2484.52 | W7: 0 | X7: 0 | Y7: 0 | Z7: =V7-Y7 -> -2484.52
A8: P360024 | B8: NTI PHONE CASE | C8: 300 | D8: 特种一 | E8: 360 | F8: Google Inc. | G8: 44722 | H8: (空白) | I8: 0 | J8: 0 | K8: 0 | L8: 0 | M8: 0 | N8: 0 | O8: 0 | P8: 0 | Q8: 0 | R8: 0 | S8: 0 | T8: 0 | U8: 0 | V8: 0 | W8: 0 | X8: 0 | Y8: 0 | Z8: =V8-Y8 -> 0
A9: P391001 | B9: GENEVA | C9: 300 | D9: 特种一 | E9: 391 | F9: Latch Systems, Inc. | G9: 44226 | H9: 44301 | I9: 0 | J9: 0 | K9: 0 | L9: 0 | M9: 0 | N9: 0 | O9: 0 | P9: 0 | Q9: 0 | R9: 6077.4 | S9: 0 | T9: 0 | U9: 6077.4 | V9: -6077.4 | W9: 0 | X9: 0 | Y9: 0 | Z9: =V9-Y9 -> -6077.4
A10: P404003 | B10: BOSS | C10: 300 | D10: 特种一 | E10: 404 | F10: Google Inc | G10: 44226 | H10: 44034 | I10: 0 | J10: 0 | K10: 0 | L10: 0 | M10: 0 | N10: 0 | O10: 0 | P10: 0 | Q10: 0 | R10: 1356.55 | S10: 0 | T10: 0 | U10: 1356.55 | V10: -1356.55 | W10: 125.67 | X10: 0 | Y10: 125.67 | Z10: =V10-Y10 -> -1482.22
A11: P404006 | B11: D3 | C11: 300 | D11: 特种一 | E11: 404 | F11: Google Inc | G11: 44226 | H11: 42657 | I11: 0 | J11: 0 | K11: 0 | L11: 0 | M11: 0 | N11: 0 | O11: 0 | P11: 0 | Q11: 0 | R11: 124124.61 | S11: 0 | T11: 0 | U11: 124124.61 | V11: -124124.61 | W11: 112505.6 | X11: 0 | Y11: 112505.6 | Z11: =V11-Y11 -> -236630.21
A12: P404014 | B12: BISMUTH | C12: 300 | D12: 特种一 | E12: 404 | F12: Google Inc | G12: 44334 | H12: 43328 | I12: 67325484 | J12: 544635 | K12: 0 | L12: 140072.18 | M12: 230100 | N12: 0 | O12: 914807.18 | P12: 614996.69 | Q12: 0 | R12: 2116.24 | S12: 93829.46 | T12: 225277.77 | U12: 936220.16 | V12: -21412.98 | W12: 169196.96 | X12: 62893.21 | Y12: 232090.17 | Z12: =V12-Y12 -> -253503.15
A13: P437020 | B13: MIRA | C13: 300 | D13: 特种一 | E13: 437 | F13: Fitbit Inc. | G13: 44226 | H13: 43993 | I13: 0 | J13: 0 | K13: 0 | L13: 0 | M13: 0 | N13: 0 | O13: 0 | P13: 0 | Q13: 0 | R13: 0 | S13: 0 | T13: 0 | U13: 0 | V13: 0 | W13: 0 | X13: 0 | Y13: 0 | Z13: =V13-Y13 -> 0
A14: P437021 | B14: Atlas | C14: 300 | D14: 特种一 | E14: 437 | F14: Fitbit Inc. | G14: 44226 | H14: 44042 | I14: 0 | J14: 0 | K14: 0 | L14: 0 | M14: 0 | N14: 0 | O14: 0 | P14: 0 | Q14: 0 | R14: 0 | S14: 0 | T14: 0 | U14: 0 | V14: 0 | W14: 0 | X14: 0 | Y14: 0 | Z14: =V14-Y14 -> 0
A15: P437028 | B15: BUZZ | C15: 300 | D15: 特种一 | E15: 437 | F15: Fitbit Inc. | G15: 44226 | H15: 44364 | I15: 0 | J15: 0 | K15: 0 | L15: 0 | M15: 0 | N15: 0 | O15: 0 | P15: 0 | Q15: 0 | R15: 0 | S15: 0 | T15: 0 | U15: 0 | V15: 0 | W15: 2887.48 | X15: 0 | Y15: 2887.48 | Z15: =V15-Y15 -> -2887.48
A16: P437029 | B16: MORGAN | C16: 300 | D16: 特种一 | E16: 437 | F16: Fitbit Inc. | G16: 44226 | H16: 44407 | I16: 1702800 | J16: 0 | K16: 0 | L16: 0 | M16: 0 | N16: 0 | O16: 0 | P16: 0 | Q16: 0 | R16: 71702.32 | S16: 0 | T16: 0 | U16: 71702.32 | V16: -71702.32 | W16: 0 | X16: 0 | Y16: 0 | Z16: =V16-Y16 -> -71702.32
A17: P437030 | B17: RHEA | C17: 300 | D17: 特种一 | E17: 437 | F17: Fitbit Inc. | G17: 44226 | H17: 44175 | I17: 5227500 | J17: 0 | K17: 0 | L17: 0 | M17: 0 | N17: 0 | O17: 0 | P17: 0 | Q17: 0 | R17: 25128.83 | S17: 0 | T17: 0 | U17: 25128.83 | V17: -25128.83 | W17: 1803.05 | X17: 0 | Y17: 1803.05 | Z17: =V17-Y17 -> -26931.88
A18: P437031 | B18: HERA | C18: 300 | D18: 特种一 | E18: 437 | F18: Fitbit Inc. | G18: 44384 | H18: 44426 | I18: 805290 | J18: 0 | K18: 0 | L18: 0 | M18: 0 | N18: 0 | O18: 0 | P18: 0 | Q18: 0 | R18: 0 | S18: 0 | T18: 0 | U18: 0 | V18: 0 | W18: 763.71 | X18: 0 | Y18: 763.71 | Z18: =V18-Y18 -> -763.71
A19: P437032 | B19: RENO | C19: 300 | D19: 特种一 | E19: 437 | F19: Fitbit Inc. | G19: 44488 | H19: 44774 | I19: 1460200 | J19: 33076.59 | K19: 0 | L19: 0 | M19: 0 | N19: 0 | O19: 33076.59 | P19: 0 | Q19: 0 | R19: 0 | S19: 0 | T19: 0 | U19: 0 | V19: 33076.59 | W19: 0 | X19: 2663.46 | Y19: 2663.46 | Z19: =V19-Y19 -> 30413.13
A20: P437033 | B20: P11 | C20: 300 | D20: 特种一 | E20: 437 | F20: Fitbit Inc. | G20: 44628 | I20: 14160122 | J20: 0 | K20: 0 | L20: 9920.35 | M20: 25222.76 | N20: 21680.56 | O20: 56823.67 | P20: 0 | Q20: 17543.17 | R20: 88407.34 | S20: 0 | T20: 54587.07 | U20: 160537.58 | V20: -103713.91 | W20: 42823.07 | X20: 110494.55 | Y20: 153317.62 | Z20: =V20-Y20 -> -257031.53
A21: P437034 | B21: EOS | C21: 300 | D21: 特种一 | E21: 437 | F21: Fitbit Inc. | G21: 44805 | I21: 8042400 | J21: 0 | K21: 0 | L21: 0 | M21: 0 | N21: 0 | O21: 0 | P21: 0 | Q21: 0 | R21: 136804.84 | S21: 0 | T21: 0 | U21: 136804.84 | V21: -136804.84 | W21: 3976.45 | X21: 0 | Y21: 3976.45 | Z21: =V21-Y21 -> -140781.29
A22: P437035 | B22: FM22( MORGAN 2) | C22: 300 | D22: 特种一 | E22: 437 | F22: Fitbit Inc. | G22: 44847 | I22: 4560000 | J22: 185878 | K22: 0 | L22: 48259.34 | M22: 52717.5 | N22: 0 | O22: 286854.84 | P22: 166353 | Q22: 0 | R22: 109797.68 | S22: 0 | T22: 0 | U22: 276150.68 | V22: 10704.16 | W22: 84.01 | X22: 1088.3 | Y22: 1172.31 | Z22: =V22-Y22 -> 9531.85
A23: P440052 | B23: SBA-0041 | C23: 300 | D23: 特种一 | E23: 440 | F23: Otter Products LLC (for mold) | G23: 44226 | H23: 44336 | I23: 0 | J23: 0 | K23: 0 | L23: 0 | M23: 0 | N23: 0 | O23: 0 | P23: 0 | Q23: 0 | R23: 0 | S23: 0 | T23: 0 | U23: 0 | V23: 0 | W23: 100423.38 | X23: 0 | Y23: 100423.38 | Z23: =V23-Y23 -> -100423.38
A24: P440054 | B24: TechDev 2021 | C24: 300 | D24: 特种一 | E24: 440 | F24: Otter Products LLC (for mold) | G24: 44228 | H24: 44313 | I24: 0 | J24: 0 | K24: 0 | L24: 0 | M24: 0 | N24: 0 | O24: 0 | P24: 0 | Q24: 0 | R24: 0 | S24: 0 | T24: 0 | U24: 0 | V24: 0 | W24: 0 | X24: 0 | Y24: 0 | Z24: =V24-Y24 -> 0
A25: P440060 | B25: RAMV-0227 | C25: 300 | D25: 特种一 | E25: 440 | F25: Otter Products LLC (for mold) | G25: 44329 | H25: 44431 | I25: 0 | J25: 0 | K25: 0 | L25: 0 | M25: 0 | N25: 0 | O25: 0 | P25: 0 | Q25: 0 | R25: 0 | S25: 0 | T25: 0 | U25: 0 | V25: 0 | W25: 0 | X25: 0 | Y25: 0 | Z25: =V25-Y25 -> 0
A26: P440071 | B26: TECHDEV 2022 | C26: 300 | D26: 特种一 | E26: 440 | F26: Otter Products LLC (for mold) | G26: 44623 | I26: 0 | J26: 0 | K26: 0 | L26: 0 | M26: 0 | N26: 0 | O26: 0 | P26: 0 | Q26: 0 | R26: 0 | S26: 0 | T26: 0 | U26: 0 | V26: 0 | W26: 0 | X26: 0 | Y26: 0 | Z26: =V26-Y26 -> 0
A27: P440072 | B27: JAMS-0193 | C27: 300 | D27: 特种一 | E27: 440 | F27: Otter Products LLC (for mold) | G27: 44698 | H27: 44952 | I27: 0 | J27: 0 | K27: 0 | L27: 0 | M27: 0 | N27: 0 | O27: 0 | P27: 0 | Q27: 0 | R27: 0 | S27: 0 | T27: 0 | U27: 0 | V27: 0 | W27: 0 | X27: 0 | Y27: 0 | Z27: =V27-Y27 -> 0
A28: P440073 | B28: JAMS-0227 | C28: 300 | D28: 特种一 | E28: 440 | F28: Otter Products LLC (for mold) | G28: 44698 | H28: 44826 | I28: 0 | J28: 0 | K28: 0 | L28: 0 | M28: 0 | N28: 0 | O28: 0 | P28: 0 | Q28: 0 | R28: 0 | S28: 0 | T28: -9156.37 | U28: -9156.37 | V28: 9156.37 | W28: 0 | X28: 0 | Y28: 0 | Z28: =V28-Y28 -> 9156.37
A29: P440074 | B29: JAMS-0277 | C29: 300 | D29: 特种一 | E29: 440 | F29: Otter Products LLC (for mold) | G29: 44698 | H29: 44826 | I29: 0 | J29: 0 | K29: 0 | L29: 0 | M29: 0 | N29: 0 | O29: 0 | P29: 0 | Q29: 0 | R29: 0 | S29: 0 | T29: 0 | U29: 0 | V29: 0 | W29: 0 | X29: 0 | Y29: 0 | Z29: =V29-Y29 -> 0
A30: P440075 | B30: JAMS-0097 | C30: 300 | D30: 特种一 | E30: 440 | F30: Otter Products LLC (for mold) | G30: 44698 | H30: 44838 | I30: 15668730 | J30: 0 | K30: 0 | L30: 83983.05 | M30: 0 | N30: 0 | O30: 83983.05 | P30: 0 | Q30: 0 | R30: 0 | S30: 0 | T30: 57554.78 | U30: 57554.78 | V30: 26428.27 | W30: 2003.31 | X30: 0 | Y30: 2003.31 | Z30: =V30-Y30 -> 24424.96
A31: P440076 | B31: JAMS-0085 | C31: 300 | D31: 特种一 | E31: 440 | F31: Otter Products LLC (for mold) | G31: 44698 | H31: 44830 | I31: 7643856 | J31: 0 | K31: 0 | L31: 0 | M31: 0 | N31: 0 | O31: 0 | P31: 0 | Q31: 0 | R31: 0 | S31: 1900.51 | T31: 0 | U31: 1900.51 | V31: -1900.51 | W31: 34953.85 | X31: 0 | Y31: 34953.85 | Z31: =V31-Y31 -> -36854.36
A32: P440078 | B32: JAMS-0262 | C32: 300 | D32: 特种一 | E32: 440 | F32: Otter Products LLC (for mold) | G32: 44698 | I32: 0 | J32: 0 | K32: 0 | L32: 0 | M32: 0 | N32: 0 | O32: 0 | P32: 0 | Q32: 0 | R32: 0 | S32: 0 | T32: 0 | U32: 0 | V32: 0 | W32: 0 | X32: 0 | Y32: 0 | Z32: =V32-Y32 -> 0
A33: P440080 | B33: JAMS-0041 | C33: 300 | D33: 特种一 | E33: 440 | F33: Otter Products LLC (for mold) | G33: 44699 | H33: 44830 | I33: 0 | J33: 0 | K33: 0 | L33: 0 | M33: 0 | N33: 0 | O33: 0 | P33: 0 | Q33: 0 | R33: 0 | S33: 0 | T33: 0 | U33: 0 | V33: 0 | W33: 0 | X33: 0 | Y33: 0 | Z33: =V33-Y33 -> 0
A34: P440083 | B34: SMURFS-99-DRIFTER | C34: 300 | D34: 特种一 | E34: 440 | F34: Otter Products LLC (for mold) | G34: 44921 | I34: 0 | J34: 0 | K34: 0 | L34: 0 | M34: 0 | N34: 0 | O34: 0 | P34: 0 | Q34: 0 | R34: 0 | S34: 0 | T34: 0 | U34: 0 | V34: 0 | W34: 0 | X34: 0 | Y34: 0 | Z34: =V34-Y34 -> 0
A35: P440084 | B35: SMURFS-99-CIRCA | C35: 300 | D35: 特种一 | E35: 440 | F35: Otter Products LLC (for mold) | G35: 44921 | I35: 3655260 | J35: 0 | K35: 0 | L35: 3112 | M35: 0 | N35: 0 | O35: 3112 | P35: 0 | Q35: 0 | R35: 0 | S35: 0 | T35: 89681.59 | U35: 89681.59 | V35: -86569.59 | W35: 769.52 | X35: 0 | Y35: 769.52 | Z35: =V35-Y35 -> -87339.11
A36: P440085 | B36: TECHDEV 2023 | C36: 300 | D36: 特种一 | E36: 440 | F36: Otter Products LLC (for mold) | G36: 44930 | I36: 0 | J36: 0 | K36: 0 | L36: 0 | M36: 0 | N36: 0 | O36: 0 | P36: 0 | Q36: 0 | R36: 0 | S36: 0 | T36: 0 | U36: 0 | V36: 0 | W36: 0 | X36: 0 | Y36: 0 | Z36: =V36-Y36 -> 0
A37: P815005 | B37: URANUS | C37: 300 | D37: 特种一 | E37: C815 | F37: 问问智能信息科技有限公司 | G37: 44629 | I37: 0 | J37: 0 | K37: 0 | L37: 0 | M37: 0 | N37: 0 | O37: 0 | P37: 0 | Q37: 0 | R37: 0 | S37: 0 | T37: 0 | U37: 0 | V37: 0 | W37: 0 | X37: 0 | Y37: 0 | Z37: =V37-Y37 -> 0
A38: P440055 | B38: AST-0227 | C38: 300 | D38: 特种一 | E38: 440 | F38: Otter Products LLC (for mold) | G38: 44250 | H38: 44377 | I38: 90783 | J38: 0 | K38: 0 | L38: 0 | M38: 0 | N38: 0 | O38: 0 | P38: 0 | Q38: 0 | R38: 0 | S38: 0 | T38: 0 | U38: 0 | V38: 0 | W38: 0 | X38: 0 | Y38: 0 | Z38: =V38-Y38 -> 0
A39: P440046 | B39: SHAMROCK | C39: 300 | D39: 特种一 | E39: 440 | F39: Otter Products LLC (for mold) | G39: 44226 | H39: 44169 | I39: 0 | J39: 0 | K39: 0 | L39: 0 | M39: 0 | N39: 0 | O39: 0 | P39: 0 | Q39: 0 | R39: 0 | S39: 0 | T39: 0 | U39: 0 | V39: 0 | W39: 0 | X39: 0 | Y39: 0 | Z39: =V39-Y39 -> 0
A40: P437036 | B40: FL22 | C40: 300 | D40: 特种一 | E40: 437 | F40: Fitbit Inc. | G40: 44991 | I40: 526370 | J40: 0 | K40: 0 | L40: 506337.61 | M40: 3120 | N40: 0 | O40: 509457.61 | P40: 0 | Q40: 0 | R40: 3915.23 | S40: 0 | T40: 239269.28 | U40: 243184.51 | V40: 266273.1 | W40: 0 | X40: 0 | Y40: 0 | Z40: =V40-Y40 -> 266273.1
A41: P437037 | B41: FSE22 | C41: 300 | D41: 特种一 | E41: 437 | F41: Fitbit Inc. | G41: 44993 | I41: 453000 | J41: 0 | K41: 0 | L41: 518156.24 | M41: 0 | N41: 0 | O41: 518156.24 | P41: 0 | Q41: 0 | R41: 197.55 | S41: 596.95 | T41: 103728.87 | U41: 104523.37 | V41: 413632.87 | W41: 11850.96 | X41: 0 | Y41: 11850.96 | Z41: =V41-Y41 -> 401781.91
A42: P440091 | B42: MUPPETS, SMURFS-0097 | C42: 300 | D42: 特种一 | E42: 440 | F42: Otter Products LLC (for mold) | G42: 45022 | I42: 4235770 | J42: 0 | K42: 0 | L42: 0 | M42: 0 | N42: 0 | O42: 0 | P42: 0 | Q42: 0 | R42: 0 | S42: 0 | T42: 102758.15 | U42: 102758.15 | V42: -102758.15 | W42: 0 | X42: 0 | Y42: 0 | Z42: =V42-Y42 -> -102758.15
A43: P440068 | B43: FACETOFACE-0041 | C43: 300 | D43: 特种一 | E43: 440 | F43: Otter Products LLC (for mold) | G43: 44446 | H43: 44581 | I43: 3011964 | J43: 0 | K43: 0 | L43: 0 | M43: 0 | N43: 0 | O43: 0 | P43: 0 | Q43: 0 | R43: 0 | S43: 0 | T43: 0 | U43: 0 | V43: 0 | W43: 0 | X43: 0 | Y43: 0 | Z43: =V43-Y43 -> 0
A44: P404008 | B44: Onxy | C44: 300 | D44: 特种一 | E44: 404 | F44: Google Inc | G44: 44226 | H44: 43003 | I44: 0 | J44: 0 | K44: 0 | L44: 0 | M44: 0 | N44: 0 | O44: 0 | P44: 0 | Q44: 0 | R44: 0 | S44: 0 | T44: 0 | U44: 0 | V44: 0 | W44: 0 | X44: 0 | Y44: 0 | Z44: =V44-Y44 -> 0
A45: P440086 | B45: SNAP-0097 | C45: 300 | D45: 特种一 | E45: 440 | F45: Otter Products LLC (for mold) | G45: 45020 | I45: 1037575 | J45: 0 | K45: 0 | L45: 13770.6 | M45: 379664 | N45: 0 | O45: 393434.6 | P45: 0 | Q45: 0 | R45: 0 | S45: 0 | T45: 0 | U45: 0 | V45: 393434.6 | W45: 0 | X45: 0 | Y45: 0 | Z45: =V45-Y45 -> 393434.6
A46: P440087 | B46: SNAP-0227 | C46: 300 | D46: 特种一 | E46: 440 | F46: Otter Products LLC (for mold) | G46: 45020 | I46: 3173940 | J46: 0 | K46: 0 | L46: 162446.4 | M46: 0 | N46: 0 | O46: 162446.4 | P46: 0 | Q46: 0 | R46: 0 | S46: 29509.98 | T46: 120688.33 | U46: 150198.31 | V46: 12248.09 | W46: 11695.45 | X46: 10728.5 | Y46: 22423.95 | Z46: =V46-Y46 -> -10175.86
A47: P440088 | B47: SNAP-0262 | C47: 300 | D47: 特种一 | E47: 440 | F47: Otter Products LLC (for mold) | G47: 45020 | I47: 2073456 | J47: 0 | K47: 0 | L47: 0 | M47: 0 | N47: 0 | O47: 0 | P47: 0 | Q47: 0 | R47: 0 | S47: 0 | T47: 5440.85 | U47: 5440.85 | V47: -5440.85 | W47: 0 | X47: 0 | Y47: 0 | Z47: =V47-Y47 -> -5440.85
A48: P440089 | B48: SNAP-0041 | C48: 300 | D48: 特种一 | E48: 440 | F48: Otter Products LLC (for mold) | G48: 45020 | I48: 1760000 | J48: 0 | K48: 0 | L48: 0 | M48: 0 | N48: 0 | O48: 0 | P48: 0 | Q48: 0 | R48: 0 | S48: 0 | T48: 0 | U48: 0 | V48: 0 | W48: 0 | X48: 0 | Y48: 0 | Z48: =V48-Y48 -> 0
A49: P440090 | B49: SNAP-0277 | C49: 300 | D49: 特种一 | E49: 440 | F49: Otter Products LLC (for mold) | G49: 45020 | I49: 2996840 | J49: 0 | K49: 0 | L49: 117529.64 | M49: 0 | N49: 0 | O49: 117529.64 | P49: 0 | Q49: 0 | R49: 0 | S49: 0 | T49: 21970.04 | U49: 21970.04 | V49: 95559.6 | W49: 0 | X49: 0 | Y49: 0 | Z49: =V49-Y49 -> 95559.6
A50: P404010 | B50: AG1 | C50: 300 | D50: 特种一 | E50: 404 | F50: Google Inc | G50: 44226 | H50: 43430 | I50: 0 | J50: 0 | K50: 0 | L50: 0 | M50: 0 | N50: 0 | O50: 0 | P50: 0 | Q50: 0 | R50: 0 | S50: 0 | T50: 0 | U50: 0 | V50: 0 | W50: 0 | X50: 0 | Y50: 0 | Z50: =V50-Y50 -> 0
A51: P360006 | B51: Newman | C51: 300 | D51: 特种一 | E51: 360 | F51: Google Inc. | G51: 44226 | H51: 43655 | I51: 0 | J51: 0 | K51: 0 | L51: 0 | M51: 0 | N51: 0 | O51: 0 | P51: 0 | Q51: 0 | R51: 0 | S51: 0 | T51: 0 | U51: 0 | V51: 0 | W51: 0 | X51: 0 | Y51: 0 | Z51: =V51-Y51 -> 0
A52: P360003 | B52: Joplin | C52: 300 | D52: 特种一 | E52: 360 | F52: Google Inc. | G52: 44226 | H52: 43038 | I52: 0 | J52: 0 | K52: 0 | L52: 0 | M52: 0 | N52: 0 | O52: 0 | P52: 0 | Q52: 0 | R52: 0 | S52: 0 | T52: 0 | U52: 0 | V52: 0 | W52: 0 | X52: 0 | Y52: 0 | Z52: =V52-Y52 -> 0
A53: P302001 | B53: Power Pack | C53: 300 | D53: 特种一 | E53: 302 | F53: Magic Leap Inc. | G53: 44226 | H53: 43405 | I53: 0 | J53: 0 | K53: 0 | L53: 0 | M53: 0 | N53: 0 | O53: 0 | P53: 0 | Q53: 0 | R53: 0 | S53: 0 | T53: 0 | U53: 0 | V53: 0 | W53: 0 | X53: 0 | Y53: 0 | Z53: =V53-Y53 -> 0
A54: P404011 | B54: HQ-Head | C54: 300 | D54: 特种一 | E54: 404 | F54: Google Inc | G54: 44226 | H54: 42208 | I54: 0 | J54: 0 | K54: 0 | L54: 0 | M54: 0 | N54: 0 | O54: 0 | P54: 0 | Q54: 0 | R54: 0 | S54: 0 | T54: 0 | U54: 0 | V54: 0 | W54: 0 | X54: 0 | Y54: 0 | Z54: =V54-Y54 -> 0
A55: P440017 | B55: TECH DEV-84&85 | C55: 300 | D55: 特种一 | E55: 440 | F55: Otter Products LLC (for mold) | G55: 44226 | H55: 43606 | I55: 0 | J55: -9800 | K55: 0 | L55: 0 | M55: 0 | N55: 0 | O55: -9800 | P55: 0 | Q55: 0 | R55: 0 | S55: 0 | T55: 0 | U55: 0 | V55: -9800 | W55: 0 | X55: 0 | Y55: 0 | Z55: =V55-Y55 -> -9800
A56: P892001 | B56: X571 | C56: 300 | D56: 特种一 | E56: C892 | F56: Dyson R&D (Shanghai) Limitied | G56: 45070 | I56: 60500 | J56: 0 | K56: 0 | L56: 0 | M56: 0 | N56: 0 | O56: 0 | P56: 0 | Q56: 0 | R56: 0 | S56: 0 | T56: 0 | U56: 0 | V56: 0 | W56: 0 | X56: 0 | Y56: 0 | Z56: =V56-Y56 -> 0
A57: P360005 | B57: Estelle | C57: 300 | D57: 特种一 | E57: 360 | F57: Google | G57: 0 | H57: 0 | I57: 0 | J57: 0 | K57: 0 | L57: 0 | M57: 0 | N57: 0 | O57: 0 | P57: 0 | Q57: 0 | R57: 0 | S57: 0 | T57: 0 | U57: 0 | V57: 0 | W57: 0 | X57: 0 | Y57: 0 | Z57: =V57-Y57 -> 0
A58: P437017 | B58: Argon | C58: 300 | D58: 特种一 | E58: 437 | F58: Fitbit Inc. | G58: 0 | H58: 0 | I58: 0 | J58: 0 | K58: 0 | L58: 0 | M58: 0 | N58: 0 | O58: 0 | P58: 0 | Q58: 0 | R58: 0 | S58: 0 | T58: 0 | U58: 0 | V58: 0 | W58: 0 | X58: 0 | Y58: 0 | Z58: =V58-Y58 -> 0
A59: P440008 | B59: Whitetail-28IML | C59: 300 | D59: 特种一 | E59: 440 | F59: Otter Products LLC (for mold) | G59: 0 | H59: 0 | I59: 0 | J59: 0 | K59: 0 | L59: 0 | M59: 0 | N59: 0 | O59: 0 | P59: 0 | Q59: 0 | R59: 0 | S59: 0 | T59: 0 | U59: 0 | V59: 0 | W59: 0 | X59: 0 | Y59: 0 | Z59: =V59-Y59 -> 0
A60: P404004 | B60: Wall plate | C60: 300 | D60: 特种一 | E60: 40406 | F60: Google | G60: 0 | H60: 0 | I60: 0 | J60: 0 | K60: 0 | L60: 0 | M60: 0 | N60: 0 | O60: 0 | P60: 0 | Q60: 0 | R60: 0 | S60: 0 | T60: 0 | U60: 0 | V60: 0 | W60: 0 | X60: 0 | Y60: 0 | Z60: =V60-Y60 -> 0
A61: P805035 | B61: N1002 | C61: 300 | D61: 特种一 | E61: C805 | F61: 深圳市合元科技有限公司 | G61: 45141 | I61: 55000 | J61: 0 | K61: 0 | L61: 0 | M61: 0 | N61: 0 | O61: 0 | P61: 0 | Q61: 0 | R61: 0 | S61: 0 | T61: 0 | U61: 0 | V61: 0 | W61: 0 | X61: 0 | Y61: 0 | Z61: =V61-Y61 -> 0
A62: P440065 | B62: RAMV-0097 | C62: 300 | D62: 特种一 | E62: 440 | F62: Otter Products LLC (for mold) | G62: 44371 | I62: 3193960 | J62: 0 | K62: 0 | L62: 0 | M62: 0 | N62: 0 | O62: 0 | P62: 0 | Q62: 0 | R62: 0 | S62: 0 | T62: 0 | U62: 0 | V62: 0 | W62: 0 | X62: 0 | Y62: 0 | Z62: =V62-Y62 -> 0
A63: P460003 | B63: SPRINKLE | C63: 300 | D63: 特种一 | E63: 460 | F63: Amazon com, Inc | G63: 44226 | H63: 43620 | I63: 0 | J63: 0 | K63: 0 | L63: 0 | M63: 0 | N63: 0 | O63: 0 | P63: 0 | Q63: 0 | R63: 0 | S63: 572.17 | T63: 0 | U63: 572.17 | V63: -572.17 | W63: 0 | X63: 3278.06 | Y63: 3278.06 | Z63: =V63-Y63 -> -3850.23
A64: P893001 | B64: PUFFIN | C64: 300 | D64: 特种一 | E64: C893 | F64: Whoop,Inc | G64: 45133 | I64: 1634140 | J64: 0 | K64: 0 | L64: 0 | M64: 0 | N64: 0 | O64: 0 | P64: 0 | Q64: 0 | R64: 0 | S64: 34738.89 | T64: 156473.33 | U64: 191212.22 | V64: -191212.22 | W64: 7153.97 | X64: 0 | Y64: 7153.97 | Z64: =V64-Y64 -> -198366.19
A65: P437038 | B65: FMK23 | C65: 300 | D65: 特种一 | E65: 437 | F65: Fitbit Inc. | G65: 45237 | I65: 98000 | J65: 126036 | K65: 0 | L65: 0 | M65: 0 | N65: 0 | O65: 126036 | P65: 61841.26 | Q65: 0 | R65: 1019.95 | S65: 4009.5 | T65: 532.15 | U65: 67402.86 | V65: 58633.14 | W65: 0 | X65: 0 | Y65: 0 | Z65: =V65-Y65 -> 58633.14
A66: P809008 | B66: RITA | C66: 300 | D66: 特种一 | E66: C809 | F66: 歌尔股份有限公司 | G66: 45222 | I66: 865000 | J66: 0 | K66: 0 | L66: 48163.01 | M66: 0 | N66: 0 | O66: 48163.01 | P66: 52505.47 | Q66: 53460.11 | R66: 1264.47 | S66: 29394.12 | T66: 56534.26 | U66: 193158.43 | V66: -144995.42 | W66: 0 | X66: 0 | Y66: 0 | Z66: =V66-Y66 -> -144995.42
A67: P460002 | B67: Project Vesta | C67: 300 | D67: 特种一 | E67: 460 | F67: Amazon com, Inc | G67: 44226 | H67: 44407 | I67: 0 | J67: 0 | K67: 0 | L67: 0 | M67: 0 | N67: 0 | O67: 0 | P67: 0 | Q67: 0 | R67: 2170.48 | S67: 0 | T67: 0 | U67: 2170.48 | V67: -2170.48 | W67: 0 | X67: 0 | Y67: 0 | Z67: =V67-Y67 -> -2170.48
A68: P460004 | B68: POWELL | C68: 300 | D68: 特种一 | E68: 460 | F68: Amazon com, Inc | G68: 44226 | H68: 44410 | I68: 0 | J68: 0 | K68: 0 | L68: 0 | M68: 0 | N68: 0 | O68: 0 | P68: 0 | Q68: 0 | R68: 1003.54 | S68: 0 | T68: 0 | U68: 1003.54 | V68: -1003.54 | W68: 0 | X68: 0 | Y68: 0 | Z68: =V68-Y68 -> -1003.54
A69: P460012 | B69: MARLIN | C69: 300 | D69: 特种一 | E69: 460 | F69: Amazon com, Inc | G69: 44431 | H69: 44770 | I69: 3950325.7 | J69: 0 | K69: 0 | L69: 0 | M69: 0 | N69: 0 | O69: 0 | P69: 26833.04 | Q69: 0 | R69: 30241.87 | S69: 0 | T69: 0 | U69: 57074.91 | V69: -57074.91 | W69: 0 | X69: 29294.09 | Y69: 29294.09 | Z69: =V69-Y69 -> -86369
A70: P460013 | B70: GERALD | C70: 300 | D70: 特种一 | E70: 460 | F70: Amazon com, Inc | G70: 44851 | H70: 45153 | I70: 3652691.5 | J70: 0 | K70: 0 | L70: 0 | M70: 0 | N70: 0 | O70: 0 | P70: 17884.31 | Q70: 0 | R70: 22826.3 | S70: 0 | T70: 0 | U70: 40710.61 | V70: -40710.61 | W70: 0 | X70: 5668.33 | Y70: 5668.33 | Z70: =V70-Y70 -> -46378.94
A71: P460014 | B71: CITRINE | C71: 300 | D71: 特种一 | E71: 460 | F71: Amazon com, Inc | G71: 44872 | H71: 45092 | I71: 397100 | J71: 0 | K71: 0 | L71: 0 | M71: 0 | N71: 0 | O71: 0 | P71: 0 | Q71: 0 | R71: 38718.64 | S71: 0 | T71: 0 | U71: 38718.64 | V71: -38718.64 | W71: 2384.7 | X71: 0 | Y71: 2384.7 | Z71: =V71-Y71 -> -41103.34
A72: P460005 | B72: THEIA | C72: 300 | D72: 特种一 | E72: 460 | F72: Amazon com, Inc | G72: 44226 | H72: 44127 | I72: 0 | J72: 0 | K72: 0 | L72: 0 | M72: 0 | N72: 0 | O72: 0 | P72: 0 | Q72: 0 | R72: 8541.86 | S72: 463.91 | T72: 0 | U72: 9005.77 | V72: -9005.77 | W72: 1092.12 | X72: 6587.95 | Y72: 7680.07 | Z72: =V72-Y72 -> -16685.84
A73: P460011 | B73: CRUSH | C73: 300 | D73: 特种一 | E73: 460 | F73: Amazon com, Inc | G73: 44350 | H73: 44369 | I73: 3460402 | J73: 0 | K73: 0 | L73: 0 | M73: 0 | N73: 0 | O73: 0 | P73: 0 | Q73: 0 | R73: 6390.28 | S73: 0 | T73: 0 | U73: 6390.28 | V73: -6390.28 | W73: 0 | X73: 0 | Y73: 0 | Z73: =V73-Y73 -> -6390.28
A74: P460009 | B74: CORAL | C74: 300 | D74: 特种一 | E74: 460 | F74: Amazon com, Inc | G74: 44226 | H74: 44382 | I74: 4349725.9 | J74: 0 | K74: 0 | L74: 0 | M74: 0 | N74: 0 | O74: 0 | P74: 0 | Q74: 0 | R74: 30702 | S74: 8087.44 | T74: 0 | U74: 38789.44 | V74: -38789.44 | W74: 0 | X74: -2747.83 | Y74: -2747.83 | Z74: =V74-Y74 -> -36041.61
A75: P440092 | B75: PIXYSTIX-99-DAYGLOW | C75: 300 | D75: 特种一 | E75: 440 | F75: Otter Products LLC (for mold) | G75: 45282 | I75: 660000 | J75: 0 | K75: 0 | L75: 0 | M75: 226200 | N75: 0 | O75: 226200 | P75: 0 | Q75: 35651.22 | R75: 0 | S75: 12347.16 | T75: 0 | U75: 47998.38 | V75: 178201.62 | W75: 591.88 | X75: 0 | Y75: 591.88 | Z75: =V75-Y75 -> 177609.74
A76: P805036 | B76: TIGER2 | C76: 300 | D76: 特种一 | E76: C805 | F76: 深圳市合元科技有限公司 | G76: 45167 | H76: 45343 | I76: 5132100 | J76: 0 | K76: 0 | L76: 0 | M76: 0 | N76: 0 | O76: 0 | P76: 0 | Q76: 0 | R76: 0 | S76: 0 | T76: 0 | U76: 0 | V76: 0 | W76: 0 | X76: 0 | Y76: 0 | Z76: =V76-Y76 -> 0
A77: P805041 | B77: ARTEMIS 1.1 PRO | C77: 300 | D77: 特种一 | E77: C805 | F77: 深圳市合元科技有限公司 | G77: 45240 | I77: 1542670 | J77: 0 | K77: 0 | L77: 1731.44 | M77: 0 | N77: 0 | O77: 1731.44 | P77: 0 | Q77: 0 | R77: 0 | S77: 0 | T77: 0 | U77: 0 | V77: 1731.44 | W77: 0 | X77: 0 | Y77: 0 | Z77: =V77-Y77 -> 1731.44
A78: P824012 | B78: MODI 1K BOX ENTRY | C78: 300 | D78: 特种一 | E78: C824 | F78: NICOVENTURES TRADING LIMITED | G78: 45219 | I78: 15435200 | J78: 0 | K78: 0 | L78: 0 | M78: 0 | N78: 0 | O78: 0 | P78: 0 | Q78: 0 | R78: 0 | S78: 905.15 | T78: 0 | U78: 905.15 | V78: -905.15 | W78: 0 | X78: 0 | Y78: 0 | Z78: =V78-Y78 -> -905.15
A79: P921001 | B79: POLARIS2.8 | C79: 300 | D79: 特种一 | E79: C921 | F79: 汉朔科技股份有限公司 | G79: 45341 | I79: 128200 | J79: 0 | K79: 0 | L79: 22047.52 | M79: 0 | N79: 0 | O79: 22047.52 | P79: 0 | Q79: 0 | R79: 0 | S79: 1622.9 | T79: 22672.5 | U79: 24295.4 | V79: -2247.88 | W79: 0 | X79: 0 | Y79: 0 | Z79: =V79-Y79 -> -2247.88
A80: P360025 | B80: FME23 | C80: 300 | D80: 特种一 | E80: 360 | F80: Google Inc. | G80: 45348 | I80: 953697 | J80: 0 | K80: 0 | L80: 63481.39 | M80: 0 | N80: 0 | O80: 63481.39 | P80: 3245.79 | Q80: 0 | R80: 0 | S80: 14610.82 | T80: 34560.98 | U80: 52417.59 | V80: 11063.8 | W80: 0 | X80: 0 | Y80: 0 | Z80: =V80-Y80 -> 11063.8
A81: P360026 | B81: FK23 | C81: 300 | D81: 特种一 | E81: 360 | F81: Google Inc. | G81: 45348 | I81: 1315730 | J81: 0 | K81: 0 | L81: 27044 | M81: 63180 | N81: 0 | O81: 90224 | P81: 0 | Q81: 0 | R81: 0 | S81: 11904.42 | T81: 5936.75 | U81: 17841.17 | V81: 72382.83 | W81: 0 | X81: 0 | Y81: 0 | Z81: =V81-Y81 -> 72382.83
A82: P460015 | B82: MALRIN REFRESH | C82: 300 | D82: 特种一 | E82: 460 | F82: Amazon com, Inc | G82: 45313 | I82: 0 | J82: 0 | K82: 0 | L82: 0 | M82: 0 | N82: 0 | O82: 0 | P82: 0 | Q82: 10012.97 | R82: 0 | S82: 787.58 | T82: 9565.08 | U82: 20365.63 | V82: -20365.63 | W82: 21185.99 | X82: 14024.36 | Y82: 35210.35 | Z82: =V82-Y82 -> -55575.98
A83: P893002 | B83: GOOSE | C83: 300 | D83: 特种一 | E83: C893 | F83: Whoop,Inc | G83: 45322 | I83: 1213168 | J83: 0 | K83: 0 | L83: 63126.92 | M83: 57720 | N83: 0 | O83: 120846.92 | P83: 0 | Q83: 0 | R83: 0 | S83: 4474.37 | T83: 24311.92 | U83: 28786.29 | V83: 92060.63 | W83: 0 | X83: 0 | Y83: 0 | Z83: =V83-Y83 -> 92060.63
A84: P922001 | B84: ALPHA | C84: 300 | D84: 特种一 | E84: C922 | F84: Philip Morris Asia Limited | G84: 45362 | I84: 1025000 | J84: 0 | K84: 0 | L84: 0 | M84: 0 | N84: 0 | O84: 0 | P84: 0 | Q84: 0 | R84: 0 | S84: 1907.23 | T84: 38541.33 | U84: 40448.56 | V84: -40448.56 | W84: 0 | X84: 0 | Y84: 0 | Z84: =V84-Y84 -> -40448.56
A85: P921002 | B85: POLARS2.8 | C85: 300 | D85: 特种一 | E85: C921 | F85: 汉朔科技股份有限公司 | G85: 45376 | I85: 200000 | J85: 0 | K85: 0 | L85: 0 | M85: 0 | N85: 0 | O85: 0 | P85: 0 | Q85: 0 | R85: 0 | S85: 0 | T85: 5434.69 | U85: 5434.69 | V85: -5434.69 | W85: 0 | X85: 0 | Y85: 0 | Z85: =V85-Y85 -> -5434.69
A86: P921003 | B86: N266 | C86: 300 | D86: 特种一 | E86: C921 | F86: 汉朔科技股份有限公司 | G86: 45397 | I86: 238000 | J86: 0 | K86: 0 | L86: 0 | M86: 0 | N86: 0 | O86: 0 | P86: 0 | Q86: 0 | R86: 0 | S86: 0 | T86: 3214.18 | U86: 3214.18 | V86: -3214.18 | W86: 0 | X86: 0 | Y86: 0 | Z86: =V86-Y86 -> -3214.18
A87: P805040 | B87: 合元-加热不燃烧项目-F5427-实验模具启动 | C87: 300 | D87: 特种一 | E87: C805 | F87: 深圳市合元科技有限公司 | G87: 45233 | I87: 630000 | J87: 0 | K87: 0 | L87: 0 | M87: 0 | N87: 0 | O87: 0 | P87: 0 | Q87: 17660.93 | R87: 0 | S87: 0 | T87: 0 | U87: 17660.93 | V87: -17660.93 | W87: 0 | X87: 0 | Y87: 0 | Z87: =V87-Y87 -> -17660.93
A88: P440093 | B88: HART-0097 | C88: 300 | D88: 特种一 | E88: 440 | F88: Otter Products LLC (for mold) | G88: 45411 | I88: 6247876.8 | J88: 0 | K88: 0 | L88: 37204 | M88: 0 | N88: 0 | O88: 37204 | P88: 0 | Q88: 0 | R88: 0 | S88: 90235.44 | T88: 52192.34 | U88: 142427.78 | V88: -105223.78 | W88: 0 | X88: 0 | Y88: 0 | Z88: =V88-Y88 -> -105223.78
A89: P460016 | B89: BARLEY | C89: 300 | D89: 特种一 | E89: 460 | F89: Amazon com, Inc | G89: 45406 | I89: 825500 | J89: 0 | K89: 0 | L89: 0 | M89: 0 | N89: 0 | O89: 0 | P89: 0 | Q89: 0 | R89: 0 | S89: 8611.14 | T89: 9192.13 | U89: 17803.27 | V89: -17803.27 | W89: 0 | X89: 0 | Y89: 0 | Z89: =V89-Y89 -> -17803.27
A90: VIP返利 | C90: 300 | D90: 特种一 | F90: VIP返利 | I90: 0 | J90: 0 | K90: 0 | L90: 0 | M90: 0 | N90: 0 | O90: 0 | P90: -329639.78 | Q90: 0 | R90: 0 | S90: 0 | T90: 0 | U90: -329639.78 | V90: 329639.78 | W90: 0 | X90: 0 | Y90: 0 | Z90: =V90-Y90 -> 329639.78
A91: 合计 | I91: =SUM(I4:I90) -> 2.0771133e+08 | J91: =SUM(J4:J90) -> 879825.59 | K91: =SUM(K4:K90) -> 0 | L91: =SUM(L4:L90) -> 1866385.7 | M91: =SUM(M4:M90) -> 1037924.3 | N91: =SUM(N4:N90) -> 21680.56 | O91: =SUM(O4:O90) -> 3805816.1 | P91: =SUM(P4:P90) -> 614019.78 | ... Z91: =SUM(Z4:Z90) -> -214517.37

Sheet MDT
A1: MDT 2024年1-6月NPI报表明细
A2: 币别:HKD
A3: TK项目号 | B3: 项目名称 | C3: 利润中心 | D3: 事业部 | E3: 终端客户 | F3: 终端客户名称 | G3: 创建日期 | H3: 量产日期 | I3: NPI预算收入 | J3: 注塑模具收入 | K3: 其他模具收入 | L3: 样板费收入 | M3: 夹治具收入 | N3: 其它杂项收入 | O3: 量产前收入 | P3: 注塑模具成本 | Q3: 其他模具成本 | R3: 自费模具摊销 | S3: 量产前夹治具成本 | T3: 试模成本 | U3: 量产前成本 | V3: 量产前收益 | W3: 量产后夹治具成本 | X3: 量产后打样成本 | Y3: 量产后成本 | Z3: 项目收益
A4: P201009 | B4: 新产业单孔反应杯 | C4: A01 | D4: 医疗器械 | E4: C201 | F4: 深圳市新产业生物医学工程股份有限公司 | G4: 44226 | H4: 44195 | I4: 52313745 | J4: 0 | K4: 0 | L4: 0 | M4: 117776.09 | N4: 0 | O4: 117776.09 | P4: 26308.36 | Q4: 0 | R4: 6051.19 | S4: 0 | T4: 19372.84 | U4: 51732.39 | V4: 66043.7 | W4: 0 | X4: 5347.42 | Y4: 5347.42 | Z4: =V4-Y4 -> 60696.28
A5: P201010 | B5: 反应杯-16腔六联杯 | C5: A01 | D5: 医疗器械 | E5: C201 | F5: 深圳市新产业生物医学工程股份有限公司 | G5: 44616 | H5: 44848 | I5: 5247000 | J5: 576713.82 | K5: 0 | L5: 0 | M5: 0 | N5: 0 | O5: 576713.82 | P5: 0 | Q5: 0 | R5: 0 | S5: 0 | T5: 0 | U5: 0 | V5: 576713.82 | W5: 0 | X5: 2530.34 | Y5: 2530.34 | Z5: =V5-Y5 -> 574183.48
A6: P201008 | B6: 新产业反应杯 | C6: A01 | D6: 医疗器械 | E6: C201 | F6: 深圳市新产业生物医学工程股份有限公司 | G6: 44226 | H6: 44249 | I6: 0 | J6: 0 | K6: 0 | L6: 0 | M6: 0 | N6: 0 | O6: 0 | P6: 0 | Q6: 0 | R6: 0 | S6: 0 | T6: 0 | U6: 0 | V6: 0 | W6: 0 | X6: 0 | Y6: 0 | Z6: =V6-Y6 -> 0
A7: P924001 | B7: 2A00量产前二次加工打样成本 | C7: A01 | D7: 医疗器械 | E7: C924 | F7: 深圳高视科技有限公司 | G7: 45373 | I7: 6000 | J7: 0 | K7: 0 | L7: 4119.62 | M7: 0 | N7: 0 | O7: 4119.62 | P7: 0 | Q7: 0 | R7: 0 | S7: 0 | T7: 2212.76 | U7: 2212.76 | V7: 1906.86 | W7: 0 | X7: 210.02 | Y7: 210.02 | Z7: =V7-Y7 -> 1696.84
A8: P201012 | B8: 2A00量产前二次加工打样成本 | C8: A01 | D8: 医疗器械 | E8: C201 | F8: 深圳市新产业生物医学工程股份有限公司 | G8: 45288 | I8: 8152950 | J8: 0 | K8: 0 | L8: 0 | M8: 0 | N8: 0 | O8: 0 | P8: 0 | Q8: 0 | R8: 0 | S8: 22028.53 | T8: 7712.44 | U8: 29740.97 | V8: -29740.97 | W8: 0 | X8: 0 | Y8: 0 | Z8: =V8-Y8 -> -29740.97
A9: P896001 | B9: 试剂条 | C9: A01 | D9: 医疗器械 | E9: C896 | F9: 上海艾瑞德生物科技有限公司 | G9: 45075 | I9: 389300 | J9: 0 | K9: 0 | L9: 0 | M9: 0 | N9: 0 | O9: 0 | P9: 0 | Q9: 0 | R9: 0 | S9: 0 | T9: 0 | U9: 0 | V9: 0 | W9: 0 | X9: 0 | Y9: 0 | Z9: =V9-Y9 -> 0
A10: 合计 | I10: =SUM(I4:I9) -> 66108995 | J10: =SUM(J4:J9) -> 576713.82 | K10: =SUM(K4:K9) -> 0 | L10: =SUM(L4:L9) -> 4119.62 | M10: =SUM(M4:M9) -> 117776.09 | N10: =SUM(N4:N9) -> 0 | O10: =SUM(O4:O9) -> 698609.53 | P10: =SUM(P4:P9) -> 26308.36 | ... Y10: =SUM(Y4:Y9) -> 8087.78 | Z10: =V10-Y10 -> 606835.63

Sheet HCT
A1: HCT 2024年1-6月NPI报表明细
A2: 币别:HKD
A3: TK项目号 | B3: 项目名称 | C3: 利润中心 | D3: 事业部 | E3: 终端客户 | F3: 终端客户名称 | G3: 创建日期 | H3: 量产日期 | I3: NPI预算收入 | J3: 注塑模具收入 | K3: 其他模具收入 | L3: 样板费收入 | M3: 夹治具收入 | N3: 其它杂项收入 | O3: 量产前收入 | P3: 注塑模具成本 | Q3: 其他模具成本 | R3: 自费模具摊销 | S3: 量产前夹治具成本 | T3: 试模成本 | U3: 量产前成本 | V3: 量产前收益 | W3: 量产后夹治具成本 | X3: 量产后打样成本 | Y3: 量产后成本 | Z3: 项目收益
A4: P408003 | B4: CH12+ | C4: 801 | D4: 健康科技 | E4: C408 | F4: Coloplast Hungary Kft | G4: 44226 | H4: 42688 | I4: 0 | J4: 0 | K4: 0 | L4: 0 | M4: 0 | N4: 0 | O4: 0 | P4: 0 | Q4: 0 | R4: 0 | S4: 0 | T4: 0 | U4: 0 | V4: 0 | W4: 0 | X4: 0 | Y4: 0 | Z4: =V4-Y4 -> 0
A5: P438012 | B5: Tokyo | C5: 801 | D5: 健康科技 | E5: 438 | F5: Philips Domestic Appliances & | G5: 44226 | H5: 42391 | I5: 0 | J5: 0 | K5: 0 | L5: 0 | M5: 0 | N5: 0 | O5: 0 | P5: 0 | Q5: 0 | R5: 0 | S5: 0 | T5: 0 | U5: 0 | V5: 0 | W5: 0 | X5: 0 | Y5: 0 | Z5: =V5-Y5 -> 0
A6: P438018 | B6: Doutzen | C6: 801 | D6: 健康科技 | E6: 438 | F6: Philips Domestic Appliances & | G6: 44226 | H6: 42936 | I6: 0 | J6: 0 | K6: 0 | L6: 0 | M6: 0 | N6: 0 | O6: 0 | P6: 0 | Q6: 0 | R6: 0 | S6: 0 | T6: 0 | U6: 0 | V6: 0 | W6: 0 | X6: 0 | Y6: 0 | Z6: =V6-Y6 -> 0
A7: P438023 | B7: Shanghai | C7: 801 | D7: 健康科技 | E7: 438 | F7: Philips Domestic Appliances & | G7: 44226 | H7: 42909 | I7: 6202000 | J7: 0 | K7: 0 | L7: 0 | M7: 0 | N7: 0 | O7: 0 | P7: 3270.48 | Q7: 0 | R7: 3857.89 | S7: 0 | T7: 0 | U7: 7128.37 | V7: -7128.37 | W7: 0 | X7: 587.38 | Y7: 587.38 | Z7: =V7-Y7 -> -7715.75
A8: P438024 | B8: Sydney | C8: 801 | D8: 健康科技 | E8: 438 | F8: Philips Domestic Appliances & | G8: 44226 | H8: 43118 | I8: 0 | J8: 0 | K8: 0 | L8: 0 | M8: 0 | N8: 0 | O8: 0 | P8: 0 | Q8: 0 | R8: 70867.8 | S8: 0 | T8: 0 | U8: 70867.8 | V8: -70867.8 | W8: 0 | X8: 5758.02 | Y8: 5758.02 | Z8: =V8-Y8 -> -76625.82
A9: P438025 | B9: BOHU | C9: 801 | D9: 健康科技 | E9: 438 | F9: Philips Domestic Appliances & | G9: 44226 | H9: 42690 | I9: 0 | J9: 0 | K9: 0 | L9: 0 | M9: 0 | N9: 0 | O9: 0 | P9: 0 | Q9: 0 | R9: 0 | S9: 0 | T9: 0 | U9: 0 | V9: 0 | W9: 0 | X9: 0 | Y9: 0 | Z9: =V9-Y9 -> 0
A10: P438026 | B10: U-tube | C10: 801 | D10: 健康科技 | E10: 438 | F10: Philips Domestic Appliances & | G10: 44226 | H10: 43124 | I10: 120006.6 | J10: 0 | K10: 0 | L10: 0 | M10: 0 | N10: 0 | O10: 0 | P10: 9208.88 | Q10: 0 | R10: 22590.2 | S10: 0 | T10: 0 | U10: 31799.08 | V10: -31799.08 | W10: 0 | X10: 0 | Y10: 0 | Z10: =V10-Y10 -> -31799.08
A11: P438032 | B11: Hobart | C11: 801 | D11: 健康科技 | E11: 438 | F11: Philips Domestic Appliances & | G11: 44226 | H11: 43420 | I11: 0 | J11: 0 | K11: 0 | L11: 0 | M11: 0 | N11: 0 | O11: 0 | P11: 0 | Q11: 0 | R11: 26399.09 | S11: 0 | T11: 0 | U11: 26399.09 | V11: -26399.09 | W11: 0 | X11: 0 | Y11: 0 | Z11: =V11-Y11 -> -26399.09
A12: P438035 | B12: APA | C12: 801 | D12: 健康科技 | E12: 438 | F12: Philips Domestic Appliances & | G12: 44226 | H12: 44054 | I12: 0 | J12: 0 | K12: 0 | L12: 0 | M12: 0 | N12: 0 | O12: 0 | P12: 0 | Q12: 0 | R12: 18447.75 | S12: 0 | T12: 4282.82 | U12: 22730.57 | V12: -22730.57 | W12: 0 | X12: 782.37 | Y12: 782.37 | Z12: =V12-Y12 -> -23512.94
A13: P438045 | B13: OSAKA | C13: 801 | D13: 健康科技 | E13: 438 | F13: Philips Domestic Appliances & | G13: 44516 | H13: 44937 | I13: 7342600 | J13: 0 | K13: 0 | L13: 120388.34 | M13: 0 | N13: 0 | O13: 120388.34 | P13: 0 | Q13: 0 | R13: 0 | S13: 0 | T13: 0 | U13: 0 | V13: 120388.34 | W13: 0 | X13: 3166.03 | Y13: 3166.03 | Z13: =V13-Y13 -> 117222.31
A14: P438049 | B14: CAIRO | C14: 801 | D14: 健康科技 | E14: 438 | F14: Philips Domestic Appliances & | G14: 44706 | I14: 25730568 | J14: 0 | K14: 0 | L14: 315522.76 | M14: 0 | N14: 0 | O14: 315522.76 | P14: 0 | Q14: 0 | R14: 2576.15 | S14: 0 | T14: 48234.58 | U14: 50810.73 | V14: 264712.03 | W14: 0 | X14: 0 | Y14: 0 | Z14: =V14-Y14 -> 264712.03
A15: P813001 | B15: FRAZIER3 | C15: 801 | D15: 健康科技 | E15: C813 | F15: Lifescan Global Cooperation | G15: 44226 | H15: 44362 | I15: 0 | J15: 82005 | K15: 0 | L15: 0 | M15: 0 | N15: 0 | O15: 82005 | P15: 50929.01 | Q15: 0 | R15: 13594.86 | S15: 0 | T15: 0 | U15: 64523.87 | V15: 17481.13 | W15: 0 | X15: 17586.16 | Y15: 17586.16 | Z15: =V15-Y15 -> -105.03
A16: P823001 | B16: CEPHEID | C16: 801 | D16: 健康科技 | E16: C823 | F16: Cepheid US | G16: 44226 | H16: 44088 | I16: 0 | J16: 0 | K16: 0 | L16: 0 | M16: 0 | N16: 26520 | O16: 26520 | P16: 0 | Q16: 0 | R16: 0 | S16: 0 | T16: 0 | U16: 0 | V16: 26520 | W16: 0 | X16: 0 | Y16: 0 | Z16: =V16-Y16 -> 26520
A17: P201008 | B17: 新产业反应杯 | C17: 801 | D17: 健康科技 | E17: C201 | F17: 深圳市新产业生物医学工程股份有限公司 | G17: 44226 | H17: 44249 | I17: 0 | J17: 0 | K17: 0 | L17: 0 | M17: 0 | N17: 0 | O17: 0 | P17: 0 | Q17: 0 | R17: 1541.46 | S17: 0 | T17: 0 | U17: 1541.46 | V17: -1541.46 | W17: 0 | X17: 0 | Y17: 0 | Z17: =V17-Y17 -> -1541.46
A18: P201009 | B18: 新产业单孔反应杯 | C18: 801 | D18: 健康科技 | E18: C201 | F18: 深圳市新产业生物医学工程股份有限公司 | G18: 44226 | H18: 44195 | I18: 4630730.5 | J18: 0 | K18: 0 | L18: 0 | M18: 0 | N18: 0 | O18: 0 | P18: 0 | Q18: 0 | R18: 0 | S18: 0 | T18: 0 | U18: 0 | V18: 0 | W18: 0 | X18: 0 | Y18: 0 | Z18: =V18-Y18 -> 0
A19: P438037 | B19: XIAN | C19: 801 | D19: 健康科技 | E19: 438 | F19: Philips Domestic Appliances & | G19: 44226 | H19: 44005 | I19: 0 | J19: 0 | K19: 0 | L19: 0 | M19: 0 | N19: 0 | O19: 0 | P19: 0 | Q19: 0 | R19: 873.68 | S19: 0 | T19: 0 | U19: 873.68 | V19: -873.68 | W19: 0 | X19: 0 | Y19: 0 | Z19: =V19-Y19 -> -873.68
A20: P438040 | B20: SQUAMISH | C20: 801 | D20: 健康科技 | E20: 438 | F20: Philips Domestic Appliances & | G20: 44226 | H20: 44252 | I20: 0 | J20: 0 | K20: 0 | L20: 0 | M20: 0 | N20: 0 | O20: 0 | P20: 0 | Q20: 0 | R20: 0 | S20: 0 | T20: 0 | U20: 0 | V20: 0 | W20: 0 | X20: 0 | Y20: 0 | Z20: =V20-Y20 -> 0
A21: P408001 | B21: CH08 | C21: 801 | D21: 健康科技 | E21: C408 | F21: Coloplast Hungary Kft | G21: 44226 | H21: 43490 | I21: 0 | J21: 0 | K21: 0 | L21: 0 | M21: 0 | N21: 34320 | O21: 34320 | P21: 0 | Q21: 0 | R21: 0 | S21: 0 | T21: 0 | U21: 0 | V21: 34320 | W21: 0 | X21: 0 | Y21: 0 | Z21: =V21-Y21 -> 34320
A22: P813002 | B22: SELECT PLUS ENHANCEMENT | C22: 801 | D22: 健康科技 | E22: C813 | F22: Lifescan Global Cooperation | G22: 44446 | I22: 2096100 | J22: 0 | K22: 0 | L22: 0 | M22: 0 | N22: 0 | O22: 0 | P22: 0 | Q22: 0 | R22: 0 | S22: 0 | T22: 0 | U22: 0 | V22: 0 | W22: 0 | X22: 0 | Y22: 0 | Z22: =V22-Y22 -> 0
A23: P895001 | B23: 8003射频仪 | C23: 801 | D23: 健康科技 | E23: C895 | F23: 云南贝泰妮生物科技集团股份有限公司 | G23: 45068 | I23: 834000 | J23: 0 | K23: 0 | L23: 0 | M23: 0 | N23: 0 | O23: 0 | P23: 0 | Q23: 0 | R23: 0 | S23: 10744.34 | T23: 43921.45 | U23: 54665.79 | V23: -54665.79 | W23: 0 | X23: 0 | Y23: 0 | Z23: =V23-Y23 -> -54665.79
A24: P408005 | B24: CH10+ | C24: 801 | D24: 健康科技 | E24: C408 | F24: Coloplast Hungary Kft | G24: 44226 | H24: 42391 | I24: 0 | J24: 0 | K24: 0 | L24: 0 | M24: 0 | N24: 0 | O24: 0 | P24: 0 | Q24: 0 | R24: 0 | S24: 0 | T24: 0 | U24: 0 | V24: 0 | W24: 0 | X24: 0 | Y24: 0 | Z24: =V24-Y24 -> 0
A25: P408007 | B25: CH14+ | C25: 801 | D25: 健康科技 | E25: C408 | F25: Coloplast Hungary Kft | G25: 44226 | H25: 43763 | I25: 0 | J25: 0 | K25: 0 | L25: 0 | M25: 0 | N25: 0 | O25: 0 | P25: 0 | Q25: 0 | R25: 0 | S25: 0 | T25: 0 | U25: 0 | V25: 0 | W25: 0 | X25: 0 | Y25: 0 | Z25: =V25-Y25 -> 0
A26: P880001 | B26: SILKN VII | C26: 801 | D26: 健康科技 | E26: C880 | F26: 深圳市恒天伟焱科技股份有限公司 | G26: 44903 | I26: 9660000 | J26: 0 | K26: 0 | L26: 0 | M26: 0 | N26: 0 | O26: 0 | P26: 1949.24 | Q26: 0 | R26: 2208.89 | S26: 0 | T26: 0 | U26: 4158.13 | V26: -4158.13 | W26: 0 | X26: 3003.89 | Y26: 3003.89 | Z26: =V26-Y26 -> -7162.02
A27: P438043 | B27: CANARY | C27: 801 | D27: 健康科技 | E27: 438 | F27: Philips Domestic Appliances & | G27: 44302 | H27: 44364 | I27: 523426.2 | J27: 0 | K27: 0 | L27: 0 | M27: 0 | N27: 0 | O27: 0 | P27: 0 | Q27: 0 | R27: 0 | S27: 0 | T27: 0 | U27: 0 | V27: 0 | W27: 0 | X27: 0 | Y27: 0 | Z27: =V27-Y27 -> 0
A28: P438044 | B28: ZETA | C28: 801 | D28: 健康科技 | E28: 438 | F28: Philips Domestic Appliances & | G28: 44442 | H28: 44873 | I28: 110000 | J28: 0 | K28: 0 | L28: 0 | M28: 0 | N28: 0 | O28: 0 | P28: 0 | Q28: 0 | R28: 0 | S28: 0 | T28: 0 | U28: 0 | V28: 0 | W28: 0 | X28: 0 | Y28: 0 | Z28: =V28-Y28 -> 0
A29: P438052 | B29: PTB | C29: 801 | D29: 健康科技 | E29: 438 | F29: Philips Domestic Appliances & | G29: 45301 | I29: 78309 | J29: 8629.99 | K29: 0 | L29: 18619.2 | M29: 0 | N29: 0 | O29: 27249.19 | P29: 5366.81 | Q29: 0 | R29: 0 | S29: 2529.81 | T29: 10765.35 | U29: 18661.97 | V29: 8587.22 | W29: 0 | X29: 1013.03 | Y29: 1013.03 | Z29: =V29-Y29 -> 7574.19
A30: P438042 | B30: S9000 | C30: 801 | D30: 健康科技 | E30: 438 | F30: Philips Domestic Appliances & | G30: 44298 | H30: 44405 | I30: 0 | J30: 0 | K30: 0 | L30: 2271.74 | M30: 0 | N30: 0 | O30: 2271.74 | P30: 0 | Q30: 0 | R30: 0 | S30: 0 | T30: 0 | U30: 0 | V30: 2271.74 | W30: 0 | X30: 1087.39 | Y30: 1087.39 | Z30: =V30-Y30 -> 1184.35
A31: P897001 | B31: ZINGO | C31: 801 | D31: 健康科技 | E31: C897 | F31: 普乐（广州）药业有限公司 | G31: 45072 | I31: 270000 | J31: 0 | K31: 0 | L31: 0 | M31: 0 | N31: 1275 | O31: 1275 | P31: 0 | Q31: 0 | R31: 0 | S31: 0 | T31: 0 | U31: 0 | V31: 1275 | W31: 0 | X31: 0 | Y31: 0 | Z31: =V31-Y31 -> 1275
A32: P438050 | B32: YANGZE | C32: 801 | D32: 健康科技 | E32: 438 | F32: Philips Domestic Appliances & | G32: 45254 | I32: 0 | J32: 0 | K32: 0 | L32: 0 | M32: 0 | N32: 0 | O32: 0 | P32: 0 | Q32: 0 | R32: 0 | S32: 0 | T32: 4133.28 | U32: 4133.28 | V32: -4133.28 | W32: 0 | X32: 0 | Y32: 0 | Z32: =V32-Y32 -> -4133.28
A33: P201010 | B33: 反应杯-16腔六联杯 | C33: 801 | D33: 健康科技 | E33: C201 | F33: 深圳市新产业生物医学工程股份有限公司 | G33: 44616 | H33: 44848 | I33: 1749000 | J33: 0 | K33: 0 | L33: 0 | M33: 0 | N33: 0 | O33: 0 | P33: 0 | Q33: 0 | R33: 0 | S33: 0 | T33: 0 | U33: 0 | V33: 0 | W33: 0 | X33: 0 | Y33: 0 | Z33: =V33-Y33 -> 0
A34: 合计 | I34: =SUM(I4:I33) -> 59346740 | J34: =SUM(J4:J33) -> 90634.99 | K34: =SUM(K4:K33) -> 0 | L34: =SUM(L4:L33) -> 456802.04 | M34: =SUM(M4:M33) -> 0 | N34: =SUM(N4:N33) -> 62115 | O34: =SUM(O4:O33) -> 609552.03 | P34: =SUM(P4:P33) -> 70724.42 | ... Y34: =SUM(Y4:Y33) -> 32984.27 | Z34: =V34-Y34 -> 218273.94

Sheet HZ1 
A1: HZ 2024年1-6月NPI报表明细
A2: 币别:HKD
A3: TK项目号 | B3: 项目名称 | C3: 利润中心 | D3: 事业部 | E3: 终端客户 | F3: 终端客户名称 | G3: 创建日期 | H3: 量产日期 | I3: NPI预算收入 | J3: 注塑模具收入 | K3: 其他模具收入 | L3: 样板费收入 | M3: 夹治具收入 | N3: 其它杂项收入 | O3: 量产前收入 | P3: 注塑模具成本 | Q3: 其他模具成本 | R3: 自费模具摊销 | S3: 量产前夹治具成本 | T3: 试模成本 | U3: 量产前成本 | V3: 量产前收益 | W3: 量产后夹治具成本 | X3: 量产后打样成本 | Y3: 量产后成本 | Z3: 项目收益
A4: P024087 | B4: Skyline Base&Entry | C4: TKHZ02 | D4: HZ1 | E4: C024 | F4: POLYCOM,INC. | G4: 44226 | H4: 43259 | I4: 4700000 | J4: 0 | K4: 0 | L4: 0 | M4: 0 | N4: 0 | O4: 0 | P4: 9651.12 | Q4: 0 | R4: 0 | S4: 0 | T4: 0 | U4: 9651.12 | V4: -9651.12 | W4: 0 | X4: 6094.93 | Y4: 6094.93 | Z4: =V4-Y4 -> -15746.05
A5: P024095 | B5: MX681 | C5: TKHZ02 | D5: HZ1 | E5: C024 | F5: POLYCOM,INC. | G5: 44226 | H5: 43922 | I5: 1156250 | J5: 0 | K5: 0 | L5: 0 | M5: 0 | N5: 0 | O5: 0 | P5: 27151.34 | Q5: 0 | R5: 5402.56 | S5: 0 | T5: 0 | U5: 32553.9 | V5: -32553.9 | W5: 0 | X5: 0 | Y5: 0 | Z5: =V5-Y5 -> -32553.9
A6: P024096 | B6: HDT611 | C6: TKHZ02 | D6: HZ1 | E6: C024 | F6: POLYCOM,INC. | G6: 44226 | H6: 44375 | I6: 0 | J6: 0 | K6: 0 | L6: 374400 | M6: 0 | N6: 0 | O6: 374400 | P6: 189194.26 | Q6: 0 | R6: 2984.41 | S6: 0 | T6: 0 | U6: 192178.67 | V6: 182221.33 | W6: 0 | X6: 62932.71 | Y6: 62932.71 | Z6: =V6-Y6 -> 119288.62
A7: P028008 | B7: BOSE SERENA | C7: TKHZ02 | D7: HZ1 | E7: 28 | F7: Bose Corporation | G7: 44817 | I7: 7833000 | J7: 0 | K7: 0 | L7: 0 | M7: 0 | N7: 0 | O7: 0 | P7: 0 | Q7: 0 | R7: 0 | S7: 0 | T7: 65927.03 | U7: 65927.03 | V7: -65927.03 | W7: 4974.48 | X7: 112313.56 | Y7: 117288.04 | Z7: =V7-Y7 -> -183215.07
A8: P028009 | B8: SCOTTY | C8: TKHZ02 | D8: HZ1 | E8: 28 | F8: Bose Corporation | G8: 44859 | I8: 3972000 | J8: 0 | K8: 0 | L8: 0 | M8: 0 | N8: 0 | O8: 0 | P8: 0 | Q8: 0 | R8: 0 | S8: 12611.78 | T8: 0 | U8: 12611.78 | V8: -12611.78 | W8: 9763.48 | X8: 3147.41 | Y8: 12910.89 | Z8: =V8-Y8 -> -25522.67
A9: P207004 | B9: JF-139 | C9: TKHZ02 | D9: HZ1 | E9: 207 | F9: 广州骏丰医疗器械有限公司 | G9: 44226 | H9: 42198 | I9: 0 | J9: 0 | K9: 0 | L9: 283.56 | M9: 0 | N9: 0 | O9: 283.56 | P9: 2144.17 | Q9: 0 | R9: 0 | S9: 0 | T9: 0 | U9: 2144.17 | V9: -1860.61 | W9: 0 | X9: 8688.55 | Y9: 8688.55 | Z9: =V9-Y9 -> -10549.16
A10: P207007 | B10: JFC-602A | C10: TKHZ02 | D10: HZ1 | E10: 207 | F10: 广州骏丰医疗器械有限公司 | G10: 44226 | H10: 41820 | I10: 0 | J10: 0 | K10: 0 | L10: 227.19 | M10: 0 | N10: 0 | O10: 227.19 | P10: 1162.47 | Q10: 0 | R10: 0 | S10: 2696.28 | T10: 0 | U10: 3858.75 | V10: -3631.56 | W10: 40808.76 | X10: 1364.02 | Y10: 42172.78 | Z10: =V10-Y10 -> -45804.34
A11: P208004 | B11: TT0 | C11: TKHZ02 | D11: HZ1 | E11: C208 | F11: 深圳市韶音科技有限公司 | G11: 44306 | H11: 44403 | I11: 0 | J11: 0 | K11: 0 | L11: 0 | M11: 0 | N11: 0 | O11: 0 | P11: 0 | Q11: 0 | R11: 0 | S11: 0 | T11: 0 | U11: 0 | V11: 0 | W11: 0 | X11: 0 | Y11: 0 | Z11: =V11-Y11 -> 0
A12: P208009 | B12: HSD | C12: TKHZ02 | D12: HZ1 | E12: C208 | F12: 深圳市韶音科技有限公司 | G12: 44799 | I12: 958000 | J12: 0 | K12: 0 | L12: 0 | M12: 0 | N12: 0 | O12: 0 | P12: 0 | Q12: 0 | R12: 0 | S12: 0 | T12: 0 | U12: 0 | V12: 0 | W12: 0 | X12: 16592.96 | Y12: 16592.96 | Z12: =V12-Y12 -> -16592.96
A13: P208010 | B13: CWS | C13: TKHZ02 | D13: HZ1 | E13: C208 | F13: 深圳市韶音科技有限公司 | G13: 44883 | H13: 45064 | I13: 3077800 | J13: 0 | K13: 0 | L13: 0 | M13: 10527.79 | N13: 0 | O13: 10527.79 | P13: 0 | Q13: 0 | R13: 4801.97 | S13: 418.43 | T13: 0 | U13: 5220.4 | V13: 5307.39 | W13: 13751.58 | X13: 115784.01 | Y13: 129535.59 | Z13: =V13-Y13 -> -124228.2
A14: P404001 | B14: TBD | C14: TKHZ02 | D14: HZ1 | E14: 404 | F14: Google Inc | G14: 44226 | H14: 42198 | I14: 462000 | J14: 0 | K14: 0 | L14: 0 | M14: 0 | N14: 0 | O14: 0 | P14: 60554.25 | Q14: 0 | R14: 0 | S14: 0 | T14: 0 | U14: 60554.25 | V14: -60554.25 | W14: 0 | X14: 1428.43 | Y14: 1428.43 | Z14: =V14-Y14 -> -61982.68
A15: P438037 | B15: XIAN | C15: TKHZ02 | D15: HZ1 | E15: 438 | F15: Philips Domestic Appliances & | G15: 44226 | H15: 44005 | I15: 0 | J15: 0 | K15: 0 | L15: 0 | M15: 0 | N15: 0 | O15: 0 | P15: 8010.38 | Q15: 0 | R15: 2641.13 | S15: 0 | T15: 0 | U15: 10651.51 | V15: -10651.51 | W15: 0 | X15: 10650.4 | Y15: 10650.4 | Z15: =V15-Y15 -> -21301.91
A16: P438044 | B16: ZETA | C16: TKHZ02 | D16: HZ1 | E16: 438 | F16: Philips Domestic Appliances & | G16: 44442 | H16: 44873 | I16: 770000 | J16: 0 | K16: 0 | L16: 41007.48 | M16: 172.38 | N16: 0 | O16: 41179.86 | P16: 5698.39 | Q16: 0 | R16: 6663.15 | S16: 0 | T16: 34528.65 | U16: 46890.19 | V16: -5710.33 | W16: 0 | X16: 53736.09 | Y16: 53736.09 | Z16: =V16-Y16 -> -59446.42
A17: P438048 | B17: GAEA 1 | C17: TKHZ02 | D17: HZ1 | E17: 438 | F17: Philips Domestic Appliances & | G17: 44677 | H17: 44873 | I17: 0 | J17: 0 | K17: 0 | L17: 0 | M17: 0 | N17: 0 | O17: 0 | P17: 0 | Q17: 0 | R17: 0 | S17: 0 | T17: 0 | U17: 0 | V17: 0 | W17: 0 | X17: 0 | Y17: 0 | Z17: =V17-Y17 -> 0
A18: P805005 | B18: AIO扁烟 | C18: TKHZ02 | D18: HZ1 | E18: C805 | F18: 深圳市合元科技有限公司 | G18: 44226 | H18: 44076 | I18: 0 | J18: 0 | K18: 0 | L18: 0 | M18: 0 | N18: 0 | O18: 0 | P18: 0 | Q18: 0 | R18: 0 | S18: 0 | T18: 0 | U18: 0 | V18: 0 | W18: 0 | X18: 0 | Y18: 0 | Z18: =V18-Y18 -> 0
A19: P805026 | B19: PLUZE 1.5 | C19: TKHZ02 | D19: HZ1 | E19: C805 | F19: 深圳市合元科技有限公司 | G19: 44670 | H19: 45009 | I19: 31275160 | J19: 0 | K19: 0 | L19: 76914.16 | M19: 0 | N19: 0 | O19: 76914.16 | P19: 25916.44 | Q19: 0 | R19: 4167.69 | S19: 3053.06 | T19: 259.47 | U19: 33396.66 | V19: 43517.5 | W19: 0 | X19: 870.09 | Y19: 870.09 | Z19: =V19-Y19 -> 42647.41
A20: P805029 | B20: NVS | C20: TKHZ02 | D20: HZ1 | E20: C805 | F20: 深圳市合元科技有限公司 | G20: 44848 | I20: 0 | J20: 0 | K20: 0 | L20: 0 | M20: 0 | N20: 0 | O20: 0 | P20: 0 | Q20: 0 | R20: 0 | S20: 0 | T20: 0 | U20: 0 | V20: 0 | W20: 0 | X20: 0 | Y20: 0 | Z20: =V20-Y20 -> 0
A21: P807001 | B21: HSL-4 | C21: TKHZ02 | D21: HZ1 | E21: C807 | F21: 喜利得（中国）有限公司 | G21: 44226 | H21: 43950 | I21: 0 | J21: 0 | K21: 0 | L21: 0 | M21: 0 | N21: 0 | O21: 0 | P21: 53159.13 | Q21: 0 | R21: 0 | S21: 0 | T21: 0 | U21: 53159.13 | V21: -53159.13 | W21: 0 | X21: 0 | Y21: 0 | Z21: =V21-Y21 -> -53159.13
A22: P815001 | B22: ROVER | C22: TKHZ02 | D22: HZ1 | E22: C815 | F22: 问问智能信息科技有限公司 | G22: 44226 | H22: 44103 | I22: 0 | J22: 0 | K22: 0 | L22: 0 | M22: 0 | N22: 0 | O22: 0 | P22: 916.46 | Q22: 0 | R22: 0 | S22: 0 | T22: 0 | U22: 916.46 | V22: -916.46 | W22: 0 | X22: 672.93 | Y22: 672.93 | Z22: =V22-Y22 -> -1589.39
A23: P815005 | B23: URANUS | C23: TKHZ02 | D23: HZ1 | E23: C815 | F23: 问问智能信息科技有限公司 | G23: 44629 | I23: 5427000 | J23: 0 | K23: 0 | L23: 0 | M23: 0 | N23: 0 | O23: 0 | P23: 2815.22 | Q23: 0 | R23: 8093.37 | S23: 0 | T23: 0 | U23: 10908.59 | V23: -10908.59 | W23: 2291.14 | X23: 141.25 | Y23: 2432.39 | Z23: =V23-Y23 -> -13340.98
A24: P824005 | B24: MODERN DISPOSABLE TX500 | C24: TKHZ02 | D24: HZ1 | E24: C824 | F24: NICOVENTURES TRADING LIMITED | G24: 44588 | H24: 44791 | I24: 32574420 | J24: 47905.55 | K24: 0 | L24: 0 | M24: 0 | N24: 0 | O24: 47905.55 | P24: 2230151 | Q24: 0 | R24: 117430.36 | S24: 0 | T24: 0 | U24: 2347581.3 | V24: -2299675.8 | W24: 0 | X24: 0 | Y24: 0 | Z24: =V24-Y24 -> -2299675.8
A25: P824006 | B25: MD2.0 | C25: TKHZ02 | D25: HZ1 | E25: C824 | F25: NICOVENTURES TRADING LIMITED | G25: 44729 | I25: 4796000 | J25: 0 | K25: 0 | L25: 0 | M25: 0 | N25: 0 | O25: 0 | P25: 0 | Q25: 0 | R25: 21775.83 | S25: 0 | T25: 0 | U25: 21775.83 | V25: -21775.83 | W25: 0 | X25: 0 | Y25: 0 | Z25: =V25-Y25 -> -21775.83
A26: P828001 | B26: RPP | C26: TKHZ02 | D26: HZ1 | E26: C828 | F26: Braloba (HK) Ltd | G26: 44226 | H26: 44316 | I26: 0 | J26: 0 | K26: 0 | L26: 0 | M26: 0 | N26: 0 | O26: 0 | P26: 0 | Q26: 0 | R26: 0 | S26: 0 | T26: 0 | U26: 0 | V26: 0 | W26: 0 | X26: 0 | Y26: 0 | Z26: =V26-Y26 -> 0
A27: P831003 | B27: NEST 1.5 | C27: TKHZ02 | D27: HZ1 | E27: C831 | F27: August Home, Inc. | G27: 44411 | I27: 8056400 | J27: 0 | K27: 0 | L27: 0 | M27: 0 | N27: 0 | O27: 0 | P27: 0 | Q27: 0 | R27: 13584.78 | S27: 0 | T27: 0 | U27: 13584.78 | V27: -13584.78 | W27: 0 | X27: 0 | Y27: 0 | Z27: =V27-Y27 -> -13584.78
A28: P831004 | B28: IO LOCK | C28: TKHZ02 | D28: HZ1 | E28: C831 | F28: August Home, Inc. | G28: 44503 | I28: 2249280 | J28: 730384.2 | K28: 0 | L28: 2962.88 | M28: 0 | N28: 0 | O28: 733347.08 | P28: 747658.93 | Q28: 0 | R28: 0 | S28: 0 | T28: 5596.77 | U28: 753255.7 | V28: -19908.62 | W28: 0 | X28: 47.65 | Y28: 47.65 | Z28: =V28-Y28 -> -19956.27
A29: P831005 | B29: 400 SERIES | C29: TKHZ02 | D29: HZ1 | E29: C831 | F29: August Home, Inc. | G29: 44607 | I29: 4711014 | J29: 0 | K29: 0 | L29: 0 | M29: 0 | N29: 0 | O29: 0 | P29: 190.93 | Q29: 0 | R29: 6982.16 | S29: 2516.4 | T29: 1950.13 | U29: 11639.62 | V29: -11639.62 | W29: 12036.72 | X29: 62837.67 | Y29: 74874.39 | Z29: =V29-Y29 -> -86514.01
A30: P831006 | B30: TITAN | C30: TKHZ02 | D30: HZ1 | E30: C831 | F30: August Home, Inc. | G30: 44770 | I30: 3018400 | J30: 0 | K30: 0 | L30: 0 | M30: 0 | N30: 0 | O30: 0 | P30: 0 | Q30: 0 | R30: 0 | S30: 0 | T30: 0 | U30: 0 | V30: 0 | W30: 0 | X30: 7426.87 | Y30: 7426.87 | Z30: =V30-Y30 -> -7426.87
A31: P856001 | B31: NT02 | C31: TKHZ02 | D31: HZ1 | E31: C856 | F31: 微软(中国)有限公司 | G31: 44767 | I31: 9158310 | J31: 0 | K31: 0 | L31: 0 | M31: 0 | N31: 0 | O31: 0 | P31: 0 | Q31: 0 | R31: 0 | S31: 1238.24 | T31: 20385.68 | U31: 21623.92 | V31: -21623.92 | W31: 0 | X31: 0 | Y31: 0 | Z31: =V31-Y31 -> -21623.92
A32: P857001 | B32: AUDIGO INTRO | C32: TKHZ02 | D32: HZ1 | E32: C857 | F32: Audigo Labs Inc | G32: 44461 | H32: 44944 | I32: 1900000 | J32: 0 | K32: 0 | L32: 0 | M32: 0 | N32: 0 | O32: 0 | P32: 0 | Q32: 0 | R32: 0 | S32: 0 | T32: 0 | U32: 0 | V32: 0 | W32: 0 | X32: 12178.5 | Y32: 12178.5 | Z32: =V32-Y32 -> -12178.5
A33: P860003 | B33: AURA4 | C33: TKHZ02 | D33: HZ1 | E33: C860 | F33: 通力科技股份有限公司 | G33: 44767 | H33: 45028 | I33: 14100000 | J33: 64724.91 | K33: 0 | L33: 0 | M33: 0 | N33: 0 | O33: 64724.91 | P33: 46957.58 | Q33: 0 | R33: 33602.72 | S33: 0 | T33: 132559.25 | U33: 213119.55 | V33: -148394.64 | W33: 19088.31 | X33: 20124.92 | Y33: 39213.23 | Z33: =V33-Y33 -> -187607.87
A34: P865001 | B34: DTM2 | C34: TKHZ02 | D34: HZ1 | E34: C865 | F34: Ubicquia Inc | G34: 44678 | I34: 0 | J34: 0 | K34: 0 | L34: 0 | M34: 0 | N34: 0 | O34: 0 | P34: 0 | Q34: 0 | R34: 0 | S34: 0 | T34: 0 | U34: 0 | V34: 0 | W34: 0 | X34: 0 | Y34: 0 | Z34: =V34-Y34 -> 0
A35: P870001 | B35: N6 | C35: TKHZ02 | D35: HZ1 | E35: C870 | F35: 北京行者无疆科技有限公司 | G35: 44799 | I35: 8004000 | J35: 0 | K35: 0 | L35: 0 | M35: 0 | N35: 0 | O35: 0 | P35: 9461.28 | Q35: 0 | R35: 7104.44 | S35: 779.69 | T35: 3328.1 | U35: 20673.51 | V35: -20673.51 | W35: 3177.75 | X35: 18513.34 | Y35: 21691.09 | Z35: =V35-Y35 -> -42364.6
A36: P870002 | B36: N8 | C36: TKHZ02 | D36: HZ1 | E36: C870 | F36: 北京行者无疆科技有限公司 | G36: 44895 | I36: 3045000 | J36: 0 | K36: 0 | L36: 0 | M36: 0 | N36: 0 | O36: 0 | P36: 0 | Q36: 0 | R36: 0 | S36: 0 | T36: 0 | U36: 0 | V36: 0 | W36: 0 | X36: 2198.54 | Y36: 2198.54 | Z36: =V36-Y36 -> -2198.54
A37: P875001 | B37: ABAC1918 | C37: TKHZ02 | D37: HZ1 | E37: C875 | F37: 深圳市卓力能技术有限公司 | G37: 44826 | I37: 6006000 | J37: 15326.09 | K37: 0 | L37: 0 | M37: 0 | N37: 0 | O37: 15326.09 | P37: 11005.31 | Q37: 0 | R37: 3468.08 | S37: 24365.52 | T37: 0 | U37: 38838.91 | V37: -23512.82 | W37: 0 | X37: 0 | Y37: 0 | Z37: =V37-Y37 -> -23512.82
A38: P876001 | B38: BHP701 | C38: TKHZ02 | D38: HZ1 | E38: C876 | F38: Sonos, Inc. | G38: 44830 | I38: 130488000 | J38: 10260460 | K38: 0 | L38: 400127.16 | M38: 362453.03 | N38: 0 | O38: 11023040 | P38: 11307722 | Q38: 0 | R38: 97195.74 | S38: 564869.81 | T38: 285911.44 | U38: 12255699 | V38: -1232658.8 | W38: 636172.49 | X38: 487622.28 | Y38: 1123794.8 | Z38: =V38-Y38 -> -2356453.5
A39: P879001 | B39: EP | C39: TKHZ02 | D39: HZ1 | E39: C879 | F39: teenage engineering | G39: 44860 | I39: 8344501 | J39: 0 | K39: 0 | L39: 20229.3 | M39: 0 | N39: 0 | O39: 20229.3 | P39: 9267.57 | Q39: 0 | R39: 0 | S39: 1891.15 | T39: 23536.92 | U39: 34695.64 | V39: -14466.34 | W39: 3629.93 | X39: 2111.29 | Y39: 5741.22 | Z39: =V39-Y39 -> -20207.56
A40: P800001 | B40: WAM03 | C40: TKHZ02 | D40: HZ1 | E40: 800 | F40: Withings SA | G40: 44226 | H40: 43767 | I40: 0 | J40: 0 | K40: 0 | L40: 83176.5 | M40: 0 | N40: 0 | O40: 83176.5 | P40: 837.86 | Q40: 0 | R40: 0 | S40: 0 | T40: 0 | U40: 837.86 | V40: 82338.64 | W40: 0 | X40: 26511.2 | Y40: 26511.2 | Z40: =V40-Y40 -> 55827.44
A41: P024089 | B41: Richards and Miko | C41: TKHZ02 | D41: HZ1 | E41: C024 | F41: POLYCOM,INC. | G41: 44226 | H41: 42811 | I41: 0 | J41: 0 | K41: 0 | L41: 0 | M41: 0 | N41: 0 | O41: 0 | P41: 0 | Q41: 0 | R41: 0 | S41: 0 | T41: 0 | U41: 0 | V41: 0 | W41: 0 | X41: 0 | Y41: 0 | Z41: =V41-Y41 -> 0
A42: P815002 | B42: E3 | C42: TKHZ02 | D42: HZ1 | E42: C815 | F42: 问问智能信息科技有限公司 | G42: 44226 | H42: 44459 | I42: 0 | J42: 0 | K42: 0 | L42: 0 | M42: 0 | N42: 0 | O42: 0 | P42: 1985.66 | Q42: 0 | R42: 0 | S42: 0 | T42: 0 | U42: 1985.66 | V42: -1985.66 | W42: 0 | X42: 779.45 | Y42: 779.45 | Z42: =V42-Y42 -> -2765.11
A43: P815004 | B43: FALCON | C43: TKHZ02 | D43: HZ1 | E43: C815 | F43: 问问智能信息科技有限公司 | G43: 44466 | H43: 44708 | I43: 226000 | J43: 0 | K43: 0 | L43: 0 | M43: 0 | N43: 0 | O43: 0 | P43: 286.4 | Q43: 0 | R43: 0 | S43: 0 | T43: 0 | U43: 286.4 | V43: -286.4 | W43: 0 | X43: 0 | Y43: 0 | Z43: =V43-Y43 -> -286.4
A44: P860005 | B44: PELICAN | C44: TKHZ02 | D44: HZ1 | E44: C860 | F44: 通力科技股份有限公司 | G44: 44818 | I44: 870100 | J44: 0 | K44: 0 | L44: 0 | M44: 0 | N44: 0 | O44: 0 | P44: 0 | Q44: 0 | R44: 0 | S44: 0 | T44: 0 | U44: 0 | V44: 0 | W44: 0 | X44: 0 | Y44: 0 | Z44: =V44-Y44 -> 0
A45: P880001 | B45: SILKN VII | C45: TKHZ02 | D45: HZ1 | E45: C880 | F45: 深圳市恒天伟焱科技股份有限公司 | G45: 44903 | I45: 1610000 | J45: 0 | K45: 0 | L45: 0 | M45: 0 | N45: 0 | O45: 0 | P45: 0 | Q45: 0 | R45: 0 | S45: 0 | T45: 0 | U45: 0 | V45: 0 | W45: 0 | X45: 0 | Y45: 0 | Z45: =V45-Y45 -> 0
A46: P818002 | B46: HDT666 | C46: TKHZ02 | D46: HZ1 | E46: C818 | F46: 美律电子（深圳）有限公司 | G46: 44757 | I46: 3571600 | J46: 0 | K46: 0 | L46: 0 | M46: 0 | N46: 0 | O46: 0 | P46: 0 | Q46: 0 | R46: 0 | S46: 0 | T46: 0 | U46: 0 | V46: 0 | W46: 0 | X46: 26379.27 | Y46: 26379.27 | Z46: =V46-Y46 -> -26379.27
A47: P438047 | B47: IOTA | C47: TKHZ02 | D47: HZ1 | E47: 438 | F47: Philips Domestic Appliances & | G47: 44615 | H47: 45001 | I47: 40000 | J47: 36660 | K47: 0 | L47: -394.09 | M47: 0 | N47: 0 | O47: 36265.91 | P47: 30275.72 | Q47: 0 | R47: 0 | S47: 0 | T47: 0 | U47: 30275.72 | V47: 5990.19 | W47: 0 | X47: 209.63 | Y47: 209.63 | Z47: =V47-Y47 -> 5780.56
A48: P438019 | B48: Calgary | C48: TKHZ02 | D48: HZ1 | E48: 438 | F48: Philips Domestic Appliances & | G48: 44226 | H48: 42909 | I48: 0 | J48: 0 | K48: 0 | L48: 0 | M48: 0 | N48: 0 | O48: 0 | P48: 0 | Q48: 0 | R48: 0 | S48: 0 | T48: 0 | U48: 0 | V48: 0 | W48: 0 | X48: 0 | Y48: 0 | Z48: =V48-Y48 -> 0
A49: P438023 | B49: Shanghai | C49: TKHZ02 | D49: HZ1 | E49: 438 | F49: Philips Domestic Appliances & | G49: 44226 | H49: 42909 | I49: 1240400 | J49: 0 | K49: 0 | L49: 0 | M49: 0 | N49: 0 | O49: 0 | P49: 0 | Q49: 0 | R49: 0 | S49: 0 | T49: 0 | U49: 0 | V49: 0 | W49: 86338.09 | X49: 291.26 | Y49: 86629.35 | Z49: =V49-Y49 -> -86629.35
A50: P438012 | B50: Tokyo | C50: TKHZ02 | D50: HZ1 | E50: 438 | F50: Philips Domestic Appliances & | G50: 44226 | H50: 42391 | I50: 0 | J50: 0 | K50: 0 | L50: 0 | M50: 0 | N50: 0 | O50: 0 | P50: 0 | Q50: 0 | R50: 0 | S50: 0 | T50: 0 | U50: 0 | V50: 0 | W50: 0 | X50: 0 | Y50: 0 | Z50: =V50-Y50 -> 0
A51: P438046 | B51: MASERATI | C51: TKHZ02 | D51: HZ1 | E51: 438 | F51: Philips Domestic Appliances & | G51: 44531 | I51: 271600 | J51: 0 | K51: 0 | L51: 0 | M51: 0 | N51: 0 | O51: 0 | P51: 0 | Q51: 0 | R51: 0 | S51: 0 | T51: 0 | U51: 0 | V51: 0 | W51: 0 | X51: 0 | Y51: 0 | Z51: =V51-Y51 -> 0
A52: P805018 | B52: N1002-A3油杯 | C52: TKHZ02 | D52: HZ1 | E52: C805 | F52: 深圳市合元科技有限公司 | G52: 44229 | H52: 44251 | I52: 291500 | J52: 0 | K52: 0 | L52: 0 | M52: 0 | N52: 0 | O52: 0 | P52: 27925.7 | Q52: 0 | R52: 0 | S52: 1461.93 | T52: 0 | U52: 29387.63 | V52: -29387.63 | W52: 0 | X52: 0 | Y52: 0 | Z52: =V52-Y52 -> -29387.63
A53: P024083 | B53: Oculus | C53: TKHZ02 | D53: HZ1 | E53: C024 | F53: POLYCOM,INC. | G53: 44226 | H53: 42551 | I53: 0 | J53: 0 | K53: 0 | L53: 0 | M53: 0 | N53: 0 | O53: 0 | P53: 0 | Q53: 0 | R53: 0 | S53: 0 | T53: 0 | U53: 0 | V53: 0 | W53: 0 | X53: 195.17 | Y53: 195.17 | Z53: =V53-Y53 -> -195.17
A54: P438045 | B54: OSAKA | C54: TKHZ02 | D54: HZ1 | E54: 438 | F54: Philips Domestic Appliances & | G54: 44516 | H54: 44937 | I54: 3671300 | J54: 0 | K54: 0 | L54: 0 | M54: 0 | N54: 0 | O54: 0 | P54: 0 | Q54: 0 | R54: 0 | S54: 0 | T54: 0 | U54: 0 | V54: 0 | W54: 0 | X54: 0 | Y54: 0 | Z54: =V54-Y54 -> 0
A55: P437033 | B55: P11 | C55: TKHZ02 | D55: HZ1 | E55: 437 | F55: Fitbit Inc. | G55: 44628 | I55: 1218353.6 | J55: 0 | K55: 0 | L55: 0 | M55: 0 | N55: 0 | O55: 0 | P55: 0 | Q55: 0 | R55: 0 | S55: 0 | T55: 0 | U55: 0 | V55: 0 | W55: 0 | X55: 0 | Y55: 0 | Z55: =V55-Y55 -> 0
A56: P208003 | B56: VIE | C56: TKHZ02 | D56: HZ1 | E56: C208 | F56: 深圳市韶音科技有限公司 | G56: 44226 | H56: 44223 | I56: 1484000 | J56: 0 | K56: 0 | L56: 0 | M56: 0 | N56: 0 | O56: 0 | P56: 0 | Q56: 0 | R56: 0 | S56: 0 | T56: 0 | U56: 0 | V56: 0 | W56: 0 | X56: 53464.27 | Y56: 53464.27 | Z56: =V56-Y56 -> -53464.27
A57: P894001 | B57: HAMMERHEAD | C57: TKHZ02 | D57: HZ1 | E57: C894 | F57: 陆逊梯卡华宏（东莞）眼镜有限公司 | G57: 45057 | I57: 24860 | J57: 0 | K57: 0 | L57: 0 | M57: 0 | N57: 0 | O57: 0 | P57: 0 | Q57: 0 | R57: 0 | S57: 0 | T57: 0 | U57: 0 | V57: 0 | W57: 0 | X57: 0 | Y57: 0 | Z57: =V57-Y57 -> 0
A58: P894003 | B58: SM | C58: TKHZ02 | D58: HZ1 | E58: C894 | F58: 陆逊梯卡华宏（东莞）眼镜有限公司 | G58: 45105 | I58: 79200 | J58: 0 | K58: 0 | L58: 0 | M58: 0 | N58: 0 | O58: 0 | P58: 21518.72 | Q58: 0 | R58: 0 | S58: 0 | T58: 1880.56 | U58: 23399.28 | V58: -23399.28 | W58: 0 | X58: 0 | Y58: 0 | Z58: =V58-Y58 -> -23399.28
A59: P024106 | B59: REVLON | C59: TKHZ02 | D59: HZ1 | E59: C024 | F59: POLYCOM,INC. | G59: 44245 | H59: 44271 | I59: 13075015 | J59: 0 | K59: 0 | L59: 0 | M59: 0 | N59: 0 | O59: 0 | P59: 0 | Q59: 0 | R59: 0 | S59: 0 | T59: 0 | U59: 0 | V59: 0 | W59: 0 | X59: 0 | Y59: 0 | Z59: =V59-Y59 -> 0
A60: P330044 | B60: ELFIN | C60: TKHZ02 | D60: HZ1 | E60: 330 | F60: GN Audio A/S(GSC) | G60: 44973 | I60: 44000 | J60: 0 | K60: 0 | L60: 0 | M60: 0 | N60: 0 | O60: 0 | P60: 0 | Q60: 0 | R60: 0 | S60: 0 | T60: 0 | U60: 0 | V60: 0 | W60: 0 | X60: 0 | Y60: 0 | Z60: =V60-Y60 -> 0
A61: P208002 | B61: SE | C61: TKHZ02 | D61: HZ1 | E61: C208 | F61: 深圳市韶音科技有限公司 | G61: 44226 | H61: 43888 | I61: 444114 | J61: 0 | K61: 0 | L61: 0 | M61: 0 | N61: 0 | O61: 0 | P61: 0 | Q61: 0 | R61: 0 | S61: 0 | T61: 0 | U61: 0 | V61: 0 | W61: 0 | X61: 0 | Y61: 0 | Z61: =V61-Y61 -> 0
A62: P435003 | B62: Dublin controller | C62: TKHZ02 | D62: HZ1 | E62: 330 | F62: GN Audio A/S(GSC) | G62: 44226 | H62: 42306 | I62: 0 | J62: 0 | K62: 0 | L62: 0 | M62: 0 | N62: 0 | O62: 0 | P62: 0 | Q62: 0 | R62: 0 | S62: 0 | T62: 0 | U62: 0 | V62: 0 | W62: 0 | X62: 0 | Y62: 0 | Z62: =V62-Y62 -> 0
A63: P297001 | B63: Wallace | C63: TKHZ02 | D63: HZ1 | E63: 297 | F63: Currant, Inc. | G63: 0 | H63: 0 | I63: 0 | J63: 0 | K63: 0 | L63: 0 | M63: 0 | N63: 0 | O63: 0 | P63: 0 | Q63: 0 | R63: 0 | S63: 0 | T63: 0 | U63: 0 | V63: 0 | W63: 0 | X63: 0 | Y63: 0 | Z63: =V63-Y63 -> 0
A64: P330019 | B64: ERASMUS | C64: TKHZ02 | D64: HZ1 | E64: 330 | F64: GN Audio A/S(GSC) | G64: 44226 | H64: 42198 | I64: 913000 | J64: 0 | K64: 0 | L64: 0 | M64: 0 | N64: 0 | O64: 0 | P64: 0 | Q64: 0 | R64: 0 | S64: 0 | T64: 0 | U64: 0 | V64: 0 | W64: 0 | X64: 0 | Y64: 0 | Z64: =V64-Y64 -> 0
A65: P330046 | B65: BLIZZARD | C65: TKHZ02 | D65: HZ1 | E65: 330 | F65: GN Audio A/S(GSC) | G65: 45133 | I65: 1815592.9 | J65: 0 | K65: 0 | L65: 0 | M65: 0 | N65: 0 | O65: 0 | P65: 0 | Q65: 0 | R65: 0 | S65: 0 | T65: 13142.27 | U65: 13142.27 | V65: -13142.27 | W65: 0 | X65: 7294.81 | Y65: 7294.81 | Z65: =V65-Y65 -> -20437.08
A66: P895001 | B66: 8003射频仪 | C66: TKHZ02 | D66: HZ1 | E66: C895 | F66: 云南贝泰妮生物科技集团股份有限公司 | G66: 45068 | I66: 884000 | J66: 0 | K66: 0 | L66: 0 | M66: 0 | N66: 0 | O66: 0 | P66: 0 | Q66: 0 | R66: 0 | S66: 11108.68 | T66: 53015.84 | U66: 64124.52 | V66: -64124.52 | W66: 0 | X66: 0 | Y66: 0 | Z66: =V66-Y66 -> -64124.52
A67: P805039 | B67: LYRA BASIC | C67: TKHZ02 | D67: HZ1 | E67: C805 | F67: 深圳市合元科技有限公司 | G67: 45226 | I67: 267800 | J67: 0 | K67: 0 | L67: 1934.72 | M67: 0 | N67: 0 | O67: 1934.72 | P67: 0 | Q67: 0 | R67: 0 | S67: 0 | T67: 12883.14 | U67: 12883.14 | V67: -10948.42 | W67: 0 | X67: 0 | Y67: 0 | Z67: =V67-Y67 -> -10948.42
A68: P208013 | B68: BOS | C68: TKHZ02 | D68: HZ1 | E68: C208 | F68: 深圳市韶音科技有限公司 | G68: 45212 | I68: 1554800 | J68: 0 | K68: 0 | L68: 0 | M68: 0 | N68: 0 | O68: 0 | P68: 0 | Q68: 0 | R68: 0 | S68: 21717.11 | T68: 713795.92 | U68: 735513.03 | V68: -735513.03 | W68: 0 | X68: 0 | Y68: 0 | Z68: =V68-Y68 -> -735513.03
A69: P208014 | B69: SEAL | C69: TKHZ02 | D69: HZ1 | E69: C208 | F69: 深圳市韶音科技有限公司 | G69: 45212 | I69: 188500 | J69: 0 | K69: 0 | L69: 0 | M69: 0 | N69: 0 | O69: 0 | P69: 0 | Q69: 0 | R69: 0 | S69: 1059.25 | T69: 38245.3 | U69: 39304.55 | V69: -39304.55 | W69: 0 | X69: 5388.42 | Y69: 5388.42 | Z69: =V69-Y69 -> -44692.97
A70: P831008 | B70: 400 FP | C70: TKHZ02 | D70: HZ1 | E70: C831 | F70: August Home, Inc. | G70: 45173 | I70: 756800 | J70: 0 | K70: 0 | L70: 16440.37 | M70: 15560 | N70: 0 | O70: 32000.37 | P70: 471.29 | Q70: 0 | R70: 0 | S70: 12149.73 | T70: 174051.15 | U70: 186672.17 | V70: -154671.8 | W70: 0 | X70: 0 | Y70: 0 | Z70: =V70-Y70 -> -154671.8
A71: P913001 | B71: WB-01 | C71: TKHZ02 | D71: HZ1 | E71: C913 | F71: 惠州市恩雅乐器有限公司 | G71: 45266 | I71: 0 | J71: 0 | K71: 0 | L71: 0 | M71: 0 | N71: 0 | O71: 0 | P71: 837.86 | Q71: 0 | R71: 0 | S71: 6659.12 | T71: 3154.16 | U71: 10651.14 | V71: -10651.14 | W71: 0 | X71: 2219.59 | Y71: 2219.59 | Z71: =V71-Y71 -> -12870.73
A72: P208012 | B72: CCT | C72: TKHZ02 | D72: HZ1 | E72: C208 | F72: 深圳市韶音科技有限公司 | G72: 45175 | I72: 1030000 | J72: 0 | K72: 0 | L72: 0 | M72: 0 | N72: 0 | O72: 0 | P72: 0 | Q72: 0 | R72: 0 | S72: 8933.3 | T72: 134135.09 | U72: 143068.39 | V72: -143068.39 | W72: 725.55 | X72: 14463.93 | Y72: 15189.48 | Z72: =V72-Y72 -> -158257.87
A73: P913002 | B73: NEXG SE | C73: TKHZ02 | D73: HZ1 | E73: C913 | F73: 惠州市恩雅乐器有限公司 | G73: 45267 | I73: 0 | J73: 0 | K73: 0 | L73: 0 | M73: 0 | N73: 0 | O73: 0 | P73: 0 | Q73: 0 | R73: 0 | S73: 1502.57 | T73: 8980.14 | U73: 10482.71 | V73: -10482.71 | W73: 0 | X73: 0 | Y73: 0 | Z73: =V73-Y73 -> -10482.71
A74: P861005 | B74: GD16 | C74: TKHZ02 | D74: HZ1 | E74: C861 | F74: 深圳雾芯科技有限公司 | G74: 45279 | I74: 209000 | J74: 0 | K74: 0 | L74: 0 | M74: 0 | N74: 0 | O74: 0 | P74: 22816.02 | Q74: 0 | R74: 0 | S74: 0 | T74: 29648.74 | U74: 52464.76 | V74: -52464.76 | W74: 0 | X74: 1565.89 | Y74: 1565.89 | Z74: =V74-Y74 -> -54030.65
A75: P913004 | B75: MG01 | C75: TKHZ02 | D75: HZ1 | E75: C913 | F75: 惠州市恩雅乐器有限公司 | G75: 45275 | I75: 1404480 | J75: 0 | K75: 0 | L75: 69384.42 | M75: 0 | N75: 0 | O75: 69384.42 | P75: 9822.24 | Q75: 0 | R75: 0 | S75: 803.81 | T75: 178305.35 | U75: 188931.4 | V75: -119546.98 | W75: 0 | X75: 8207.92 | Y75: 8207.92 | Z75: =V75-Y75 -> -127754.9
A76: P907002 | B76: 668 | C76: TKHZ02 | D76: HZ1 | E76: C907 | F76: 索尼电子 | G76: 45282 | I76: 1140000 | J76: 0 | K76: 0 | L76: 0 | M76: 0 | N76: 0 | O76: 0 | P76: 0 | Q76: 0 | R76: 0 | S76: 8501.39 | T76: 198763.99 | U76: 207265.38 | V76: -207265.38 | W76: 0 | X76: 0 | Y76: 0 | Z76: =V76-Y76 -> -207265.38
A77: P918001 | B77: GD16 | C77: TKHZ02 | D77: HZ1 | E77: C918 | F77: 深圳云普星河科技服务有限公司 | G77: 45365 | I77: 0 | J77: 0 | K77: 0 | L77: 2561.26 | M77: 0 | N77: 0 | O77: 2561.26 | P77: 0 | Q77: 0 | R77: 0 | S77: 0 | T77: 0 | U77: 0 | V77: 2561.26 | W77: 0 | X77: 0 | Y77: 0 | Z77: =V77-Y77 -> 2561.26
A78: P809006 | B78: JUNO | C78: TKHZ02 | D78: HZ1 | E78: C809 | F78: 歌尔股份有限公司 | G78: 44226 | H78: 44151 | I78: 429000 | J78: 0 | K78: 0 | L78: 0 | M78: 0 | N78: 0 | O78: 0 | P78: 0 | Q78: 0 | R78: 64290.35 | S78: 0 | T78: 0 | U78: 64290.35 | V78: -64290.35 | W78: 0 | X78: 0 | Y78: 0 | Z78: =V78-Y78 -> -64290.35
A79: P894004 | B79: SAN MARCO | C79: TKHZ02 | D79: HZ1 | E79: C894 | F79: 陆逊梯卡华宏（东莞）眼镜有限公司 | G79: 45321 | I79: 68200 | J79: 0 | K79: 0 | L79: 53916.97 | M79: 0 | N79: 0 | O79: 53916.97 | P79: 0 | Q79: 0 | R79: 0 | S79: 2016.14 | T79: 64773.07 | U79: 66789.21 | V79: -12872.24 | W79: 0 | X79: 0 | Y79: 0 | Z79: =V79-Y79 -> -12872.24
A80: P915001 | B80: FYAS11 | C80: TKHZ02 | D80: HZ1 | E80: C915 | F80: 東莞市富穎電子材料有限公司 | G80: 45282 | I80: 106700 | J80: 0 | K80: 0 | L80: 0 | M80: 0 | N80: 0 | O80: 0 | P80: 0 | Q80: 0 | R80: 0 | S80: 0 | T80: 7865.18 | U80: 7865.18 | V80: -7865.18 | W80: 0 | X80: 0 | Y80: 0 | Z80: =V80-Y80 -> -7865.18
A81: P330020 | B81: Leo | C81: TKHZ02 | D81: HZ1 | E81: 330 | F81: GN Audio A/S(GSC) | G81: 44226 | H81: 44371 | I81: 0 | J81: 0 | K81: 0 | L81: 0 | M81: 0 | N81: 0 | O81: 0 | P81: 0 | Q81: 0 | R81: 0 | S81: 0 | T81: 12463.34 | U81: 12463.34 | V81: -12463.34 | W81: 0 | X81: 0 | Y81: 0 | Z81: =V81-Y81 -> -12463.34
A82: P809009 | B82: AG10AG20 | C82: TKHZ02 | D82: HZ1 | E82: C809 | F82: 歌尔股份有限公司 | G82: 45273 | I82: 2428000 | J82: 0 | K82: 0 | L82: 0 | M82: 0 | N82: 0 | O82: 0 | P82: 0 | Q82: 0 | R82: 0 | S82: 2234.75 | T82: 20440.41 | U82: 22675.16 | V82: -22675.16 | W82: 0 | X82: 0 | Y82: 0 | Z82: =V82-Y82 -> -22675.16
A83: P831002 | B83: TITAN | C83: TKHZ02 | D83: HZ1 | E83: C831 | F83: August Home, Inc. | G83: 44277 | H83: 44306 | I83: 276860 | J83: 0 | K83: 0 | L83: 0 | M83: 0 | N83: 0 | O83: 0 | P83: 0 | Q83: 0 | R83: 0 | S83: 0 | T83: 0 | U83: 0 | V83: 0 | W83: 0 | X83: 6213.03 | Y83: 6213.03 | Z83: =V83-Y83 -> -6213.03
A84: P024080 | B84: Leaf | C84: TKHZ02 | D84: HZ1 | E84: C024 | F84: POLYCOM,INC. | G84: 44226 | H84: 42345 | I84: 0 | J84: 0 | K84: 0 | L84: 0 | M84: 0 | N84: 0 | O84: 0 | P84: 0 | Q84: 0 | R84: 0 | S84: 0 | T84: 0 | U84: 0 | V84: 0 | W84: 0 | X84: 2363.32 | Y84: 2363.32 | Z84: =V84-Y84 -> -2363.32
A85: P850002 | B85: GS-1399 /1401 硅胶耳挂 | C85: TKHZ02 | D85: 惠州一注塑 | E85: C850 | F85: 深圳市冠旭电子股份有限公司 | G85: 45351 | I85: 294800 | J85: 0 | K85: 0 | L85: 0 | M85: 0 | N85: 0 | O85: 0 | P85: 1678.36 | Q85: 0 | R85: 0 | S85: 0 | T85: 3696.86 | U85: 5375.22 | V85: -5375.22 | W85: 0 | X85: 15496.36 | Y85: 15496.36 | Z85: =V85-Y85 -> -20871.58
A86: P860001 | B86: HERCULES | C86: TKHZ02 | D86: 惠州一注塑 | E86: C860 | F86: 通力科技股份有限公司 | G86: 44546 | I86: 1147800 | J86: 0 | K86: 0 | L86: 0 | M86: 0 | N86: 0 | O86: 0 | P86: 0 | Q86: 0 | R86: 0 | S86: 0 | T86: 1113.59 | U86: 1113.59 | V86: -1113.59 | W86: 0 | X86: 0 | Y86: 0 | Z86: =V86-Y86 -> -1113.59
A87: P438024 | B87: Sydney | C87: TKHZ02 | D87: 惠州一注塑 | E87: 438 | F87: Philips Domestic Appliances & | G87: 44226 | H87: 43118 | I87: 0 | J87: 0 | K87: 0 | L87: 0 | M87: 0 | N87: 0 | O87: 0 | P87: 0 | Q87: 0 | R87: 0 | S87: 0 | T87: 0 | U87: 0 | V87: 0 | W87: 0 | X87: 25680.69 | Y87: 25680.69 | Z87: =V87-Y87 -> -25680.69
A88: P208016 | B88: UCS | C88: TKHZ02 | D88: 惠州一喷油 | E88: C208 | F88: 深圳市韶音科技有限公司 | G88: 45442 | I88: 1790000 | J88: 0 | K88: 0 | L88: 0 | M88: 0 | N88: 0 | O88: 0 | P88: 0 | Q88: 0 | R88: 0 | S88: 370 | T88: 0 | U88: 370 | V88: -370 | W88: 0 | X88: 0 | Y88: 0 | Z88: =V88-Y88 -> -370
A89: P876002 | B89: ROUNDHOUSE | C89: TKHZ02 | D89: 惠州一喷油 | E89: C876 | F89: Sonos, Inc. | G89: 45432 | I89: 2530000 | J89: 0 | K89: 0 | L89: 0 | M89: 0 | N89: 0 | O89: 0 | P89: 0 | Q89: 0 | R89: 0 | S89: 418.46 | T89: 0 | U89: 418.46 | V89: -418.46 | W89: 0 | X89: 0 | Y89: 0 | Z89: =V89-Y89 -> -418.46
A90: VIP返利 | C90: TKHZ02 | D90: HZ1 | I90: 0 | J90: 0 | K90: 0 | L90: 0 | M90: 0 | N90: 0 | O90: 0 | P90: 0 | Q90: 0 | R90: 0 | S90: 0 | T90: 0 | U90: 0 | V90: 0 | W90: 0 | X90: 0 | Y90: 0 | Z90: =V90-Y90 -> 0
